Workbook

Sheet Front Matter
A1: Statement of Work (eSOW/Hardware)
A2: JLR-TMP-557249 Issue Level 5.1 | H2: Revision | I2: {=LOOKUP(2,1/(A108:A118<>""),A108:A118)} -> 2 | J2: {=LOOKUP(2,1/(B108:B118<>""),B108:B118)} -> Third Submission
A4: RECORDS MANAGEMENT
A5: TITLE: | B5: Engineering Statement of Work | E5: RETENTION No: | G5: CP1-001 | I5: OWNER: | J5: Marcus Penn
A6: SECURITY: | B6: CONFIDENTIAL | E6: RECORD TYPE: | G6: OFFICIAL | I6: AUTHOR: | J6: Phil MacRae
A7: This Statement of Work shall be used to define the project and technical requirements for any given sourcing project and to support the Global Sourcing Process requirements at Jaguar Land Rover. This document is the authoritative document for all engineering, technical and software requirements. Requirements defined in any other Supplemental Statement of Work (referred to as sow hereinafter) documents shall not supersede the content of this Statement of Work unless stated otherwise.
A8: Document Title: | C8: L463 30MY Injection Moulded PANELS | G8: Supplier Category: | I8: Make to Print
A9: Centre of Competence: | C9: Body Engineering | G9: Vehicle Platform: | I9: MLA
A10: Squad / Chapter: | C10: Cabin | G10: Vehicle Line / Name: | I10: L463
A11: Job #1 Date | C11: 47126 | G11: Model Year: | I11: 30MY
A12: Supplier Master Code: | G12: Supplier Name:
A14: Lead Engineer: | C14: Marton Minda | E14: CDSID: | F14: mminda1 | G14: GSPid Code: | I14: IN_10322
A15: Group Leader: | C15: Marek Pyka | E15: CDSID: | F15: mpyka | G15: Commodity Plan: | I15: L463 30MY IM PANELS
A16: Module Lead: | C16: Mark Croucher | E16: CDSID: | F16: mcrouch7 | G16: Commodity Plan Code: | I16: P-0008384
A17: Strategic Buyer: | C17: Lauren Spensley | E17: CDSID: | F17: lspensl1 | G17: Component / System: | I17: Floor Coverings
A18: Service Lead: | C18: Mark Hardy | E18: CDSID: | F18: mhardy28 | G18: CPSCII Code: | I18: 010501
A21: SIGNATURES BLOCK
A22: Jaguar Land Rover Lead Engineer:
A23: Name: | B23: =C14 -> Marton Minda | D23: CDSID: | E23: =F14 -> mminda1 | F23: DATE: | H23: SIGNED:
A26: Jaguar Land Rover Module Leader:
A27: Name: | B27: =C16 -> Mark Croucher | D27: CDSID: | E27: =F16 -> mcrouch7 | F27: DATE: | H27: SIGNED:
A30: Authorising Service Signatory: *This signatory is mandatory. Contact Mark Hardy (mhardy28) for direction and guidance.
A31: Name: | B31: =C18 -> Mark Hardy | D31: CDSID: | E31: =F18 -> mhardy28 | F31: DATE: | H31: SIGNED:
A34: Supplier Representing Engineer:
A35: Name: | D35: ID No: | F35: DATE: | H35: SIGNED:
A41: Record of Changes to JLR-TMP-557249 Template
A42: This section contains a detailed list of all changes to the template. The use of this section is reserved for use by the Content Author and the Content Owner as defined in JLR Way in accordance with the Statement of Work (eSOW/Hardware) JLR-TMP-557249 operational template. This section must not be changed or edited by any signature of the Statement of Work.
A43: ISSUE LEVEL | B43: ISSUE CHANGE | C43: CHANGE TYPE | D43: LOCATION TAB / APPENDIX | F43: DESCRIPTION
A44: 3.0 | B44: MAJOR | C44: N/A | D44: ALL | F44: The Statement of Work has been overhauled, 100% content revision.
A45: 3.1 | B45: MINOR | C45: NEW | D45: ALL | F45: Sticky Notes added to section titles for guidance and clarity of instruction. Not visible to supplier when printed to .pdf format.
C46: NEW | D46: ELECTRICAL REQUIREMENTS | F46: Added Cyber Security Section.
A47: 3.2 | B47: MINOR | C47: CHANGE | D47: FRONT MATTER | F47: Improvements to Warranty Terms and Conditions Section.
C48: CHANGE | D48: FRONT MATTER | F48: Changes to 3DX License Requirements within Core Applications Section.
A49: 3.3 | B49: MINOR | C49: NEW | D49: APPENDIX G | F49: New Appendix added (H) for Semiconductor sourcing requirements.
C50: CHANGE | D50: HARDWARE / CAD | F50: Hardware Requirements Tab updated to include Hardware technical requirements and all CAD/CAE requirements.
C51: CHANGE | D51: ELECTRICAL REQUIREMENTS | F51: Revised to only define Cyber Security, Electrical Connectors and Bespoke requirements. Other information captured in Tab Technical Requirements.
A52: 3.4 | B52: MINOR | C52: CHANGE | D52: FRONT MATTER | F52: Official Records Statement and Retention Code update to reflect correct JLR Official Records Policy.
C53: DELETED | D53: FRONT MATTER | F53: Hyperlinks to sources outside of the Statement of Work deleted due to problems with access needs, site security and excel.
A54: 3.5 | B54: MINOR | C54: NEW | D54: FRONT MATTER | F54: Flash Page replaced with new version; directly Infront of Signature block on Page 1.
C55: NEW | D55: FRONT MATTER | F55: Reference changed in Parts Development and Validation. Prototype Part Governance Process changed from JLR-PRD-557143 to JLR-PRD-557806.
C56: CHANGE | D56: ALL | F56: Document JLR-TMP-557249 Title changed from 'Engineering Statement of Work (eSOW)' or 'eSOW 'to Statement of Work (eSOW/Hardware).
C57: DELETED | D57: READ ME THEN DELETE ME | F57: READ ME THEN DELETE ME guidance tab or engineers deleted and replaced with Statement of Work - Responsibilities and Operating Procedure JLR-PRD-570407.
A58: 3.6 | B58: MINOR | C58: NEW | D58: CYBER SEC. REQUIREMENTS | F58: New Tab created for Cyber Security Requirements
C59: NEW | D59: SERVICE REQUIREMENTS | F59: New Tab created for Service Requirements
C60: CHANGE | D60: ELECTRICAL REQUIREMENTS | F60: Cyber Security information removed; moved to Cyber Security Requirements Tab
A61: 3.7 | B61: MINOR | C61: NEW | D61: APPENDIX K | F61: New Appendix added (K) for Software Sourcing.
C62: CHANGE | D62: SERVICE REQUIREMENTS | F62: Update to text and instructions
A63: 3.8 | B63: MINOR | C63: NEW | D63: FRONT MATTER | F63: New Section added; Record of Changes to Template JLR-557249.
C64: NEW | D64: APPENDIX J | F64: New Appendix added (J) for Injection Moulded Plastics.
C65: NEW | D65: APPENDIX L | F65: New Appendix added (L) for Door Trim Sourcing Requirements.
C66: NEW | D66: FRONT MATTER | F66: New Supplier Category for ESP_Door Trim Teams. Affects Appendix A only.
C67: NEW | D67: FRONT MATTER | F67: Supplier Master Code and Supplier Name re-added to Front Matter Page 1.
C68: CHANGE | D68: ALL | F68: All references of 'eSOW' changed to 'Statement of Work'.
C69: CHANGE | D69: APPENDIX A | F69: RASIC descriptions auto-populated by selecting supplier category in Front Matter. Bespoke RASICs created for dedicated CoCs (i.e.. Door Trim).
C70: CHANGE | D70: ENVIROMENTAL REQUIREMENTS | F70: Removed incorrect references to 'Table 5.' Changed to correct internal reference ERR.9 and ERR 1. respectively.
C71: CHANGE | D71: APPENDIX D | F71: Name of Appendix changed from "Parts Lists" to "Parts and Materials"
C72: CHANGE | D72: APPENDIX D | F72: New section added for material information to be included with the part. Additional disclaimer for materials added to introduction section.
A73: ISSUE LEVEL | B73: ISSUE CHANGE | C73: CHANGE TYPE | D73: LOCATION TAB / APPENDIX | F73: DESCRIPTION
A74: 3.9 | B74: MINOR | C74: NEW | D74: (M) PROJECT MANAGEMENT | F74: New Section for Magna Project Management sourcing only
C75: NEW | D75: (M) Appendix Ai. L2 RASIC | F75: New Level 2 RASIC Tab specifically for Magna Projects
C76: NEW | D76: (M) Appendix Aii. L3 RASIC | F76: New Level 3 RASIC Tab specifically for Magna FSS Projects
C77: NEW | D77: SUPPLIER CATEGORY | F77: Category ESP_MAGNA_LEVEL_01 added
C78: CHANGE | D78: APPENDIX D | F78: Added Cost Pack Templates to Appendix D
A79: 4.0 | B79: MAJOR | C79: NEW | D79: SUPPLY CHAIN TRANSPARENCY | F79: New section for Supplier Transparency and Management
C80: NEW | D80: Front Matter | F80: New section relating to Change Management for Costs Post SCPA (Page 6)
C81: CHANGE | D81: APPENDIX J | F81: Improvements to wording for Appendix J. Removed allowance for supplier to use alternatives source files as deliverables to JLR.
A82: 4.1 | B82: MINOR | C82: CHANGE | D82: ENVIRONMENTAL REQUIREMENTS | F82: Added section ERR 11b referring to Per and Poly Fluorinated Substances (PFAS)
D83: ENVIRONMENTAL REQUIREMENTS | F83: Change to ERR 12 Frequently Asked Questions; - What is Part Marking?; Changes to rules on ISO 1043 applicable sections - Why is the RSMS Req. Important; addition of reference to STJLR.999.9999 - How do I report declarable substances; removal of reference to STJLR.99.9999 and changed to www.GADSL.org
C84: CHANGE | D84: ELECTRICAL REQUIREMENTS | F84: Complete rewrite of section EER.1 Electrical Connectors
A85: 4.2 | B85: MINOR CHANGE | C85: MINOR CHANGE | D85: METADATA OF THE DOCUMENT | F85: The authorship of the document has been transferred to ayeoman1 the ownership of the document has been transferred to agierhar
A86: 4.3 | B86: MINOR CHANGE | C86: MINOR CHANGE | D86: METADATA OF THE DOCUMENT | F86: Failures on issue level number corrected
A87: 4.4 | B87: - | C87: - | D87: - | F87: Changes not captured by previous owners of the documents
A88: 4.5 | B88: MINOR CHANGE | C88: MINOR CHANGE | D88: FRONT MATTER | F88: Line 168 - Change Mgmt. relating to cost post SCPA- update to ED&T rate information. Removed content and covered by NEW ED&T policy process - JLR-HTG-586067
B89: MINOR CHANGE | C89: MINOR CHANGE | D89: FRONT MATTER | F89: Line 166 - Engineering Design & Testing (ED&T) information update to align with new policy JLR-HTG-586067
B90: MINOR CHANGE | C90: MINOR CHANGE | D90: APPENDIX K | F90: Line 9 - APX.K.2 working change to incorporate SESOW template reference JLR-TMP-569740
B91: MINOR CHANGE | C91: MINOR CHANGE | D91: ENVIRONMENTAL REQ. | F91: line 2 removed reference WCR as no longer valid.
B92: MINOR CHANGE | C92: MINOR CHANGE | D92: CYBER SEC. REQUIREMENTS | F92: Line 10 added in STN-575210 (mandatory)
A93: 4.6 | B93: MINOR CHANGE | C93: MINOR CHANGE | D93: REMOVED DEAD LINK | F93: PURPOSE OF THE TEMPLATE (NOT ACTUALLY THE TEMPLATE)
A94: 4.7 | B94: MINOR CHANGE | C94: MINOR CHANGE | D94: UPDATED LINE 94 | F94: UPATED LINE 94 WITH CORRECT 4.7 VERSION & TO UPDATE THE TITLE LEVEL TIDY UP
A95: 4.8 | B95: MINOR CHANGE | C95: MINOR CHANGE | D95: UPDATED ALL PAGES TO 4.8 | F95: 4.4 WAS LEFT ON SOME PAGES NOT UPDATED - GENERAL TIDY UP
A96: 4.9 | B96: MAJOR CHANGE | C96: MINOR CHANGE | D96: 3 MAGNA TABS | F96: REMOVE ALL MAGNA CONTENT TABS (AGREED 7/3/25 DURING CONSULTATION
B97: MINOR CHANGE | C97: MINOR CHANGE | D97: ENVIRONMENTAL REQ | F97: ESOW ENVIRONMENTAL REQ. TAB TO REFLECT ENGINEERING REQUIREMENTS FOR LATEST VERSION OF STJLR 51.5270 (LINE 62
B98: MINOR CHANGE | C98: MINOR CHANGE | D98: ENVIRONMENTAL REQ | F98: UPDATE BY TAB OWNERS TO ENHANCE INFORMATION (ENSURING CLEARER STATEMENTS) LINES 15/16/25/26/45/46/59
B99: MINOR CHANGE | C99: MINOR CHANGE | D99: SERVICE REQUIREMENTS | F99: TURNED TAB TO RED TO ENSURE IT IS CONSIDERED AS MANDATORY CONSIDERATION REQUIREMENT
B100: MINOR CHANGE | C100: MINOR CHANGE | D100: CYBER SEC. REQUIREMENTS | F100: UPDATED LINES 2 TO INCORPORATE ENHANCEMENT TO INCLUDE CSMS JLR WAY PROCESS
B101: MINOR CHANGE | C101: MINOR CHANGE | D101: REF TO CP1-001 CORPORATE RETENTION UPDATE | F101: UPDATED TO REFLECT THE NEW CORPORATE RETENTION REFERENCE/DOCUMENT
A102: 5.1 | B102: minor | C102: MINOR CHANGE | D102: update to rev level only to align with JLR way | F102: update to rev level only to align with JLR way - added previously and JLR way misaligned with document
A103: 5.2 | B103: minor | C103: MINOR CHANGE | D103: spelling updates | F103: updates to all spellings within the document
A104: 5.3 | B104: minor | C104: MINOR CHANGE | D104: spelling updates | F104: updates for all tabs spelling issues
A106: FM.4 Record of Statement of Work Revisions
A107: REVISION | B107: SUBMISSION | D107: DESCRIPTION OF CHANGES | I107: LE | J107: GL | K107: DATE
A108: 0 | B108: First Submission | D108: N/A | I108: amitroi | J108: =E27 -> mcrouch7 | K108: =G23 -> 0
A109: 1 | B109: Second Submission | D109: IT-0023 STRESS CRACKING FOR PLASTICS added to Technical Requirements tab
A110: 2 | B110: Third Submission | D110: Constructoin changed to Grained and Injection moulded ABS Requirements for wrapped parts and foils removed Requirements for unpainted plastics added Timings updated to reflect current VPF
A120: FM.5 Supplier Category
A121: The supplier category defines how the supplier will work with Jaguar Land Rover and their design input and responsibility. This selection will affect which Core Applications and RASIC requirements are applicable.
A122: SUPPLIER CATEGORY | E122: SHORT DESCRIPTION / USE CASE
A123: Engineering Service Provider | E123: General classification for suppliers not defined within an PSC Category
A124: Full System Provider (CSS/Module Level) | E124: When the Supplier LEADS the engineering requirement
A125: Assembly / Component Provider | E125: When the Supplier LEADS the engineering requirement
...

Sheet DATA_NEW
A1: SUPPLIER CATEGORIES | I1: LOCATIONS | M1: SKILLS | O1: REVISION | P1: SUBMISSION
A2: Engineering Service Provider | I2: NOT APPLICABLE | M2: 3D Experience | O2: 1 | P2: Second Submission
A3: Full System Provider | I3: BRAZIL | M3: ACDS | O3: 2 | P3: Third Submission
A4: Assembly or Component Provider | I4: BROWNS LANE | M4: Agile | O4: 3 | P4: Fourth Submission
A5: Consultancy Component Provider | I5: CASTLE BROMWICH | M5: Agile QBR management process | O5: 4 | P5: Fifth Submission
A6: Make to Print | I6: CHINA | M6: AIMS - Process Awareness, Resolution | O6: 5 | P6: Sixth Submission
A7: ESP_DOOR TRIM | I7: EMC | M7: AIMS2 | O7: 6 | P7: Seventh Submission
I8: GAYDON | M8: Bill of Material | O8: 7 | P8: Eighth Submission
A9: CORE APPLICATIONS | I9: GRAZ | M9: Business Objects 4.2 | O9: 8 | P9: Ninth Submission
A10: APP | B10: ESI | C10: ESP | D10: FSP | E10: ASSY COM | F10: CONSULT | G10: MTP | H10: ESP_DOOR TRIM | I10: HALEWOOD | M10: C/C++ | O10: 9 | P10: Tenth Submission
A11: 3DX | B11: MANDATORY | C11: MANDATORY | D11: MANDATORY | E11: MANDATORY | F11: MANDATORY | G11: MANDATORY | H11: MANDATORY | I11: INDIA (PUNE) | M11: CAD | O11: 10 | P11: Eleventh Submission
A12: AIMS2 | B12: MANDATORY | C12: MANDATORY | D12: MANDATORY | E12: MANDATORY | F12: MANDATORY | G12: MANDATORY | H12: MANDATORY | I12: OXFORD ROAD | M12: CAE
A13: eAPQP | B13: NOT APPLIC. | C13: NOT APPLIC. | D13: MANDATORY | E13: MANDATORY | F13: MANDATORY | G13: MANDATORY | H13: MANDATORY | I13: SLOVAKIA (NITRA) | M13: CAS / CAM | O13: EMC DATA
A14: EnerjyHub | B14: MANDATORY | C14: MANDATORY | D14: MANDATORY | E14: MANDATORY | F14: MANDATORY | G14: MANDATORY | H14: MANDATORY | I14: SOLIHULL | M14: Catia V5 | O14: COMM. TYPE
A15: ePSW | B15: NOT APPLIC. | C15: NOT APPLIC. | D15: MANDATORY | E15: MANDATORY | F15: MANDATORY | G15: MANDATORY | H15: MANDATORY | I15: WHITLEY | M15: Catia V6 | O15: COMPONENT
A16: RMDV2 | B16: MANDATORY | C16: MANDATORY | D16: MANDATORY | E16: NOT APPLIC. | F16: NOT APPLIC. | G16: NOT APPLIC. | H16: NOT APPLIC. | M16: CCDS | O16: SUB-SYSTEM
A17: JIRA | B17: MANDATORY | C17: MANDATORY | D17: MANDATORY | E17: MANDATORY | F17: MANDATORY | G17: MANDATORY | H17: MANDATORY | M17: Change Decision Forum/ Scope Control | O17: DESIGN STAT.
A18: Confleunce | B18: MANDATORY | C18: MANDATORY | D18: MANDATORY | E18: MANDATORY | F18: MANDATORY | G18: MANDATORY | H18: MANDATORY | M18: Clipboards | O18: NEW
M19: Commodity Strategy L1 & L2 | O19: CARRY OVER
A20: APPLIC TABLE | D20: CAD CAE | E20: ESI | F20: ESP | G20: FSP | H20: ASSY | I20: CONSULT | J20: MTP | M20: Communication & Presentation Skills | O20: COMBO
A21: YES | D21: JLR-Q1 | M21: Confluence | O21: CARRY OVER w/CHANGE
A22: NO | D22: JLR-Q2 | M22: Current Veh. - Quality Metrics & Issue Mgmt
A23: Y | D23: JLR-Q3 | M23: Customer Feature change governance | O23: EMC_1.1 | Q23: ACCESS PORTAL
A24: N | D24: SUP-Q1 | M24: DTC's / Warning messages | O24: EMC_1.2 | Q24: DASSAULT 3D EXPERIENCE
A25: APPLICABLE | D25: SUP-Q2 | M25: eAPQP | O25: EMC_1.3 | Q25: Majenta EnerjyHub
A26: NOT APPLICABLE | D26: SUP-Q3 | M26: EBOM | O26: EMC_1.4 | Q26: OPTION 3
A27: REQUIRED | M27: EDS Clearplan | O27: EMC_1.5 | Q27: OPTION 4
A28: NOT REQUIRED | D28: RESPONSIBILITY | H28: NEW | J28: STANDARDS | M28: eFDVS | O28: EMC_1.6
A29: MANDATORY | D29: JAGUAR LAND ROVER | H29: CARRY OVER | J29: INDUSTRY | M29: EnerjyHub | O29: EMC_1.7
A30: NOT APPLICABLE | D30: SUPPLIER | H30: NTEI | J30: JLR | M30: Engineering Standards | O30: EMC_1.8
D31: TIER 1 SUPPLIER | H31: N/A | M31: ePSW | O31: EMC_1.9
D32: TIER 2 SUPPLIER | J32: TYPE | M32: Evidence Base Engineering Release (EBER) | O32: EMC_1.10
A33: Jaguar Land Rover Ltd | J33: HARDWARE | M33: Exalead (Developer) | O33: EMC_1.11
A34: Supplier | J34: CAD/CAE | M34: Exalead (End user) | O34: EMC_1.12
J35: ELECTRICAL | M35: Excel | O35: EMC_1.13
A36: Special Mandatory for Cyber | D36: CHAGE TYPE | J36: CYBER | M36: Feature code knowledge (ACE, rMFD) | O36: EMC_1.14
A37: MANDATORY SOFTWARE IN SCOPE | D37: NEW | J37: SOFTWARE | M37: Features & System Delivery Process (SSCD) | O37: EMC_1.15
A38: NOT APPLICABLE SOFTWARE NOT IN SCOPE | D38: CHANGE | J38: MISC. | M38: FMEA
D39: DELETED | M39: Gateway Papers
M40: Git | O40: Partner TAB ALIGNMEN
M41: Google Cloud Services | O41: ALIGNED
M42: Harlequins | O42: NOT ALIGNED
M43: IBM CLM application: RQM
M44: IBM CLM application: RTC RMDV | O44: INCREASE
M45: IBM CLM application: RTC SSCD | O45: DECREASE
M46: IBM DOORS Classic application: RMDV | O46: EQUAL
M47: IBM DOORS Classic application: SSCD
M48: Issue Management - Product & Process, New Model
M49: IVS releases
M50: Javascript
M51: JIRA
M52: JLR Engineering Standards
M53: JLR-Q-003 Attachment C-F
M54: Lean
M55: Lessons Learned Use and Capture
M56: Luigi
M57: Managing Programme Gateways to Approval
M58: Master Schedule
... M105: WERS +iCreate +PACN

Sheet Supply Chain Transparency
A1: Supply Chain Transparency Requirements
A2: JLR and the Supplier are expected to work under a bi-lateral agreement where JLR may request the supplier to provide visibility into supplier upstream supply chain(s) to ensure that both JLR and the supplier are working to accepted industry practice in key areas as defined below in section SCRT.1 Areas of Transparency. In some cases, the supplier may be requested to provide demonstrations and evidence of their ability to meet transparency requirement targets as defined below.
A4: SCTR.1 Areas of Transparency
A6: AREA | C6: REQUIREMENT | H6: TARGET
A7: HIGH RISK COMPONENTS | C7: To be completed by JLR Define a list of high risk components for the particular supplier | H7: To be completed by JLR Define the level of information / type of data and the method of exchange required to satisfy
A8: SUSTAINABILITY | C8: To be completed by JLR Define a list of sustainability requirements | H8: To be completed by JLR Define sustainability targets, including where applicable EU regulation or international standards.
A9: ETHICAL PRACTICES | C9: To be completed by JLR Define a list of ethical practices or standards | H9: To be completed by JLR Define targets in accordance with local, nation or international guidelines or governance
A10: Spare | C10: For JLR Only Use this row to define additional transparency requirements.
A11: Spare | C11: For JLR Only Use this row to define additional transparency requirements.
A12: Spare | C12: For JLR Only Use this row to define additional transparency requirements.
A14: SCTR.2 Supply Chain Transparency Lead / Point of Contact
A15: JLR invites the supplier to nominate an individual, or department to act as a liaison between JLR and the supplier relating to all matters defined above. The nominated individual or department is not required to be defined as a technical expert in any area defined above, however is expected act in the best interest of transparency, openness, integrity and to continue the completion of all targets in the spirit of good supplier behaviour practices and open collaboration with JLR.
A17: Supplier Representing Transparency Point of Contact:
A18: Name: | D18: ID No: | F18: DATE: | H18: SIGNED:
E21: END OF SECTION

Sheet Environmental Req.
A1: Environmental and Recycling Requirements
A2: Suppliers of production materials, equipment, services and consumption goods play a vital part in the development and production of Jaguar Land Rover products. Therefore, all goods and services supplied to Jaguar Land Rover shall be aligned with the Jaguar Land Rover Environmental Requirements and any applicable legislation. Supplied parts and services shall comply with the environmental targets as detailed in the Sourcing and Commercial Programme Agreement (SCPA), Engineering Statements of Work, Advanced Product Quality Planning (APQP) Requirements and Guidelines, JLR Global Sustainability Web Guide – Supplier Environmental & Social Requirements, System or Vehicle Design Specifications and the program specific targets. All legislation must be fulfilled and complied with. Jaguar Land Rover requires all production and non-production suppliers with manufacturing facilities third party certify all facilities to ISO 14001. Parts must comply with the environmental targets as detailed below. All engineering standards such as STJLRs shall be made available to the supplier through the Enerjyhub system.
A4: ERR.1 Restricted Substances and Materials of Concern
A5: REQUIREMENT | C5: All parts shall comply with the Restricted Substance Management Standard (RSMS) STJLR.99.9999. The supplier shall fulfil and comply with the reporting requirements in the Prohibited and Declarable Substances table in STJLR.99.9999. The Supplier is responsible to make sure that all their parts conform to the End-Of-Life Vehicles (ELV) legislation. The supplier shall support JLR or international material phase-out strategies.
A6: TIMING | C6: Where required, the supplier shall submit a compliance plan 30 days before the most up to date, and understood PRDJ date through the RMDV access portal. Full International Material Data System (IMDS) data is required prior to CSO for all non-tuneable parts and VSSO for all tuneable and non-tuneable parts. Refer to the IMDS Submission Guide For Suppliers to Jaguar Land Rover. This guide is located in Enerjyhub.
A7: TARGET | C7: All parts must comply with the RSMS standard STJLR.99.9999. Non exempted components containing Lead, Mercury, Cadmium and Hexavalent Chromium are prohibited. Suppliers shall identify lead in solder application codes according to Appendix G. Lead-Free Solder Checklist to enable compliance with Annex II, 2000/53/EC. The Supplier shall comply with STJLR.50.5353. Companies who distribute brominated flame retardants and the users of these retardants are advised to subscribe to the VECAP programme (www.vecap.info) to reduce emissions into the environment. Tier 1 suppliers to Jaguar Land Rover shall cascade these requirements, rules and advisements to Tier 2 suppliers and all other affected suppliers.
A9: ERR.2 Vehicle Recyclability - Parts Reuse Restrictions
A10: REQUIREMENT | C10: Do not supply any re-used parts for production of vehicles which are prohibited in Annex V of Recyclability Type Approval Directive 2005/64/EC in its latest amended version.
A11: TIMING | C11: Before JOB #1.
A12: TARGET | C12: To Comply with Annex V of the Recyclability Type Approval Directive 2005/64/EC.
A14: ERR.3 Vehicle Recyclability - Design
A15: REQUIREMENT | C15: Increase the recyclable share of the vehicle that is economically viable. Promote the use of mono-material usage in components where possible, followed by use of mechanical fixings between materials to promote pre-shredding material separation and reduce contamination.
A16: TIMING | C16: For recyclability, refer to RSMS STJLR.99.9999 Section H, for IMDS reporting timing. For materials recyclability test case, parts must be assessed prior to EDJ to enable any material compatibility/ recyclability issues to be resolved.
A17: TARGET | C17: To support Vehicle Recyclability as measured by method (ISO 22628), required for whole vehicle type approval, material composition is to be reported via IMDS in accordance with RSMS requirements. Ref example parts in Table 4 that should be designed to be recyclable.
A18: ERR.4 Parts Marking
A19: REQUIREMENT | C19: All plastic and elastomeric parts shall be marked for recycling.
A20: TIMING | C20: To comply with the parts marking requirements of the End of Life Vehicle Directive 2000/53/EC, polymeric components exceeding 100 grams and elastomeric components exceeding 200 grams are required to be marked according to ISO 1043 Part 1 and Part 2, ISO 11469 or ISO 1629. The CAD shall include the polymeric parts marking symbols and identify their correct location on the part before PRDJ.
A21: TARGET | C21: All plastic & elastomeric parts to be marked as identified. Refer to ISO standards: ISO 1043-1, 1043-2 and 11469 for plastics and ISO 1629 for rubber materials. Above 100 grams for plastics and above 200 grams for elastomers. The parts marking symbol and the parts marking check box shall be accurately recorded in the IMDS submission for the part.
A23: ERR.5 Recycled Materials
A24: REQUIREMENT | C24: The Supplier shall identify opportunities to incorporate post-consumer recycled (PCR) content(closed loop prioritised) and post-industrial recycled (PIR) / pre-consumer recycled material content into appropriate components. For new programmes from 29MY onwards, all parts must comply with the requirements defined in STJLR.51.5270 V3 Use of Recycled Material in Polymers, Aluminium, Steel and Glass. Programme's prior to this, will comply to STJLR 51.5270 V2. Any MCF/unit programme's where by opportunities to use recycled content are available, these should be explored. Potential applications should be identified and shall be pursued and evaluated with the relevant JLR Materials Engineer / JLR Sustainability Programme Integration Lead, in order to comply with vehicle targets. Home scrap recycling is not accepted as recycled content. Refer to ISO 14021.
A25: TIMING | C25: Supplier to notify JLR Lead Engineer of any issues in meeting the requirement before FR/EDC. Component specification/drawing to include recycled content at EDC, final confirmation from supplier and entry into IMDS with confirmed recycled content included as evidence via RMDV by CSO.
A26: TARGET | C26: New programme's from 29MY onwards shall meet the respective CPSC level recycled content target for specified material families as per STJLR 51.5270 V3 or exception agreed by JLR Materials Engineering & Product Sustainability. Parts that already contain recycled content should continue to be specified in the same manner and aim to increase the recycled content % and/or include PCR content where possible as specified in STJLR.51.5270 V3. Any programmes prior to 29MY shall target a minimum 20% recycled content for all polymer material, if not, exception to be agreed by JLR Materials Engineering and Product Sustainability. Example target parts for recycled polymer content are listed in section ERR.11 below. Parts that already contain recycled content should continue to be specified in the same manner and increased by 10% where possible as specified in STJLR.51.5270 V2. Any MCF or unit programmes which does not have a programme level target, but does contain opportunity to introduce recycled content should be explored. At the request of Jaguar Land Rover, the Supplier shall provide evidence (via RMDV and IMDS, using the recycled tab) of recycled material content.
A28: ERR.6 Vehicle Interior Environment Quality (VIEQ)
A29: REQUIREMENT | C29: To comply with Volatile Organic compounds (VOC) emission targets within the interior cabin, the supplier shall use low VOC emission materials TÜV TOXPROOF. The Supplier shall, where appropriate, use materials within vehicle interior cabin that do not have any adverse impacts to health in accordance with the requirements in STJLR.51.5232. The supplier shall test and record results for air filtration components in accordance with TÜV TOXPROOF Criteria Catalogue, 2 PIG S 0051.
A30: TIMING | C30: The supplier shall notify the JLR Lead Engineer and relevant Materials Engineer of any issues or obstacle that will, or may prevent the supplier or Jaguar Land Rover to meet the requirements defined in the standard before FR, Final material testing and sign off before PRC, Final component testing and sign off before VSSO. The supplier shall record issues or obstacles via RMDV or by any other approved collaboration means agreed in the Project Management Section of this Statement of Work. The supplier shall support Jaguar Land Rover, when requested, to investigate components if required to meet vehicle level requirement. Skin contact materials to be tested by TUV Rheinland at PRDJ.
A31: TARGET | C31: Materials shall comply with the requirements defined in STJLR.51.5229. Applicable components shall comply with the requirements defined in STJLR.01.5202. “Skin Contact” Materials to comply with the requirements defined in STJLR.51.5232., and to be tested by TUV Rheinland and approved to their TOXPROOF Criteria catalogue.
A33: ERR.7 List of Affected Commodities
A34: REQUIREMENT | G34: AFFECTED COMMODITY
A35: Restricted Substance Management Standard | G35: All
A36: Recyclability | G36: All commodities except for parts listed in "Example Parts Identified For Recycling" Section below.
A37: Parts Marking | G37: All non-metallic parts as identified in ISO standards ISO 1043-1, 1043-2 and 11469 for plastics and ISO 1629 for rubber materials (plastics above 100 grams, elastomers above 200 grams).
A38: Recycled Materials (PCR, PIR) | G38: All components that contain polymers.
A39: Vehicle Interior Environment Quality (VIEQ) | G39: All interior parts, exterior door handles and tailgate.
A41: ERR.8 Parts Identified for Pre-Treatment
A42: Plans are required for the parts defined below to make sure that Jaguar Land Rover vehicles comply with ELV dismantling requirements.
A43: COMMODITY | G43: ACTION
A44: Parts listed in the EU ELV directive Annex I / II: - All batteries - All electronic circuit boards and other electronic components if a vehicle threshold of 60g of lead in solder is exceeded - Tyres - Electrical components which contain lead in solder or in a glass or ceramic matrix compound except glass in bulbs and glaze of spark plugs if a vehicle threshold of 60g lead is exceeded - Supercapacitors / Ultracapacitors / Electrochemical double-layer capacitors (EDLCs) | G44: Design for Disassembly actions (easy access, safe and easy removal).
A45: Pyrotechnic systems | G45: Minimum time to deploy / neutralise all devices through use of ECU or OBD connected tooling, easy access to the ECU, provision of dismantling manuals is required. New dismantling manuals are required where changes to the dismantling processes are made with MY updates.
A46: All fluid containing components | G46: Fluid removal marking, easy access. Design of component must ensure all fluid can be removed within 20 mins using gravity or suction methods.
A47: Electronics | G47: Efficient soldering techniques should be employed to reduce lead content in components. Use energy efficient components. Refer to Appendix G. Lead Free Solder Checklist for more information.
A48: Displays and Lighting | G48: Must be mercury-free solutions.
A55: ERR.9 Example Parts Identified for Recycling
A57: EXTERIOR TRIM | D57: INTERIOR TRIM | G57: POWER TRAIN | J57: ELECTRICAL
A58: Air Inlet Finishers Bumper Covers, Brackets Bumper Finishers Front Trunk Moulding Glass Roof Finisher Sill Finishers Tailgate Finishers Tow Eye Finisher Under Trays Wheel Arch Closure Post Finishers Wheel Arch Liner, Finisher | D58: Seat belts Dashboard Finisher Door Bins Door Casing Glove, Cubby Box & Lid Load Space Trim Lower Post Finishers Seat Cushions / Squabs Seat Finisher Door Frame Finisher Steering Column Cowl | G58: Emissions Catalysts Engine Finishers Engine Top Cover Radiator & Fan Housing Radiator Finisher Air Cleaner Lid, Housing | J58: Battery Tray Fuse Box Lid
A59: All other easily accessible polymeric components in excess of 250g
A61: ERR.10 Parts Identified for Recycled Content
A62: All applications containing recycled content must conform to the following requirements: 1. Resulting weight is equal to or less than currently used material solution. 2. For programmes to which STJLR 51.5270 V2 is applicable - Parts that already contain recycled content should continue to be specified in the same manner and increased where possible by 10%. For programmes to which STJLR 51.5270 V3 is applicable - Parts that already contain recycled content should continue to be specified in the same manner and aim to increase the recycled content % and/or include PCR content where possible 3. Evidence of additional recycled content shall be supplied. 4. No smell or interior emission issues occur. 5. Sustainable supply is ensured. 6. Environmental impact (measured in GWP (Global Warming Potential) CO2eq) is not adversely affected. Target parts for recycled polymer content are listed in "Example applications where recycled polymers are used" Section below.
A64: ERR.11 Example Applications Where Recycled Polymers are Currently Used
A65: BODY EXTERIOR | D65: INTERIOR TRIM | H65: POWERTRAIN / CHASSIS / ELECTRICAL
A66: Upstream ducts Wheel arch liners Bumper brackets Leafscreen water trough Undertrays | D66: IP/Centre Console carrier NVH pads Carpets (load space compartment, side trim, main floor, floor mats) Seat brackets Load floor Parcel Shelf Floor brackets Interior face fabric Trunk trim side mouldings (B-Surface) Seat backs (B-Surface) Speaker brackets, subwoofer housing | H66: Air ducting and distribution channels Fuse box cover Air cleaner box and lid Auxiliary air cooler ducts Radiator fan shroud Engine Cover
A68: ERR.11b Per and Poly Fluorinated Substances (PFAS), including fluoropolymers and fluoroelastomers
A69: REQUIREMENT | C69: 1. PFAS containing materials and components shall not be used, where the design specifications can be met with technically and economically feasible alternatives. 2. Where PFAS containing materials and components must be used, they shall be identified in the quotation, and the technical and economic implications of substitution shall be identified.
A70: TARGET | C70: PFAS free components, compliant with EU and North American restriction proposals.
A71: TIMING | C71: Data shall be provided with the quotation.
A72: ERR.12 Frequently Asked Questions
A73: This section answers the questions "What is the requirement about?", "What happens if the requirement will not be met?", "Are compromises possible?", "Where is this requirement going beyond legal requirements for Europe and why?" for the CPA requirements: - Restricted Substances and Materials of Concern. - Vehicle Recyclability and Parts Marking. - Recycled/Non-Virgin Materials. - Vehicle Interior Environment Quality (VIEQ).
A75: RESTRICTED SUBSTANCES AND MATERIALS OF CONCERN
A76: Why is the RSMS requirement important? | C76: The use of prohibited substances as listed in RSMS (within STJLR.99.9999) is in conflict with legal compliance. Some requirements seem to go beyond legislation. However, the RSMS is a corporate standard that ensures that Jaguar Land Rover Limited can also cost-effectively comply with legislation. RSMS entries are the result of a thorough impact analysis.
A77: What does 100% compliant to RSMS mean? | C77: All requirements are detailed in the RSMS standard. The main requirements include the reporting of all materials and substances in IMDS. In addition, RSMS lists those substances that are not allowed to be supplied to Jaguar Land Rover Limited (prohibited), or those substances that shall be minimized due to for example up-coming legislation (some of the declarable substance) or those substances that need to be reported for other reasons.
A78: What happens if the RSMS requirements are not met? | C78: There are fines to be paid (magnitude is different for different markets) and re-calls may be necessary. In addition, image issues may occur if an environmental non-governmental organization (NGO) detects non-compliance.
A79: How do I report declarable substances? | C79: All of the substances listed in the latest available version of the Global Automotive Declarable Substances List (www.gadsl.org) must be reported in the International Material Data System (IMDS www.mdsystem.com). IMDS reports are required for each part number. Please send part data to Jaguar Land Rover Limited, IMDS account 297.
A81: VEHICLE RECYCLABILITY AND PARTS MARKING
A82: Why are these requirements important? | C82: The EU ELV directive (2000/53/EC) mandates a minimum vehicle recyclability rate of 85% and parts marking. In addition, it states that the automotive industry has to meet all or a significant part of the end-of-life costs. Vehicle type approval is linked to this vehicle recyclability. The listed requirements ensure that a type approval for the vehicle can be done, the vehicles are legally compliant and that end-of-life costs are minimized.
A83: What is recyclability? | C83: Complete Vehicle Recyclability is an indication of the extent to which a vehicle can be recycled at the end of its life. It is measured according to ISO 22628 on a vehicle level.
A84: What is part marking? | C84: Part marking must be in accordance with the following ISO standards: ISO 1043 part 1 thru. 4 and 11469 for plastics and ISO 1629 for rubber materials reference in latest version of the CADJLR.02.02 section G. The use of ISO 18064 for the marking of thermoplastic rubber as defined in ISO 1043-1 is permitted. Compliance is mandatory for thermoplastics / thermosets above 100g and for elastomers above 200g, part of whole vehicle type approval.
A85: What happens if the requirement is not met? | C85: If recyclability cannot be demonstrated (e.g. due to missing data in IMDS), type approval of vehicles is affected. Part marking for polymers is also a legal requirement. For ELV costs, Jaguar Land Rover may ask for compensation if ELV disposal costs are incurred that are directly attributable to failure in delivering compliant components.
A86: Are compromises possible? | C86: Compromises for recyclability are only possible if the lower recyclability of one component can be compensated by another one that over achieves the vehicle targets.
A87: Frequently Asked Questions (continued.)
A89: RECYCLED MATERIALS
A90: Why are these requirements important? | C90: The increased usage of recycled materials is required by the European ELV directive and part of Jaguar Land Rover Limited Corporate Policy.
A91: What are recycled materials? | C91: The requirement is looking at non-metallic materials, in particular thermoplastics or other polymers. - Post-consumer materials are those that have passed through the hands of consumers. - Pre-consumer/Post-industrial materials are those that have at least been subjected to one additional process step and would otherwise require disposal, excludes home scrap recycling (e.g. direct re-granulation and re-feeding in the same facility). Material that is recovered within the same manufacturing process that generated it, shall not count towards recycled content. - Further definition can be found in ISO 14021 Recycled material content must be reported in IMDS.
A92: What are recyclable materials? | C92: Materials that can be recovered or diverted from the non-hazardous solid waste stream for the purpose of reuse, recycling or reclamation and a substantial portion of which is consistently used in the manufacture of products, which may otherwise be produced using raw or virgin materials.
A94: VEHICLE INTERIOR ENVIRONMENT QUALITY (VIEQ)
A95: Why are these requirements important? | C95: To protect the customer, meet the customer expectations and ensure legal compliance.
A96: What is Vehicle Interior Environment Quality (VIEQ)? | C96: Materials used in the construction of new vehicles affect the interior odour and fogging of the windscreen. Solvent based adhesives create issues with toluene and volatile organic compound (VOC) emissions, which are not permitted in certain markets. Certain dyes and surface materials need to be avoided as they are known to cause irritations to sensitized individuals and pollen, VOC and particulate matter (PM) ingress through the air conditioning needs to be minimized, as this is known to affect hay-fever sufferers. Sensitising substances, e.g. Natural Rubber Latex, Chromium VI and Nickel shall not be used for the vehicle interior, door handles etc. Smell or fogging issues are often linked with thermosets (phenol resin binders, polyurethane foams), elastomers (sulphur residue from vulcanization) and inefficient fuel tank sealing. The Restricted substance and vehicle interior requirements listed in Table 1 are designed to address these issues.
E111: END OF SECTION

Sheet Project Management
A1: Project Management
A3: SUPPLIER CATEGORY | E3: ='Front Matter'!I8 -> Make to Print
A4: This Section shall be used if the commodity to be sourced is a physical part, structure or system with no software or electrical parts. The Lead Engineer is responsible for the completion of all sections within this Statement of Work. Contact the relevant Buyer for volumes, Vehicle Programme Framework documents or other relevant project information.
A5: This section defines all information relating to the project management aspect of the sourcing project. Jaguar Land Rover shall provide the supplier with the most mature and relevant project and programme information applicable to the creation of a clear and concise Request For Quotation and receive a realistic and achievable quotation from a supplier.
A6: EPM.1 Vehicle Information
A7: Not all fields in this section may be applicable or mandatory for the sourcing requirements defined in this document, however it is recommended to complete as much information in this section for familiarisation, understanding and applicability. If any field in this section is not applicable, then enter (or select) "NOT APPLICABLE" in the respective field.
A8: CYCLE PLAN CODE | D8: VEHICLE NAME | G8: JOB #1 DATE | J8: PROGRAM SCALE
A9: Y9250 | D9: L463 | G9: 47098 | J9: 8 years
A11: MANUF. LOCATION | D11: LIFECYCLE TOTAL | G11: MANUF. LOCATION | J11: PEAK ANNUAL VOLUME
A12: Nitra | D12: 626000 | G12: Nitra | J12: 92000
B14: POWERTRAIN | G14: WHEELBASE
B15: CODE | D15: DESCRIPTION | G15: CODE | I15: DESCRIPTION
B16: - | D16: - | G16: - | I16: -
B18: CAB STYLE | G18: TRANSMISSION
B19: CODE | D19: DESCRIPTION | G19: CODE | I19: DESCRIPTION
B20: - | D20: - | G20: - | I20: -
B22: PROJECT LOCATIONS
B23: ASSEMBLY LOCATION | E23: PTO PLANT LOCATION | H23: PROTOTYPE BUILD LOCATION
B24: SLOVAKIA (NITRA) | E24: OXFORD ROAD | H24: OXFORD ROAD
A26: EPM.2 Programme Timings
A27: All programs must use and be aligned to PCDS V4 gateways, milestones, events and timelines. Where fixed dates are not available, the Lead Engineer shall apply estimated dates and provide updates to the supplier if there is a timing change.
A28: This section includes all relevant gateways and milestones in a given JLR Vehicle project. The JLR engineering shall include the relevant dates for each gateway or milestone to be used as a datum point for key supplier deliverables. Timelines and key date are required in order to fulfil the obligations of the seller in accordance with JLR-STN-19214 Global Terms and Conditions for Engineering Services, Section 3(c). The Jaguar Land Rover Lead Engineer is permitted to append a current Vehicle Program Framework (VPF) Document which outlines all relevant gateway and milestone dates, however it is recommended to complete the Timing Chart defined on the next page. Additional timing requirements can be included below in the Vehicle Programme Framework.
A29: EPM.3 Vehicle Programme Framework
A31: VEHICLE PROGRAMME FRAMEWORK
B32: CODE | C32: NAME | E32: TYPE | F32: DATE | G32: NOTES
A33: STRATEGY | B33: KO | C33: KICK OFF | E33: GATEWAY | F33: 45715
B34: PD | C34: PROG. DEFINITION | E34: GATEWAY | F34: 45729
B35: PS | C35: PROG. STRATEGY | E35: GATEWAY | F35: 45827
B36: PSC | C36: PROG. STRATEGY CONFIRMED | E36: GATEWAY | F36: 46007
A37: DELIVERY | B37: CC | C37: CONTRACT CHECKPOINT | E37: GATEWAY | F37: 46199
B38: FR | C38: FINANCIAL RELEASE | E38: GATEWAY | F38: 46311
B39: PR | C39: PRODUCTION RELEASE | E39: GATEWAY | F39: 46428
A40: LAUNCH | B40: PRC | C40: PRODUCTION RELEASE COMPLETION | E40: MILESTONE | F40: 46478
B41: LRR 1 | C41: VB READINESS | E41: MILESTONE | F41: 46541
B42: LRR 2 | C42: PLANT HANDOVER | E42: MILESTONE | F42: 46716
B43: CSO | C43: COMPONENT SIGN OFF | E43: MILESTONE | F43: 46730
B44: VSSO | C44: VEHICLE & SYSTEM SIGN OFF | E44: MILESTONE | F44: 46870
B45: LRR 3 | C45: PROCEED TO LAUNCH PRODUCTION | E45: GATEWAY | F45: 46884
B46: LRR 4 | C46: OPEN CUSTOMER SALEABLE ORDER CALL | E46: MILESTONE | F46: 47045
B47: FESO | C47: FINAL ENG. SIGN OFF | E47: MILESTONE | F47: 47010
B48: LRR 5 | C48: OK FOR JOB 1 | E48: MILESTONE | F48: 47066
B49: JOB 1 | C49: JOB 1 | E49: GATEWAY | F49: 47126
A51: EPM.4 Bespoke Timing Requirements
A52: Record timing dates or events that the supplier is shall achieve which DO NOT align to a JLR Gateway or Milestone.
A55: EPM.5 Skills and Competencies
A56: JLR shall define all skills and experience and a level of competence required for the completion of the sourcing project. The supplier is expected to review, understand and agree to all requirements listed in this section. Training programmes for tools and processes can be found in EnerjyHub.
A57: The supplier is expected provide human resources with the relevant experience and necessary skill level to support the sourcing project technical and project management requirements. The supplier shall assess their current resource capacity and provide a resource management plan for resource acquisition, or re-structuring, and the associated onboarding, training, sourcing project familiarisation and access requirements needed to meet the expected experience and skill levels needed for the sourcing project. Jaguar Land Rover is not responsible, nor expected to compensate the supplier for any work related to the acquisition, onboarding, training, sourcing project familiarisation, licenses or access rights required to support the sourcing project.
A58: SKILLS MATRIX
A59: SKILL / TOOL / PROCESS | D59: JLR EXPECTATION
A60: ePSW | D60: Access and be able to use the tool
A61: eAPQP | D61: Access and be able to use the tool
A62: Problem Solving (8D / PPS) | D62: Be able to present problem solving doucment in the form of 8Ds where required.
A63: EnerjyHub | D63: Access and be able to use the tool
A64: Processes - MX+ Data Service Provider | D64: Access and be able to use the tool
A65: 3D Experience | D65: Access and be able to read JLR Catia V6 files including annotations and drawing notes. APQP will be moved to 3D Experience.
A66: PCDS | D66: Understanding of JLR commodity plan gateways and timings
A67: JLR Engineering Standards | D67: Access to JLR engineering standards through Enerjyhub
A68: FMEA | D68: Supplier to own and develop the PFMEA
A69: Processes - PPAP | D69: Understanding and adherance to the JLR production part approval process
E75: END OF SECTION

Sheet Service Requirements
A1: Service Requirements
A2: This section contains the service requirements for the commodity that the supplier shall agree to. Jaguar Land Rover and the Supplier shall agree and understand that service requirements, including parts volume of parts, can change throughout the life of the product. Both parties shall communicate changes in writing in accordance with the Global Terms and Conditions for Engineering Services, JLR-STN-19214 and Global Terms and Conditions for Production Purchasing, JLR-STN-18499. The Lead Engineer must complete all fields with the guidance of the Service Commodity Lead, to ensure commodity-specific requirements are included where applicable. The Supplier must review the Jaguar Land Rover Aftermarket Parts and Accessories, JLR-EXP-570156. THIS SECTION IS MANDATORY. CONTACT MARK HARDY (MHARDY28) FOR DIRECTION TO THE SERVICE COMMODITY LEAD.
A4: SSR.1 General Service Requirements
A6: 1.1 Ease of Maintenance and Cost of Ownership
A7: Design all systems, components and levels of assembly to facilitate repairs identified within the Retailer Repair Procedures/Workshop Manual for ease of maintenance and/or repair at a competitive cost, and to meet programme serviceability cost of ownership (COO) targets. Where relevant, commodity must be compatible with existing consumables (e.g. oil grade, hydraulic fluid). There shall be no increase in PDI complexity or time.
A8: Notes and Bespoke Requirements (JLR Lead Engineer input only)
A9: Not Applicable
A11: 1.2 Serialization and As-Built Data
A12: Where applicable, provide serialization and as-built data for all applicable parts/systems in a format readily compatible with JLR systems. For commodities with key code functionality, ensure underlying algorithms are available to JLR lock database and demonstrate how these will be subsequently maintained.
A14: Notes and Bespoke Requirements (JLR Lead Engineer input only)
A15: Not Applicable
A17: 1.3 Repair and Replacement Procedures
... A39: Not Applicable
E41: END OF SECTION

Sheet Technical Requirements
A1: Technical Requirements
A2: This section contains the technical requirements and expectations for the commodity that the supplier shall agree to. This section contains high-level design information, commodity information, system design information and detailed technical requirements. Jaguar Land Rover may provide a Product Design Specification (PDS) in lieu of technical information in this section of the Statement of Work. A PDS is considered a Supporting Document to the Statement of Work and does not supersede or replace Statement of Work (JLR-TMP-557249). NOTE: REFER TO APPENDIX C. STANDARDS AND SUPPORTING DOCUMENTS FOR ALL ENGINEERING STANDARDS
A3: ETR.1 Product Definition Sheet
A4: Will Jaguar Land Rover issue a PDS to the supplier? | F4: YES | H4: Document Name
A6: ETR.2 Technical and System Information
A8: TECHNICAL OVERVIEW
A9: The parts contained within this eSOW are make to print floor access panel which provides access to an area of the fuel system, and provide a walkthrough floor for the 3rd row.
A11: SYSTEM OVERVIEW
A12: System interfaces: Main Floor Carpet, BIW
A14: SYSTEM CONTEXT
A15: The parts within this eSOW will interface and join to main floor carpet and BIW brackets.
A17: SYSTEM BEHAVIOURS
A18: Components shall be within tolerance to fit within the vehicle
A20: SYSTEM USE CASE
A21: Not Applicable
A22: ETR.3 Technical Targets and Attributes
A24: PANEL REF | B24: TECHNICAL ATTRIBUTE | E24: DESCRIPTION / TARGET / ATTRIBUTE | I24: CLASS. / CATEGORY / DELTA / SCORE
A25: AMS | B25: VTSO - AMS | E25: Not Applicable
A26: A1a | B26: Passive Safety | E26: Not Applicable
A27: A1b | B27: Perceived Quality | E27: Provide good percieved quality of part
A28: A1c | B28: Climate & Interior Air Quality | E28: Deliver parts within VOC limits and odor limits
A29: A1d | B29: Lighting | E29: Not Applicable
A30: A1e | B30: Sustainability | E30: Meet part recyclability requirement
A31: A2 | B31: Human Factors | E31: Not Applicable
A32: A3 | B32: Infotainment and Connectivity | E32: Not Applicable
A33: A4a | B33: Driving Dynamics | E33: Not Applicable
A34: A4b | B34: Brakes Engineering Attributes | E34: Not Applicable
A35: A4c | B35: Off Road & All Road Capability | E35: Not Applicable
A36: A5a | B36: Product Efficiency | E36: Not Applicable
... A50: VE | B50: Panel Owner | E50: Not Applicable
A51: ETR.4 Diagrams
A52: This section defines the system functional and Boundary Diagrams.
A53: FUNCTIONAL DIAGRAM
A56: BOUNDARY DIAGRAM
A58: ETR.5 Commodity Documents
A59: JLR, with support of the supplier, shall specify all drawings, documents and other technical information that the supplier is required to deliver in the table below.
A60: CoC / COMMODITY DOCUMENTS | D60: APPLICABLE | E60: LEVEL | F60: REVISION | G60: DATE | H60: MATERIAL DESCRIPTION
A61: Assembly Aids, Fixture/ Tools | D61: YES | E61: 1 | H61: Level 1 materials describe the geometric and functional attributes of the commodity (part), and how that part meets JLR's specifications and interacts with other vehicle components. At a minimum, the supplier must provide this information on Level One drawings unless otherwise approved by JLR. All Level One materials can be freely used by JLR without restriction.
A62: Component Package Drawings | D62: NO | E62: 1
A63: Component Part Drawings | D63: NO | E63: 1
A64: Control Plan | D64: YES | E64: 2 | H64: Level 2 materials describe more detailed design and manufacturing information such as FMEAs and DVP&R. The Supplier will provide the Buyer with access, including delivery of reference copies as the Buyer can reasonably request (such as for the purpose of warranty analysis, DVA, system studies, durability, durability prediction), to Level Two Materials as well as the right to use Level Two Materials internally, including to integrate the goods into the vehicle. All level 2 documents must be treated as confidential in accordance with JLR-18499 Production Purchasing Global Terms and Conditions, Section 17 - Confidentiality.
A65: Design FMEA | D65: NO | E65: 2
A66: DV / PV Test Plans | D66: YES | E66: 2
A67: Engineering Specifications | D67: NO | E67: 2
A68: Functional Requirements | D68: NO | E68: 2
A69: Guage Design Standards | D69: YES | E69: 2
A70: Process FMEA incl. Process Flow | D70: YES | E70: 2
A71: P-Diagram / Boundary Diagram | D71: NO | E71: 2
A72: Sub-Component BoM | D72: NO | E72: 2
A73: Software Functional Specifications | D73: NO | E73: 2
A74: Test Data | D74: YES | E74: 2
A75: Test Reports | D75: YES | E75: 2
A76: Test Specifications | D76: NO | E76: 2
A77: Tooling Data | D77: YES | E77: 2
A79: ETR.6 Warranty Information
A80: This section is designed to capture all expected warranty claims from the production and use of any part of the commodity / associated parts.
A81: COMMON WARRANTY CLAIMS
A82: Not Applicable
A84: RESOLUTION STRATEGY
A85: Not Applicable - Make to print part
A90: SUPPLIER RESPONSIBILITIES
A91: JLR Requirement title | E91: Requirement
A92: REQ: 55-7005 COMPLIANCE WITH VEHICLE INTERIOR AIR QUALITY VER01 | E92: The supplier must prove the part conformity against STJLR.51.5229 and STJLR.01.5202.
A93: REQ: 45-7000 EU. 2000/53/EC IMDS and Hazardous Materials Compliance VER02 (REG) | E93: Confirm that all parts comply with Jaguar Land Rover's Restricted Substance Management Standard (STJLR.99.9999 – "Latest Version"). The supplier must evaluate the proposed materials against the requirements of STJLR.99.9999 (attached). If all of the requirements are met, then the supplier must inform the engineer in writing (email) by PRDJ gateway IMDS declaration submission required by CSO gateway
A94: REQ: 55-7013 TÜV Toxproof Certification Requirements for Interior Materials VER01 | E94: TUV testing and certification in-line with STJLR.51.5232 complete by CSO gateway
A95: REQ: RF-7803 GTR. MULTINATIONAL FLAMMABILITY OF INTERIOR MATERIALS VER04 (REG) | E95: Procedure: 1/ The Supplier shall complete a flammability test to verify: a/ GB 8410 Flammability of Automotive Interior Materials. b/ FMVSS 302 Flammability of Interior Materials. 2/ The Supplier must supply JLR with a Test Report that includes the details identified in "TEMPLATE - FLAMMABILITY TEST REPORT VER02". Note: For any component which exhibits a burn rate greater than 80 mm/min, the Supplier is required to provide statistical data to prove capabilty for on-going production. Completion for CSO gateway
A96: REQ: DC-7005 Dimensional requirements for Trim components VER02 | E96: The supplier shall comply to this requirement outlines measurement and gauging requirements: STJLR 01.5160, STJLR 01.5161, STJLR 01.5166 and STJLR 00.5155. Appendix F,G,H,I to be confirmed by supplier.
A97: REQ: RF-8503 CHN. ANNOUNCEMENT 44/2019 CQC/CCAP CERTIFICATION FOR INTERIOR TRIMMING MATERIAL VER04 (REG) | E97: CQC/CCAP Accreditation: The Supplier must have accreditation for appropriate manufacturing facilities in which the components will be produced; or if not, has a plan to achieve accreditation prior to FEC. Completion by PRDJ gateway. Complete testing as per FEC Verification Plan by VSSO gateway: 1/ The supplier must complete testing in line with the requirement and provides JLR with certification evidence and test report(s) for the following: a/ the CQC or CCAP Component Certification Certificate b/ the component factory and product identifying numbers correspond with the CQC or CCAP certificates, so that information is easily cross referenced by part. c/ any markings required by the China GB standards d/ if the vehicle or the component is to be manufactured in China the supplier will also provide a copy of the Chinese language MIIT report. 2/ Annual Factory Inspection: a/ although not directly part of the Lead Engineer's sign off responsibility, the Supplier Technical Assistant (STA) agreed control plan with details of obtaining evidence of certification, Conformity of Production (CoP) and factory audits must be provided to JLR. Failure to ensure that this process is in the control plan may be detrimental to volume production rates for the Chinese market. b/ the evidence of certification, CoP testing and factory audits must continue to be sent to JLR, using the generic email account jlrcert@jaguarlandrover.com
A98: SUPPLIER RESPONSIBILITIES
A99: JLR Requirement title | E99: Requirement
A100: REQ: 55-7101 Material Performance BI Carpet and Sound Control VER05 | E100: The supplier must prove that all parts comply with: STJLR.51.5226 Standard Requirements For Production Materials STJLR.51.5341 Material Performance - Carpet STJLR.51.5229 Environmental Quality Requirements for Interior Materials and Components STJLR.51.5281 Polymeric foils. Gouge Test Acceptance criteria as per TPJLR.52.015 Appendix C STJLR.51.5306 Performance Requirements of Thermoplastic Elastomers (TPEs) Class A
A101: REQ: RM-8500 JLR Corporate E108 Parts and Accessories Branding Policy VER01 | E101: Branding details are specified in the drawing notes and CADJLR.02.02
A102: REQ: IT-9035 Cabin Trim - Assembly and Location VER02 | E102: Supplier must use STJLR.51.5261 as a guide in selecting dimensional tolerances for plastic mouldings in order to select the relevant tolerances grade required for correct function.
A103: REQ: 17-7042 Interior Surface Materials: Colour Measurement and Approval VER01 | E103: Delivery of AAR is tracked through the PPAP process. STJLR.01.5233
A104: REQ: FN-7000 System Safety Statement of Work | E104: Conform to requirements detailed in STJLR.18.059
A105: REQ: IT-0023 STRESS CRACKING FOR PLASTICS | E105: Supplier must prove and ensure that all mold release agents grease and/or materials which are designed to be in direct contact with a thermoplastic trim panel are not causing degradation to the thermoplastic (micro-cracking). Compliance shall be verified by testing to FLTM BO 127-03 with modifications shown on Detail. This requirement applies to fastener finish - do not use metal fasteners which contain or are treated with oils (i.e. S2 and S58 finishes) for the attachment of thermoplastic trim components. For U251, the lubricant for the sunvisor vanity door attacked the PC/ABS causing cracking. Colorant found in MIC sunvisor vanity attacked the PC/ABS material and parts cracked over time.Operating Conditions: 1. Prepare "L" type tensile bars per ASTM D 1822. A minimum of 4 tensile bars shall be prepared for each strain level specified in the Engineering Material Specification. 2. Condition bars for 24 hrs. 3. Assemble the tensile bars in the appropriate test fixtures to achieve the strain level require by the material specification. 4. Examine the sample for cracks using the stereo microscope. 5. Apply contact material to 3 bars keeping one as a standard, within 2 hrs. of assembling the test bar onto the fixture. 6. Expose the samples for the time period and temperature required by the Engineering Material Specification. 7. Clean the strained material without solvent and allow to condition fo 1 hr. at 23 DegreesC nd 50% relative humidity. 8. Using a stereo microscope, examine the strained sample for cracking and crazing at 20 diameters magnification while the sample is still in the straining fixture. Acceptance Criteria No additional micro cracking from standard sample.
E107: END OF SECTION

Sheet Hardware & CAD
A1: Hardware and CAD/CAE
A2: This section contains all hardware, CAD and CAE requirements for the commodity.
A3: CAD.1 CAD and CAE Requirements
A4: This section defines which organisation is responsible for CAD design and CAE requirements. For CAD Exchange Methods and associated licenses refer to Front Matter, Page 3.
A5: SUPPLIER CATEGORY: | D5: ='Front Matter'!I8 -> Make to Print | J5: APPLICABILITY
A6: Is the supplier responsible for the design of the part and have sole design responsibility? | J6: NO
A7: Is the responsibility for the design of the part shared between the supplier and JLR? | J7: NO
A8: Does JLR own the design, and have design responsibility where the supplier is responsible for the manufacture of the part? | J8: YES
A10: CAD.2 CAD Releasing Requirements
A11: All New Tool End Items (NTEI) shall be mastered supporting Model Based Definition (MBD). Model Based Definition is an annotated model and its associated data elements that define the product in a manner that can be used effectively without a drawing graphic sheet. The goal of MBD is to provide complete Technical Product Specification (TPS) to downstream users and systems for the lifecycle of the product. This means all required engineering information is communicated from one source, the annotated model. Consistency is needed in the creation and presentation of each product to ensure information is communicated effectively.
A12: RELEASE TYPE | E12: USE CASE | J12: APPLICABILITY
A13: CTM (CAD The Master) | E13: For New Tool End (Engineering) Items (NTEI) | J13: YES
A14: DTMC (Drawing The Master w/CAD | E14: For Carry Over or Modified Parts | J14: NO
A15: DTM (Drawing The Master) | E15: For Carry Over or Modified Parts | J15: NO
A16: CAD Assembly Model Tech. Specification | E16: For CAD To be released at Part Level | J16: NO
A17: CAD Assembly Kinematics | E17: For products with dynamic movement. Assemblies shall be provided that contain that kinematic movement and/or dynamic movement envelope. | J17: NO
A19: CAD.3 Technical Product Specification Requirements
A20: For 3D CAD Model, Technical Product Specification (TPS) only​. This relates to 3D CAD data in electronic format. There is no 2D drawing. ​ A 3D TPS shall conform to BS ISO 16792.​ The 3D TPS shall fully specify all geometry, datums, dimensions and tolerances in order to provide suitable and sufficient information to manufacture and verify the workpiece. A 3D TPS shall consist of 3D model information only. The 3D model(s) shall provide the CAD nominal geometry and sufficient datums, dimensions, tolerances and general notation necessary to provide suitable and sufficient information to manufacture and verify the required part.​
A21: CAD.4 CAE Virtual Engineering
A22: This section defines the Virtual Engineering (CAE) deliverables required to support the programme(s) noted above. The term CAE in this instance refers to all forms of CAA and includes the following: CFD, FE(A), MBS, 1D systems. All suppliers to Jaguar Land Rover programmes are obligated to support CAE requirements. This section shall be considered prior to the instruction to any supplier to commence CAE work on behalf of JLR. This document should be used to define the framework for CAE activity in the Engineering Statement of Work. Suppliers must submit all CAE data in a format that is compliant with JLR’s CAE strategy.
A23: CAD.5 Geometry Requirements
A24: This section defines which organisation is responsible for analysis and solid geometry design.
A26: RESPONSIBILITY | D26: APPLICABILITY | F26: Revision / Release Number / Calibration / Parameter Table I.D. | I26: Supplier Requires Boundary Diagram or Other NGD Data Types
A27: Supplier requires solid geometry | D27: YES
A29: CAD CREATION AND DELIVERY / TASK DESCRIPTION | I29: RESPONSIBILITY
A30: Creation and delivery of a CAE Finite Element meshed part from CAD (FE model build). | I30: JLR
A31: Creation and delivery of a 1D model and/or control system model(i.e. simulation model of the software that would eventually go into an ECU on a vehicle). | I31: JLR
A32: Execution of an existing method or capability in JLR to deliver some form of analysis report. | I32: JLR
A33: Development of a new simulation method or capability (Includes Capability projects). | I33: JLR
A35: CAD.6 Virtual Engineering Responsibilities
A36: This section defines the JLR and Supplier task and associated responsibilities for Virtual Engineering requirements.
A37: Task Description (Defined by Jaguar Land Rover) | F37: Responsibility for Supplier | J37: APPLICABILITY
A38: Define the nature and purpose of the CAE activity. | F38: None | J38: YES
A39: Specify the element(s) of the CAE activity to be delivered. | F39: None | J39: YES
A40: Specify the further sharing requirement. If the deliverable of this task includes a model the all users shall be identified and listed below; 1. Internal Users of the open model 2. Third party Users 3. Location (UK, Gaydon, China) | F40: Where the deliverable of the task is either in full or in part a CAE model; The model requester (Supplier Engineer) in conjunction with the Virtual Hub department at JLR must disclose the requirement to distribute the functionality of that model to JLR and to third parties*. | J40: YES
A41: * Third party in this case only refers to and is limited to; 1. Research Partners to JLR with an existing supplier relationship 2. Other suppliers to JLR with an existing supplier relationship who require, and may be expected to provide justification for, access to the design information to support any project as agreed by JLR.
A43: CAD.6.1 Virtual Engineering Responsibilities - Scope of CAD
A45: Task Description (Defined by Jaguar Land Rover) | E45: Responsibility for Supplier | J45: APPLICABILITY
A46: Provide an detailed description of the CAE model requirement. For 1D Systems Models; Download and complete the Model Specification Document Template. | E46: Understand, agree and demonstrate the ability to generate the requested model. The supplier shall prepare evidence to support their ability to create the requested model. | J46: YES
A47: This section is only applicable for 1D System Models. 1. Provide an detailed description of the inputs and outputs for 1D system model. Refer to 1D Technical Library, System IO Standard for 1D Models for the correct standards. 2. Provide the JLR Naming Standard and associated documents and naming variables. Refer to the JLR Signal Naming Convention portal for the correct standards and guidelines. 3. If the simulation modelling requires the application of Model Based Design (MBD) methods and automatic code generation then, refer to MISRA AC GMG for industry standards and guidelines. | E47: Collate, review and understand the engineering and industry standards which have been identified and provided by JLR (through any portal or communication channel) and make sure that the model requirements, and delivered product align to all relevant sections of the engineering and industry standards. Refer to Section E.5 - Engineering and Industry Standards for more information. | J47: YES
A48: Define load cases and constraints that can be applied to the model. | E48: To apply load cases and constraints and to record and validate the findings and outcomes. | J48: YES
A49: To provide non geometric data necessary for model creation and/or validation activities. The supplier may be responsible for some or all correlation/validation activity. JLR Shall confirm the scope and requirements with the supplier. | E49: The delivery of CAD/CAE in accordance with the project timelines, milestones and required engineering and industry standards. The supplier is responsible for requesting non-geometric data. The supplier is responsible for the creation of documents, reports, reviews and references such as, but not limited to; CAE Analysis Report This report shall include, a) Reference to source data for input types (CAD or NGD) b) Description of the Analysis methods used. c) Review of results and findings. d) Pass/Fail matrix determined for criteria in the Test Case. e) Suggestions for design improvement. f) Reference to source data used to achieve validation and correlation. CAE Models Models which have been supplied and/or used to conduct the analysis. These must be, a) In a format as agreed with JLR. b) Compatible with JLR’s software strategy. Other Supporting Documentation Documents appended for any CAE models supplied. These must be included, a) Block diagram showing model architecture, flow and I/O. b) Meaning & Units of Signals between model blocks and I/O. c) Scope and limitations of the model. d) Parameter names and descriptions of the model e) Tuning Parameters (incl. names and descriptions) f) User manuals for running models (incl. solver settings and parameterisation method) g) Description and data for model correlation/validation activity | J49: YES
A51: CAD.6.2 Virtual Engineering Responsibilities - Timing Requirements
A53: Task Description (Defined by Jaguar Land Rover) | E53: Responsibility for Supplier | J53: APPLICABILITY
A54: Define Milestone, Gateway and Event timing that in accordance with the Vehicle Program Plan. Where applicable, JLR will provide a Virtual Engineering Progression Schedule (VEPS) for each CPSCII code per component defined in this Statement of Work. JLR Lead engineer to provide the supplier with the latest VEPS information and glidepath. | E54: Develop a timing plan for delivery in accordance with, and aligned to JLR Milestones, Gateways and/or Events. Align and comply with the data/model maturity glide path as defined in the VEPS. | J54: YES
A55: Where applicable, Provide details of the analysis methodology(is) to be used. Provide test case details relevant to the applicable Test Case. Where applicable, complete and append the relevant test procedure documents. Provide the Simulation Detection Event Rating Matrix to assist the supplier in measuring their capability against each individual Test Case. The supplier can, although is not mandated to, provide a Benchmark Report to show results. | E55: Review and understand the methodology(is) defined by JLR and apply them to delivery of the models. Evaluate simulation capability in accordance with the JLR Simulation Detection Event Rating for test cases and provide feedback to JLR on their capabilities and any differences that may affect the test case. | J55: YES
A56: Define software and version releases and identify compatibility/non-compatibility with JLR models. Use the Tool Compatibility and Integration Matrix as defined in the 1D Technical Library. | E56: Ensuring that the same release is used throughout the life of the programme. Any valid reason for change must be communicated to JLR. | J56: YES
A58: CAD.6.3 Virtual Engineering Responsibilities - Capability
A60: Task Description (Defined by Jaguar Land Rover) | E60: Responsibility for Supplier | J60: APPLICABILITY
A61: To provide the supplier with human and/or computational resources needed to support the suppliers' ability to complete their deliverables. | E61: Regularly review and confirm that they have the necessary skilled human and computational resources and can fulfil resource capacity to complete the deliverables. | J61: YES
A62: Define the correct method for information exchange. Refer to E.3 Project Management for more information on information exchange requirements. | E62: Able to support the defined information exchange methods. | J62: YES
A64: CAD.6.4 Virtual Engineering Responsibilities - Bespoke / Other Requirements
A65: Use this section to add additional tasks and responsibilities.
A66: Task Description (Defined by Jaguar Land Rover) | E66: Responsibility for Supplier | J66: APPLICABILITY
A72: CAD.7 Bespoke Hardware System Requirements
A73: This section contains all bespoke requirements for hardware, physical parts and systems.
E92: END OF SECTION

Sheet Appendix A. RASIC
A1: Appendix A. RASIC
B3: SUPPLIER CATEGORY
B4: ='Front Matter'!I8 -> Make to Print
B6: This section defines all tasks, roles and responsibilities to be agreed between JLR and the supplier. Deviations or changes to the tasks defined in this section are not permitted and must be recorded in the Supplemental Terms and Conditions. The Lead Engineering can create additional Tasks and associated RASIC in Appendix B. RASIC Additions. A RASIC is mandatory for all sourcing projects.
A8: [PM] PROGRAMME MANAGEMENT | K8: APPLICABLE TO SOURCING PROJECT: | O8: APPLICABLE
A9: ID | B9: DESCRIPTION OF TASK | K9: Lead | L9: R | M9: A | N9: S | O9: I | P9: C
A10: =IF($B$4="Assembly or Component Provider",DATA_RASIC_DESC!A3,IF($B$4="Consultancy Component Provider",DATA_RASIC_DESC!A3,IF($B$4="Make to Print",DATA_RASIC_DESC!A3,IF($B$4="Engineering Service Provider",DATA_RASIC_DESC!A3,IF($B$4="Full System Provider",DATA_RASIC_DESC!A3,IF($B$4="ESP_DOOR TRIM",DATA_RASIC_DESC!D3,IF($B$4="ESP_Partner_LEVEL_01",DATA_RASIC_DESC!G3,""))))))) -> PM.1 | B10: =IF($B$4="Assembly or Component Provider",DATA_RASIC_DESC!B3,IF($B$4="Consultancy Component Provider",DATA_RASIC_DESC!B3,IF($B$4="Make to Print",DATA_RASIC_DESC!B3,IF($B$4="Engineering Service Provider",DATA_RASIC_DESC!B3,IF($B$4="Full System Provider",DATA_RASIC_DESC!B3,IF($B$4="ESP_DOOR TRIM",DATA_RASIC_DESC!E3,IF($B$4="ESP_Partner_LEVEL_01",DATA_RASIC_DESC!H3,""))))))) -> Provide communication as appropriate to all affected functions | K10: =IF($B$4="Assembly or Component Provider",DATA_RASIC!Q3,IF($B$4="Consultancy Component Provider",DATA_RASIC!X3,IF($B$4="Make to Print",DATA_RASIC!AE3,IF($B$4="Engineering Service Provider",DATA_RASIC!C3,IF($B$4="Full System Provider",DATA_RASIC!J3,IF($B$4="ESP_DOOR TRIM",DATA_RASIC!AL3,IF($B$4="ESP_Partner_LEVEL_01",DATA_RASIC!AS3,""))))))) -> JLR | L10: =IF($B$4="Assembly or Component Provider",DATA_RASIC!R3,IF($B$4="Consultancy Component Provider",DATA_RASIC!Y3,IF($B$4="Make to Print",DATA_RASIC!AF3,IF($B$4="Engineering Service Provider",DATA_RASIC!D3,IF($B$4="Full System Provider",DATA_RASIC!K3,IF($B$4="ESP_DOOR TRIM",DATA_RASIC!AM3,IF($B$4="ESP_Partner_LEVEL_01",DATA_RASIC!AT3,""))))))) -> JLR | M10: =IF($B$4="Assembly or Component Provider",DATA_RASIC!S3,IF($B$4="Consultancy Component Provider",DATA_RASIC!Z3,IF($B$4="Make to Print",DATA_RASIC!AG3,IF($B$4="Engineering Service Provider",DATA_RASIC!E3,IF($B$4="Full System Provider",DATA_RASIC!L3,IF($B$4="ESP_DOOR TRIM",DATA_RASIC!AN3,IF($B$4="ESP_Partner_LEVEL_01",DATA_RASIC!AU3,""))))))) -> JLR | N10: =IF($B$4="Assembly or Component Provider",DATA_RASIC!T3,IF($B$4="Consultancy Component Provider",DATA_RASIC!AA3,IF($B$4="Make to Print",DATA_RASIC!AH3,IF($B$4="Engineering Service Provider",DATA_RASIC!F3,IF($B$4="Full System Provider",DATA_RASIC!M3,IF($B$4="ESP_DOOR TRIM",DATA_RASIC!AO3,IF($B$4="ESP_Partner_LEVEL_01",DATA_RASIC!AV3,""))))))) -> - | O10: =IF($B$4="Assembly or Component Provider",DATA_RASIC!U3,IF($B$4="Consultancy Component Provider",DATA_RASIC!AB3,IF($B$4="Make to Print",DATA_RASIC!AI3,IF($B$4="Engineering Service Provider",DATA_RASIC!G3,IF($B$4="Full System Provider",DATA_RASIC!N3,IF($B$4="ESP_DOOR TRIM",DATA_RASIC!AP3,IF($B$4="ESP_Partner_LEVEL_01",DATA_RASIC!AW3,""))))))) -> SE | P10: =IF($B$4="Assembly or Component Provider",DATA_RASIC!V3,IF($B$4="Consultancy Component Provider",DATA_RASIC!AC3,IF($B$4="Make to Print",DATA_RASIC!AJ3,IF($B$4="Engineering Service Provider",DATA_RASIC!H3,IF($B$4="Full System Provider",DATA_RASIC!O3,IF($B$4="ESP_DOOR TRIM",DATA_RASIC!AQ3,IF($B$4="ESP_Partner_LEVEL_01",DATA_RASIC!AX3,""))))))) -> -
A11: =IF($B$4="Assembly or Component Provider",DATA_RASIC_DESC!A4,IF($B$4="Consultancy Component Provider",DATA_RASIC_DESC!A4,IF($B$4="Make to Print",DATA_RASIC_DESC!A4,IF($B$4="Engineering Service Provider",DATA_RASIC_DESC!A4,IF($B$4="Full System Provider",DATA_RASIC_DESC!A4,IF($B$4="ESP_DOOR TRIM",DATA_RASIC_DESC!D4,IF($B$4="ESP_Partner_LEVEL_01",DATA_RASIC_DESC!G4,""))))))) -> PM.2 | B11: =IF($B$4="Assembly or Component Provider",DATA_RASIC_DESC!B4,IF($B$4="Consultancy Component Provider",DATA_RASIC_DESC!B4,IF($B$4="Make to Print",DATA_RASIC_DESC!B4,IF($B$4="Engineering Service Provider",DATA_RASIC_DESC!B4,IF($B$4="Full System Provider",DATA_RASIC_DESC!B4,IF($B$4="ESP_DOOR TRIM",DATA_RASIC_DESC!E4,IF($B$4="ESP_Partner_LEVEL_01",DATA_RASIC_DESC!H4,""))))))) -> Develop an Early Sourcing Work plan for Programme team consensus | K11: =IF($B$4="Assembly or Component Provider",DATA_RASIC!Q4,IF($B$4="Consultancy Component Provider",DATA_RASIC!X4,IF($B$4="Make to Print",DATA_RASIC!AE4,IF($B$4="Engineering Service Provider",DATA_RASIC!C4,IF($B$4="Full System Provider",DATA_RASIC!J4,IF($B$4="ESP_DOOR TRIM",DATA_RASIC!AL4,IF($B$4="ESP_Partner_LEVEL_01",DATA_RASIC!AS4,""))))))) -> JLR | L11: =IF($B$4="Assembly or Component Provider",DATA_RASIC!R4,IF($B$4="Consultancy Component Provider",DATA_RASIC!Y4,IF($B$4="Make to Print",DATA_RASIC!AF4,IF($B$4="Engineering Service Provider",DATA_RASIC!D4,IF($B$4="Full System Provider",DATA_RASIC!K4,IF($B$4="ESP_DOOR TRIM",DATA_RASIC!AM4,IF($B$4="ESP_Partner_LEVEL_01",DATA_RASIC!AT4,""))))))) -> JLR | M11: =IF($B$4="Assembly or Component Provider",DATA_RASIC!S4,IF($B$4="Consultancy Component Provider",DATA_RASIC!Z4,IF($B$4="Make to Print",DATA_RASIC!AG4,IF($B$4="Engineering Service Provider",DATA_RASIC!E4,IF($B$4="Full System Provider",DATA_RASIC!L4,IF($B$4="ESP_DOOR TRIM",DATA_RASIC!AN4,IF($B$4="ESP_Partner_LEVEL_01",DATA_RASIC!AU4,""))))))) -> JLR | N11: =IF($B$4="Assembly or Component Provider",DATA_RASIC!T4,IF($B$4="Consultancy Component Provider",DATA_RASIC!AA4,IF($B$4="Make to Print",DATA_RASIC!AH4,IF($B$4="Engineering Service Provider",DATA_RASIC!F4,IF($B$4="Full System Provider",DATA_RASIC!M4,IF($B$4="ESP_DOOR TRIM",DATA_RASIC!AO4,IF($B$4="ESP_Partner_LEVEL_01",DATA_RASIC!AV4,""))))))) -> - | O11: =IF($B$4="Assembly or Component Provider",DATA_RASIC!U4,IF($B$4="Consultancy Component Provider",DATA_RASIC!AB4,IF($B$4="Make to Print",DATA_RASIC!AI4,IF($B$4="Engineering Service Provider",DATA_RASIC!G4,IF($B$4="Full System Provider",DATA_RASIC!N4,IF($B$4="ESP_DOOR TRIM",DATA_RASIC!AP4,IF($B$4="ESP_Partner_LEVEL_01",DATA_RASIC!AW4,""))))))) -> SE | P11: =IF($B$4="Assembly or Component Provider",DATA_RASIC!V4,IF($B$4="Consultancy Component Provider",DATA_RASIC!AC4,IF($B$4="Make to Print",DATA_RASIC!AJ4,IF($B$4="Engineering Service Provider",DATA_RASIC!H4,IF($B$4="Full System Provider",DATA_RASIC!O4,IF($B$4="ESP_DOOR TRIM",DATA_RASIC!AQ4,IF($B$4="ESP_Partner_LEVEL_01",DATA_RASIC!AX4,""))))))) -> -
A12: =IF($B$4="Assembly or Component Provider",DATA_RASIC_DESC!A5,IF($B$4="Consultancy Component Provider",DATA_RASIC_DESC!A5,IF($B$4="Make to Print",DATA_RASIC_DESC!A5,IF($B$4="Engineering Service Provider",DATA_RASIC_DESC!A5,IF($B$4="Full System Provider",DATA_RASIC_DESC!A5,IF($B$4="ESP_DOOR TRIM",DATA_RASIC_DESC!D5,IF($B$4="ESP_Partner_LEVEL_01",DATA_RASIC_DESC!G5,""))))))) -> PM.3 | B12: =IF($B$4="Assembly or Component Provider",DATA_RASIC_DESC!B5,IF($B$4="Consultancy Component Provider",DATA_RASIC_DESC!B5,IF($B$4="Make to Print",DATA_RASIC_DESC!B5,IF($B$4="Engineering Service Provider",DATA_RASIC_DESC!B5,IF($B$4="Full System Provider",DATA_RASIC_DESC!B5,IF($B$4="ESP_DOOR TRIM",DATA_RASIC_DESC!E5,IF($B$4="ESP_Partner_LEVEL_01",DATA_RASIC_DESC!H5,""))))))) -> Appoint a Project Leader & functional Manager of Jaguar Land Rover | K12: =IF($B$4="Assembly or Component Provider",DATA_RASIC!Q5,IF($B$4="Consultancy Component Provider",DATA_RASIC!X5,IF($B$4="Make to Print",DATA_RASIC!AE5,IF($B$4="Engineering Service Provider",DATA_RASIC!C5,IF($B$4="Full System Provider",DATA_RASIC!J5,IF($B$4="ESP_DOOR TRIM",DATA_RASIC!AL5,IF($B$4="ESP_Partner_LEVEL_01",DATA_RASIC!AS5,""))))))) -> JLR | L12: =IF($B$4="Assembly or Component Provider",DATA_RASIC!R5,IF($B$4="Consultancy Component Provider",DATA_RASIC!Y5,IF($B$4="Make to Print",DATA_RASIC!AF5,IF($B$4="Engineering Service Provider",DATA_RASIC!D5,IF($B$4="Full System Provider",DATA_RASIC!K5,IF($B$4="ESP_DOOR TRIM",DATA_RASIC!AM5,IF($B$4="ESP_Partner_LEVEL_01",DATA_RASIC!AT5,""))))))) -> JLR | M12: =IF($B$4="Assembly or Component Provider",DATA_RASIC!S5,IF($B$4="Consultancy Component Provider",DATA_RASIC!Z5,IF($B$4="Make to Print",DATA_RASIC!AG5,IF($B$4="Engineering Service Provider",DATA_RASIC!E5,IF($B$4="Full System Provider",DATA_RASIC!L5,IF($B$4="ESP_DOOR TRIM",DATA_RASIC!AN5,IF($B$4="ESP_Partner_LEVEL_01",DATA_RASIC!AU5,""))))))) -> JLR | N12: =IF($B$4="Assembly or Component Provider",DATA_RASIC!T5,IF($B$4="Consultancy Component Provider",DATA_RASIC!AA5,IF($B$4="Make to Print",DATA_RASIC!AH5,IF($B$4="Engineering Service Provider",DATA_RASIC!F5,IF($B$4="Full System Provider",DATA_RASIC!M5,IF($B$4="ESP_DOOR TRIM",DATA_RASIC!AO5,IF($B$4="ESP_Partner_LEVEL_01",DATA_RASIC!AV5,""))))))) -> - | O12: =IF($B$4="Assembly or Component Provider",DATA_RASIC!U5,IF($B$4="Consultancy Component Provider",DATA_RASIC!AB5,IF($B$4="Make to Print",DATA_RASIC!AI5,IF($B$4="Engineering Service Provider",DATA_RASIC!G5,IF($B$4="Full System Provider",DATA_RASIC!N5,IF($B$4="ESP_DOOR TRIM",DATA_RASIC!AP5,IF($B$4="ESP_Partner_LEVEL_01",DATA_RASIC!AW5,""))))))) -> SE | P12: =IF($B$4="Assembly or Component Provider",DATA_RASIC!V5,IF($B$4="Consultancy Component Provider",DATA_RASIC!AC5,IF($B$4="Make to Print",DATA_RASIC!AJ5,IF($B$4="Engineering Service Provider",DATA_RASIC!H5,IF($B$4="Full System Provider",DATA_RASIC!O5,IF($B$4="ESP_DOOR TRIM",DATA_RASIC!AQ5,IF($B$4="ESP_Partner_LEVEL_01",DATA_RASIC!AX5,""))))))) -> -
A13: =IF($B$4="Assembly or Component Provider",DATA_RASIC_DESC!A6,IF($B$4="Consultancy Component Provider",DATA_RASIC_DESC!A6,IF($B$4="Make to Print",DATA_RASIC_DESC!A6,IF($B$4="Engineering Service Provider",DATA_RASIC_DESC!A6,IF($B$4="Full System Provider",DATA_RASIC_DESC!A6,IF($B$4="ESP_DOOR TRIM",DATA_RASIC_DESC!D6,IF($B$4="ESP_Partner_LEVEL_01",DATA_RASIC_DESC!G6,""))))))) -> PM.4 | B13: =IF($B$4="Assembly or Component Provider",DATA_RASIC_DESC!B6,IF($B$4="Consultancy Component Provider",DATA_RASIC_DESC!B6,IF($B$4="Make to Print",DATA_RASIC_DESC!B6,IF($B$4="Engineering Service Provider",DATA_RASIC_DESC!B6,IF($B$4="Full System Provider",DATA_RASIC_DESC!B6,IF($B$4="ESP_DOOR TRIM",DATA_RASIC_DESC!E6,IF($B$4="ESP_Partner_LEVEL_01",DATA_RASIC_DESC!H6,""))))))) -> Establish Programme Management Teams (PMTs) as required and support supplier lead Programme Module Team | K13: =IF($B$4="Assembly or Component Provider",DATA_RASIC!Q6,IF($B$4="Consultancy Component Provider",DATA_RASIC!X6,IF($B$4="Make to Print",DATA_RASIC!AE6,IF($B$4="Engineering Service Provider",DATA_RASIC!C6,IF($B$4="Full System Provider",DATA_RASIC!J6,IF($B$4="ESP_DOOR TRIM",DATA_RASIC!AL6,IF($B$4="ESP_Partner_LEVEL_01",DATA_RASIC!AS6,""))))))) -> JLR | L13: =IF($B$4="Assembly or Component Provider",DATA_RASIC!R6,IF($B$4="Consultancy Component Provider",DATA_RASIC!Y6,IF($B$4="Make to Print",DATA_RASIC!AF6,IF($B$4="Engineering Service Provider",DATA_RASIC!D6,IF($B$4="Full System Provider",DATA_RASIC!K6,IF($B$4="ESP_DOOR TRIM",DATA_RASIC!AM6,IF($B$4="ESP_Partner_LEVEL_01",DATA_RASIC!AT6,""))))))) -> JLR | M13: =IF($B$4="Assembly or Component Provider",DATA_RASIC!S6,IF($B$4="Consultancy Component Provider",DATA_RASIC!Z6,IF($B$4="Make to Print",DATA_RASIC!AG6,IF($B$4="Engineering Service Provider",DATA_RASIC!E6,IF($B$4="Full System Provider",DATA_RASIC!L6,IF($B$4="ESP_DOOR TRIM",DATA_RASIC!AN6,IF($B$4="ESP_Partner_LEVEL_01",DATA_RASIC!AU6,""))))))) -> JLR | N13: =IF($B$4="Assembly or Component Provider",DATA_RASIC!T6,IF($B$4="Consultancy Component Provider",DATA_RASIC!AA6,IF($B$4="Make to Print",DATA_RASIC!AH6,IF($B$4="Engineering Service Provider",DATA_RASIC!F6,IF($B$4="Full System Provider",DATA_RASIC!M6,IF($B$4="ESP_DOOR TRIM",DATA_RASIC!AO6,IF($B$4="ESP_Partner_LEVEL_01",DATA_RASIC!AV6,""))))))) -> SE | O13: =IF($B$4="Assembly or Component Provider",DATA_RASIC!U6,IF($B$4="Consultancy Component Provider",DATA_RASIC!AB6,IF($B$4="Make to Print",DATA_RASIC!AI6,IF($B$4="Engineering Service Provider",DATA_RASIC!G6,IF($B$4="Full System Provider",DATA_RASIC!N6,IF($B$4="ESP_DOOR TRIM",DATA_RASIC!AP6,IF($B$4="ESP_Partner_LEVEL_01",DATA_RASIC!AW6,""))))))) -> - | P13: =IF($B$4="Assembly or Component Provider",DATA_RASIC!V6,IF($B$4="Consultancy Component Provider",DATA_RASIC!AC6,IF($B$4="Make to Print",DATA_RASIC!AJ6,IF($B$4="Engineering Service Provider",DATA_RASIC!H6,IF($B$4="Full System Provider",DATA_RASIC!O6,IF($B$4="ESP_DOOR TRIM",DATA_RASIC!AQ6,IF($B$4="ESP_Partner_LEVEL_01",DATA_RASIC!AX6,""))))))) -> -
A14: =IF($B$4="Assembly or Component Provider",DATA_RASIC_DESC!A7,IF($B$4="Consultancy Component Provider",DATA_RASIC_DESC!A7,IF($B$4="Make to Print",DATA_RASIC_DESC!A7,IF($B$4="Engineering Service Provider",DATA_RASIC_DESC!A7,IF($B$4="Full System Provider",DATA_RASIC_DESC!A7,IF($B$4="ESP_DOOR TRIM",DATA_RASIC_DESC!D7,IF($B$4="ESP_Partner_LEVEL_01",DATA_RASIC_DESC!G7,""))))))) -> PM.5 | B14: =IF($B$4="Assembly or Component Provider",DATA_RASIC_DESC!B7,IF($B$4="Consultancy Component Provider",DATA_RASIC_DESC!B7,IF($B$4="Make to Print",DATA_RASIC_DESC!B7,IF($B$4="Engineering Service Provider",DATA_RASIC_DESC!B7,IF($B$4="Full System Provider",DATA_RASIC_DESC!B7,IF($B$4="ESP_DOOR TRIM",DATA_RASIC_DESC!E7,IF($B$4="ESP_Partner_LEVEL_01",DATA_RASIC_DESC!H7,""))))))) -> Create commodity work plans to supplement the Programme specific VPP | K14: =IF($B$4="Assembly or Component Provider",DATA_RASIC!Q7,IF($B$4="Consultancy Component Provider",DATA_RASIC!X7,IF($B$4="Make to Print",DATA_RASIC!AE7,IF($B$4="Engineering Service Provider",DATA_RASIC!C7,IF($B$4="Full System Provider",DATA_RASIC!J7,IF($B$4="ESP_DOOR TRIM",DATA_RASIC!AL7,IF($B$4="ESP_Partner_LEVEL_01",DATA_RASIC!AS7,""))))))) -> JLR | L14: =IF($B$4="Assembly or Component Provider",DATA_RASIC!R7,IF($B$4="Consultancy Component Provider",DATA_RASIC!Y7,IF($B$4="Make to Print",DATA_RASIC!AF7,IF($B$4="Engineering Service Provider",DATA_RASIC!D7,IF($B$4="Full System Provider",DATA_RASIC!K7,IF($B$4="ESP_DOOR TRIM",DATA_RASIC!AM7,IF($B$4="ESP_Partner_LEVEL_01",DATA_RASIC!AT7,""))))))) -> JLR | M14: =IF($B$4="Assembly or Component Provider",DATA_RASIC!S7,IF($B$4="Consultancy Component Provider",DATA_RASIC!Z7,IF($B$4="Make to Print",DATA_RASIC!AG7,IF($B$4="Engineering Service Provider",DATA_RASIC!E7,IF($B$4="Full System Provider",DATA_RASIC!L7,IF($B$4="ESP_DOOR TRIM",DATA_RASIC!AN7,IF($B$4="ESP_Partner_LEVEL_01",DATA_RASIC!AU7,""))))))) -> JLR | N14: =IF($B$4="Assembly or Component Provider",DATA_RASIC!T7,IF($B$4="Consultancy Component Provider",DATA_RASIC!AA7,IF($B$4="Make to Print",DATA_RASIC!AH7,IF($B$4="Engineering Service Provider",DATA_RASIC!F7,IF($B$4="Full System Provider",DATA_RASIC!M7,IF($B$4="ESP_DOOR TRIM",DATA_RASIC!AO7,IF($B$4="ESP_Partner_LEVEL_01",DATA_RASIC!AV7,""))))))) -> SE | O14: =IF($B$4="Assembly or Component Provider",DATA_RASIC!U7,IF($B$4="Consultancy Component Provider",DATA_RASIC!AB7,IF($B$4="Make to Print",DATA_RASIC!AI7,IF($B$4="Engineering Service Provider",DATA_RASIC!G7,IF($B$4="Full System Provider",DATA_RASIC!N7,IF($B$4="ESP_DOOR TRIM",DATA_RASIC!AP7,IF($B$4="ESP_Partner_LEVEL_01",DATA_RASIC!AW7,""))))))) -> - | P14: =IF($B$4="Assembly or Component Provider",DATA_RASIC!V7,IF($B$4="Consultancy Component Provider",DATA_RASIC!AC7,IF($B$4="Make to Print",DATA_RASIC!AJ7,IF($B$4="Engineering Service Provider",DATA_RASIC!H7,IF($B$4="Full System Provider",DATA_RASIC!O7,IF($B$4="ESP_DOOR TRIM",DATA_RASIC!AQ7,IF($B$4="ESP_Partner_LEVEL_01",DATA_RASIC!AX7,""))))))) -> -
A15: =IF($B$4="Assembly or Component Provider",DATA_RASIC_DESC!A8,IF($B$4="Consultancy Component Provider",DATA_RASIC_DESC!A8,IF($B$4="Make to Print",DATA_RASIC_DESC!A8,IF($B$4="Engineering Service Provider",DATA_RASIC_DESC!A8,IF($B$4="Full System Provider",DATA_RASIC_DESC!A8,IF($B$4="ESP_DOOR TRIM",DATA_RASIC_DESC!D8,IF($B$4="ESP_Partner_LEVEL_01",DATA_RASIC_DESC!G8,""))))))) -> PM.6 | B15: =IF($B$4="Assembly or Component Provider",DATA_RASIC_DESC!B8,IF($B$4="Consultancy Component Provider",DATA_RASIC_DESC!B8,IF($B$4="Make to Print",DATA_RASIC_DESC!B8,IF($B$4="Engineering Service Provider",DATA_RASIC_DESC!B8,IF($B$4="Full System Provider",DATA_RASIC_DESC!B8,IF($B$4="ESP_DOOR TRIM",DATA_RASIC_DESC!E8,IF($B$4="ESP_Partner_LEVEL_01",DATA_RASIC_DESC!H8,""))))))) -> Provide access to Jaguar Land Rover's data systems which are required for the Programme. e.g. / WERS CONCERN , NOTICE and ALERT system to allow the supplier to generate the necessary data to support Jaguar Land Rover's release system | K15: =IF($B$4="Assembly or Component Provider",DATA_RASIC!Q8,IF($B$4="Consultancy Component Provider",DATA_RASIC!X8,IF($B$4="Make to Print",DATA_RASIC!AE8,IF($B$4="Engineering Service Provider",DATA_RASIC!C8,IF($B$4="Full System Provider",DATA_RASIC!J8,IF($B$4="ESP_DOOR TRIM",DATA_RASIC!AL8,IF($B$4="ESP_Partner_LEVEL_01",DATA_RASIC!AS8,""))))))) -> JLR | L15: =IF($B$4="Assembly or Component Provider",DATA_RASIC!R8,IF($B$4="Consultancy Component Provider",DATA_RASIC!Y8,IF($B$4="Make to Print",DATA_RASIC!AF8,IF($B$4="Engineering Service Provider",DATA_RASIC!D8,IF($B$4="Full System Provider",DATA_RASIC!K8,IF($B$4="ESP_DOOR TRIM",DATA_RASIC!AM8,IF($B$4="ESP_Partner_LEVEL_01",DATA_RASIC!AT8,""))))))) -> JLR | M15: =IF($B$4="Assembly or Component Provider",DATA_RASIC!S8,IF($B$4="Consultancy Component Provider",DATA_RASIC!Z8,IF($B$4="Make to Print",DATA_RASIC!AG8,IF($B$4="Engineering Service Provider",DATA_RASIC!E8,IF($B$4="Full System Provider",DATA_RASIC!L8,IF($B$4="ESP_DOOR TRIM",DATA_RASIC!AN8,IF($B$4="ESP_Partner_LEVEL_01",DATA_RASIC!AU8,""))))))) -> JLR | N15: =IF($B$4="Assembly or Component Provider",DATA_RASIC!T8,IF($B$4="Consultancy Component Provider",DATA_RASIC!AA8,IF($B$4="Make to Print",DATA_RASIC!AH8,IF($B$4="Engineering Service Provider",DATA_RASIC!F8,IF($B$4="Full System Provider",DATA_RASIC!M8,IF($B$4="ESP_DOOR TRIM",DATA_RASIC!AO8,IF($B$4="ESP_Partner_LEVEL_01",DATA_RASIC!AV8,""))))))) -> - | O15: =IF($B$4="Assembly or Component Provider",DATA_RASIC!U8,IF($B$4="Consultancy Component Provider",DATA_RASIC!AB8,IF($B$4="Make to Print",DATA_RASIC!AI8,IF($B$4="Engineering Service Provider",DATA_RASIC!G8,IF($B$4="Full System Provider",DATA_RASIC!N8,IF($B$4="ESP_DOOR TRIM",DATA_RASIC!AP8,IF($B$4="ESP_Partner_LEVEL_01",DATA_RASIC!AW8,""))))))) -> SE | P15: =IF($B$4="Assembly or Component Provider",DATA_RASIC!V8,IF($B$4="Consultancy Component Provider",DATA_RASIC!AC8,IF($B$4="Make to Print",DATA_RASIC!AJ8,IF($B$4="Engineering Service Provider",DATA_RASIC!H8,IF($B$4="Full System Provider",DATA_RASIC!O8,IF($B$4="ESP_DOOR TRIM",DATA_RASIC!AQ8,IF($B$4="ESP_Partner_LEVEL_01",DATA_RASIC!AX8,""))))))) -> -
A16: =IF($B$4="Assembly or Component Provider",DATA_RASIC_DESC!A9,IF($B$4="Consultancy Component Provider",DATA_RASIC_DESC!A9,IF($B$4="Make to Print",DATA_RASIC_DESC!A9,IF($B$4="Engineering Service Provider",DATA_RASIC_DESC!A9,IF($B$4="Full System Provider",DATA_RASIC_DESC!A9,IF($B$4="ESP_DOOR TRIM",DATA_RASIC_DESC!D9,IF($B$4="ESP_Partner_LEVEL_01",DATA_RASIC_DESC!G9,""))))))) -> PM.7 | B16: =IF($B$4="Assembly or Component Provider",DATA_RASIC_DESC!B9,IF($B$4="Consultancy Component Provider",DATA_RASIC_DESC!B9,IF($B$4="Make to Print",DATA_RASIC_DESC!B9,IF($B$4="Engineering Service Provider",DATA_RASIC_DESC!B9,IF($B$4="Full System Provider",DATA_RASIC_DESC!B9,IF($B$4="ESP_DOOR TRIM",DATA_RASIC_DESC!E9,IF($B$4="ESP_Partner_LEVEL_01",DATA_RASIC_DESC!H9,""))))))) -> All changes proposed by JLR to requirements or design will be formally communicated to the supplier for review and identification of impact. If the change and associated impacts are deemed acceptable, the change will be authorised by WERS. JLR must review and approve all changes via WERS or SREA | K16: =IF($B$4="Assembly or Component Provider",DATA_RASIC!Q9,IF($B$4="Consultancy Component Provider",DATA_RASIC!X9,IF($B$4="Make to Print",DATA_RASIC!AE9,IF($B$4="Engineering Service Provider",DATA_RASIC!C9,IF($B$4="Full System Provider",DATA_RASIC!J9,IF($B$4="ESP_DOOR TRIM",DATA_RASIC!AL9,IF($B$4="ESP_Partner_LEVEL_01",DATA_RASIC!AS9,""))))))) -> JLR | L16: =IF($B$4="Assembly or Component Provider",DATA_RASIC!R9,IF($B$4="Consultancy Component Provider",DATA_RASIC!Y9,IF($B$4="Make to Print",DATA_RASIC!AF9,IF($B$4="Engineering Service Provider",DATA_RASIC!D9,IF($B$4="Full System Provider",DATA_RASIC!K9,IF($B$4="ESP_DOOR TRIM",DATA_RASIC!AM9,IF($B$4="ESP_Partner_LEVEL_01",DATA_RASIC!AT9,""))))))) -> JLR | M16: =IF($B$4="Assembly or Component Provider",DATA_RASIC!S9,IF($B$4="Consultancy Component Provider",DATA_RASIC!Z9,IF($B$4="Make to Print",DATA_RASIC!AG9,IF($B$4="Engineering Service Provider",DATA_RASIC!E9,IF($B$4="Full System Provider",DATA_RASIC!L9,IF($B$4="ESP_DOOR TRIM",DATA_RASIC!AN9,IF($B$4="ESP_Partner_LEVEL_01",DATA_RASIC!AU9,""))))))) -> JLR | N16: =IF($B$4="Assembly or Component Provider",DATA_RASIC!T9,IF($B$4="Consultancy Component Provider",DATA_RASIC!AA9,IF($B$4="Make to Print",DATA_RASIC!AH9,IF($B$4="Engineering Service Provider",DATA_RASIC!F9,IF($B$4="Full System Provider",DATA_RASIC!M9,IF($B$4="ESP_DOOR TRIM",DATA_RASIC!AO9,IF($B$4="ESP_Partner_LEVEL_01",DATA_RASIC!AV9,""))))))) -> SE | O16: =IF($B$4="Assembly or Component Provider",DATA_RASIC!U9,IF($B$4="Consultancy Component Provider",DATA_RASIC!AB9,IF($B$4="Make to Print",DATA_RASIC!AI9,IF($B$4="Engineering Service Provider",DATA_RASIC!G9,IF($B$4="Full System Provider",DATA_RASIC!N9,IF($B$4="ESP_DOOR TRIM",DATA_RASIC!AP9,IF($B$4="ESP_Partner_LEVEL_01",DATA_RASIC!AW9,""))))))) -> - | P16: =IF($B$4="Assembly or Component Provider",DATA_RASIC!V9,IF($B$4="Consultancy Component Provider",DATA_RASIC!AC9,IF($B$4="Make to Print",DATA_RASIC!AJ9,IF($B$4="Engineering Service Provider",DATA_RASIC!H9,IF($B$4="Full System Provider",DATA_RASIC!O9,IF($B$4="ESP_DOOR TRIM",DATA_RASIC!AQ9,IF($B$4="ESP_Partner_LEVEL_01",DATA_RASIC!AX9,""))))))) -> -
A17: =IF($B$4="Assembly or Component Provider",DATA_RASIC_DESC!A10,IF($B$4="Consultancy Component Provider",DATA_RASIC_DESC!A10,IF($B$4="Make to Print",DATA_RASIC_DESC!A10,IF($B$4="Engineering Service Provider",DATA_RASIC_DESC!A10,IF($B$4="Full System Provider",DATA_RASIC_DESC!A10,IF($B$4="ESP_DOOR TRIM",DATA_RASIC_DESC!D10,IF($B$4="ESP_Partner_LEVEL_01",DATA_RASIC_DESC!G10,""))))))) -> PM.8 | B17: =IF($B$4="Assembly or Component Provider",DATA_RASIC_DESC!B10,IF($B$4="Consultancy Component Provider",DATA_RASIC_DESC!B10,IF($B$4="Make to Print",DATA_RASIC_DESC!B10,IF($B$4="Engineering Service Provider",DATA_RASIC_DESC!B10,IF($B$4="Full System Provider",DATA_RASIC_DESC!B10,IF($B$4="ESP_DOOR TRIM",DATA_RASIC_DESC!E10,IF($B$4="ESP_Partner_LEVEL_01",DATA_RASIC_DESC!H10,""))))))) -> Develop Service Cost of Ownership and Serviceability Index targets for all Programme defined markets utilising Company provided data and methods. Product must be consistent with vehicle service strategy, targets and agreements | K17: =IF($B$4="Assembly or Component Provider",DATA_RASIC!Q10,IF($B$4="Consultancy Component Provider",DATA_RASIC!X10,IF($B$4="Make to Print",DATA_RASIC!AE10,IF($B$4="Engineering Service Provider",DATA_RASIC!C10,IF($B$4="Full System Provider",DATA_RASIC!J10,IF($B$4="ESP_DOOR TRIM",DATA_RASIC!AL10,IF($B$4="ESP_Partner_LEVEL_01",DATA_RASIC!AS10,""))))))) -> JLR | L17: =IF($B$4="Assembly or Component Provider",DATA_RASIC!R10,IF($B$4="Consultancy Component Provider",DATA_RASIC!Y10,IF($B$4="Make to Print",DATA_RASIC!AF10,IF($B$4="Engineering Service Provider",DATA_RASIC!D10,IF($B$4="Full System Provider",DATA_RASIC!K10,IF($B$4="ESP_DOOR TRIM",DATA_RASIC!AM10,IF($B$4="ESP_Partner_LEVEL_01",DATA_RASIC!AT10,""))))))) -> JLR | M17: =IF($B$4="Assembly or Component Provider",DATA_RASIC!S10,IF($B$4="Consultancy Component Provider",DATA_RASIC!Z10,IF($B$4="Make to Print",DATA_RASIC!AG10,IF($B$4="Engineering Service Provider",DATA_RASIC!E10,IF($B$4="Full System Provider",DATA_RASIC!L10,IF($B$4="ESP_DOOR TRIM",DATA_RASIC!AN10,IF($B$4="ESP_Partner_LEVEL_01",DATA_RASIC!AU10,""))))))) -> JLR | N17: =IF($B$4="Assembly or Component Provider",DATA_RASIC!T10,IF($B$4="Consultancy Component Provider",DATA_RASIC!AA10,IF($B$4="Make to Print",DATA_RASIC!AH10,IF($B$4="Engineering Service Provider",DATA_RASIC!F10,IF($B$4="Full System Provider",DATA_RASIC!M10,IF($B$4="ESP_DOOR TRIM",DATA_RASIC!AO10,IF($B$4="ESP_Partner_LEVEL_01",DATA_RASIC!AV10,""))))))) -> - | O17: =IF($B$4="Assembly or Component Provider",DATA_RASIC!U10,IF($B$4="Consultancy Component Provider",DATA_RASIC!AB10,IF($B$4="Make to Print",DATA_RASIC!AI10,IF($B$4="Engineering Service Provider",DATA_RASIC!G10,IF($B$4="Full System Provider",DATA_RASIC!N10,IF($B$4="ESP_DOOR TRIM",DATA_RASIC!AP10,IF($B$4="ESP_Partner_LEVEL_01",DATA_RASIC!AW10,""))))))) -> SE | P17: =IF($B$4="Assembly or Component Provider",DATA_RASIC!V10,IF($B$4="Consultancy Component Provider",DATA_RASIC!AC10,IF($B$4="Make to Print",DATA_RASIC!AJ10,IF($B$4="Engineering Service Provider",DATA_RASIC!H10,IF($B$4="Full System Provider",DATA_RASIC!O10,IF($B$4="ESP_DOOR TRIM",DATA_RASIC!AQ10,IF($B$4="ESP_Partner_LEVEL_01",DATA_RASIC!AX10,""))))))) -> -
A18: =IF($B$4="Assembly or Component Provider",DATA_RASIC_DESC!A11,IF($B$4="Consultancy Component Provider",DATA_RASIC_DESC!A11,IF($B$4="Make to Print",DATA_RASIC_DESC!A11,IF($B$4="Engineering Service Provider",DATA_RASIC_DESC!A11,IF($B$4="Full System Provider",DATA_RASIC_DESC!A11,IF($B$4="ESP_DOOR TRIM",DATA_RASIC_DESC!D11,IF($B$4="ESP_Partner_LEVEL_01",DATA_RASIC_DESC!G11,""))))))) -> PM.9 | B18: =IF($B$4="Assembly or Component Provider",DATA_RASIC_DESC!B11,IF($B$4="Consultancy Component Provider",DATA_RASIC_DESC!B11,IF($B$4="Make to Print",DATA_RASIC_DESC!B11,IF($B$4="Engineering Service Provider",DATA_RASIC_DESC!B11,IF($B$4="Full System Provider",DATA_RASIC_DESC!B11,IF($B$4="ESP_DOOR TRIM",DATA_RASIC_DESC!E11,IF($B$4="ESP_Partner_LEVEL_01",DATA_RASIC_DESC!H11,""))))))) -> Meet Programme milestone deliverables. | K18: =IF($B$4="Assembly or Component Provider",DATA_RASIC!Q11,IF($B$4="Consultancy Component Provider",DATA_RASIC!X11,IF($B$4="Make to Print",DATA_RASIC!AE11,IF($B$4="Engineering Service Provider",DATA_RASIC!C11,IF($B$4="Full System Provider",DATA_RASIC!J11,IF($B$4="ESP_DOOR TRIM",DATA_RASIC!AL11,IF($B$4="ESP_Partner_LEVEL_01",DATA_RASIC!AS11,""))))))) -> JLR | L18: =IF($B$4="Assembly or Component Provider",DATA_RASIC!R11,IF($B$4="Consultancy Component Provider",DATA_RASIC!Y11,IF($B$4="Make to Print",DATA_RASIC!AF11,IF($B$4="Engineering Service Provider",DATA_RASIC!D11,IF($B$4="Full System Provider",DATA_RASIC!K11,IF($B$4="ESP_DOOR TRIM",DATA_RASIC!AM11,IF($B$4="ESP_Partner_LEVEL_01",DATA_RASIC!AT11,""))))))) -> JLR | M18: =IF($B$4="Assembly or Component Provider",DATA_RASIC!S11,IF($B$4="Consultancy Component Provider",DATA_RASIC!Z11,IF($B$4="Make to Print",DATA_RASIC!AG11,IF($B$4="Engineering Service Provider",DATA_RASIC!E11,IF($B$4="Full System Provider",DATA_RASIC!L11,IF($B$4="ESP_DOOR TRIM",DATA_RASIC!AN11,IF($B$4="ESP_Partner_LEVEL_01",DATA_RASIC!AU11,""))))))) -> JLR | N18: =IF($B$4="Assembly or Component Provider",DATA_RASIC!T11,IF($B$4="Consultancy Component Provider",DATA_RASIC!AA11,IF($B$4="Make to Print",DATA_RASIC!AH11,IF($B$4="Engineering Service Provider",DATA_RASIC!F11,IF($B$4="Full System Provider",DATA_RASIC!M11,IF($B$4="ESP_DOOR TRIM",DATA_RASIC!AO11,IF($B$4="ESP_Partner_LEVEL_01",DATA_RASIC!AV11,""))))))) -> SE | O18: =IF($B$4="Assembly or Component Provider",DATA_RASIC!U11,IF($B$4="Consultancy Component Provider",DATA_RASIC!AB11,IF($B$4="Make to Print",DATA_RASIC!AI11,IF($B$4="Engineering Service Provider",DATA_RASIC!G11,IF($B$4="Full System Provider",DATA_RASIC!N11,IF($B$4="ESP_DOOR TRIM",DATA_RASIC!AP11,IF($B$4="ESP_Partner_LEVEL_01",DATA_RASIC!AW11,""))))))) -> - | P18: =IF($B$4="Assembly or Component Provider",DATA_RASIC!V11,IF($B$4="Consultancy Component Provider",DATA_RASIC!AC11,IF($B$4="Make to Print",DATA_RASIC!AJ11,IF($B$4="Engineering Service Provider",DATA_RASIC!H11,IF($B$4="Full System Provider",DATA_RASIC!O11,IF($B$4="ESP_DOOR TRIM",DATA_RASIC!AQ11,IF($B$4="ESP_Partner_LEVEL_01",DATA_RASIC!AX11,""))))))) -> -
A19: =IF($B$4="Assembly or Component Provider",DATA_RASIC_DESC!A12,IF($B$4="Consultancy Component Provider",DATA_RASIC_DESC!A12,IF($B$4="Make to Print",DATA_RASIC_DESC!A12,IF($B$4="Engineering Service Provider",DATA_RASIC_DESC!A12,IF($B$4="Full System Provider",DATA_RASIC_DESC!A12,IF($B$4="ESP_DOOR TRIM",DATA_RASIC_DESC!D12,IF($B$4="ESP_Partner_LEVEL_01",DATA_RASIC_DESC!G12,""))))))) -> PM.10 | B19: =IF($B$4="Assembly or Component Provider",DATA_RASIC_DESC!B12,IF($B$4="Consultancy Component Provider",DATA_RASIC_DESC!B12,IF($B$4="Make to Print",DATA_RASIC_DESC!B12,IF($B$4="Engineering Service Provider",DATA_RASIC_DESC!B12,IF($B$4="Full System Provider",DATA_RASIC_DESC!B12,IF($B$4="ESP_DOOR TRIM",DATA_RASIC_DESC!E12,IF($B$4="ESP_Partner_LEVEL_01",DATA_RASIC_DESC!H12,""))))))) -> Facilitate resolution of system, subsystem, assembly and component interfaces issues including removal & repair | K19: =IF($B$4="Assembly or Component Provider",DATA_RASIC!Q12,IF($B$4="Consultancy Component Provider",DATA_RASIC!X12,IF($B$4="Make to Print",DATA_RASIC!AE12,IF($B$4="Engineering Service Provider",DATA_RASIC!C12,IF($B$4="Full System Provider",DATA_RASIC!J12,IF($B$4="ESP_DOOR TRIM",DATA_RASIC!AL12,IF($B$4="ESP_Partner_LEVEL_01",DATA_RASIC!AS12,""))))))) -> JLR | L19: =IF($B$4="Assembly or Component Provider",DATA_RASIC!R12,IF($B$4="Consultancy Component Provider",DATA_RASIC!Y12,IF($B$4="Make to Print",DATA_RASIC!AF12,IF($B$4="Engineering Service Provider",DATA_RASIC!D12,IF($B$4="Full System Provider",DATA_RASIC!K12,IF($B$4="ESP_DOOR TRIM",DATA_RASIC!AM12,IF($B$4="ESP_Partner_LEVEL_01",DATA_RASIC!AT12,""))))))) -> JLR | M19: =IF($B$4="Assembly or Component Provider",DATA_RASIC!S12,IF($B$4="Consultancy Component Provider",DATA_RASIC!Z12,IF($B$4="Make to Print",DATA_RASIC!AG12,IF($B$4="Engineering Service Provider",DATA_RASIC!E12,IF($B$4="Full System Provider",DATA_RASIC!L12,IF($B$4="ESP_DOOR TRIM",DATA_RASIC!AN12,IF($B$4="ESP_Partner_LEVEL_01",DATA_RASIC!AU12,""))))))) -> JLR | N19: =IF($B$4="Assembly or Component Provider",DATA_RASIC!T12,IF($B$4="Consultancy Component Provider",DATA_RASIC!AA12,IF($B$4="Make to Print",DATA_RASIC!AH12,IF($B$4="Engineering Service Provider",DATA_RASIC!F12,IF($B$4="Full System Provider",DATA_RASIC!M12,IF($B$4="ESP_DOOR TRIM",DATA_RASIC!AO12,IF($B$4="ESP_Partner_LEVEL_01",DATA_RASIC!AV12,""))))))) -> SE | O19: =IF($B$4="Assembly or Component Provider",DATA_RASIC!U12,IF($B$4="Consultancy Component Provider",DATA_RASIC!AB12,IF($B$4="Make to Print",DATA_RASIC!AI12,IF($B$4="Engineering Service Provider",DATA_RASIC!G12,IF($B$4="Full System Provider",DATA_RASIC!N12,IF($B$4="ESP_DOOR TRIM",DATA_RASIC!AP12,IF($B$4="ESP_Partner_LEVEL_01",DATA_RASIC!AW12,""))))))) -> - | P19: =IF($B$4="Assembly or Component Provider",DATA_RASIC!V12,IF($B$4="Consultancy Component Provider",DATA_RASIC!AC12,IF($B$4="Make to Print",DATA_RASIC!AJ12,IF($B$4="Engineering Service Provider",DATA_RASIC!H12,IF($B$4="Full System Provider",DATA_RASIC!O12,IF($B$4="ESP_DOOR TRIM",DATA_RASIC!AQ12,IF($B$4="ESP_Partner_LEVEL_01",DATA_RASIC!AX12,""))))))) -> -
A20: =IF($B$4="Assembly or Component Provider",DATA_RASIC_DESC!A13,IF($B$4="Consultancy Component Provider",DATA_RASIC_DESC!A13,IF($B$4="Make to Print",DATA_RASIC_DESC!A13,IF($B$4="Engineering Service Provider",DATA_RASIC_DESC!A13,IF($B$4="Full System Provider",DATA_RASIC_DESC!A13,IF($B$4="ESP_DOOR TRIM",DATA_RASIC_DESC!D13,IF($B$4="ESP_Partner_LEVEL_01",DATA_RASIC_DESC!G13,""))))))) -> PM.11 | B20: =IF($B$4="Assembly or Component Provider",DATA_RASIC_DESC!B13,IF($B$4="Consultancy Component Provider",DATA_RASIC_DESC!B13,IF($B$4="Make to Print",DATA_RASIC_DESC!B13,IF($B$4="Engineering Service Provider",DATA_RASIC_DESC!B13,IF($B$4="Full System Provider",DATA_RASIC_DESC!B13,IF($B$4="ESP_DOOR TRIM",DATA_RASIC_DESC!E13,IF($B$4="ESP_Partner_LEVEL_01",DATA_RASIC_DESC!H13,""))))))) -> Support Jaguar Land Rover's business processes, including change management meetings and/or open issues lists (including AIMS) | K20: =IF($B$4="Assembly or Component Provider",DATA_RASIC!Q13,IF($B$4="Consultancy Component Provider",DATA_RASIC!X13,IF($B$4="Make to Print",DATA_RASIC!AE13,IF($B$4="Engineering Service Provider",DATA_RASIC!C13,IF($B$4="Full System Provider",DATA_RASIC!J13,IF($B$4="ESP_DOOR TRIM",DATA_RASIC!AL13,IF($B$4="ESP_Partner_LEVEL_01",DATA_RASIC!AS13,""))))))) -> SE | L20: =IF($B$4="Assembly or Component Provider",DATA_RASIC!R13,IF($B$4="Consultancy Component Provider",DATA_RASIC!Y13,IF($B$4="Make to Print",DATA_RASIC!AF13,IF($B$4="Engineering Service Provider",DATA_RASIC!D13,IF($B$4="Full System Provider",DATA_RASIC!K13,IF($B$4="ESP_DOOR TRIM",DATA_RASIC!AM13,IF($B$4="ESP_Partner_LEVEL_01",DATA_RASIC!AT13,""))))))) -> SE | M20: =IF($B$4="Assembly or Component Provider",DATA_RASIC!S13,IF($B$4="Consultancy Component Provider",DATA_RASIC!Z13,IF($B$4="Make to Print",DATA_RASIC!AG13,IF($B$4="Engineering Service Provider",DATA_RASIC!E13,IF($B$4="Full System Provider",DATA_RASIC!L13,IF($B$4="ESP_DOOR TRIM",DATA_RASIC!AN13,IF($B$4="ESP_Partner_LEVEL_01",DATA_RASIC!AU13,""))))))) -> JLR | N20: =IF($B$4="Assembly or Component Provider",DATA_RASIC!T13,IF($B$4="Consultancy Component Provider",DATA_RASIC!AA13,IF($B$4="Make to Print",DATA_RASIC!AH13,IF($B$4="Engineering Service Provider",DATA_RASIC!F13,IF($B$4="Full System Provider",DATA_RASIC!M13,IF($B$4="ESP_DOOR TRIM",DATA_RASIC!AO13,IF($B$4="ESP_Partner_LEVEL_01",DATA_RASIC!AV13,""))))))) -> JLR | O20: =IF($B$4="Assembly or Component Provider",DATA_RASIC!U13,IF($B$4="Consultancy Component Provider",DATA_RASIC!AB13,IF($B$4="Make to Print",DATA_RASIC!AI13,IF($B$4="Engineering Service Provider",DATA_RASIC!G13,IF($B$4="Full System Provider",DATA_RASIC!N13,IF($B$4="ESP_DOOR TRIM",DATA_RASIC!AP13,IF($B$4="ESP_Partner_LEVEL_01",DATA_RASIC!AW13,""))))))) -> - | P20: =IF($B$4="Assembly or Component Provider",DATA_RASIC!V13,IF($B$4="Consultancy Component Provider",DATA_RASIC!AC13,IF($B$4="Make to Print",DATA_RASIC!AJ13,IF($B$4="Engineering Service Provider",DATA_RASIC!H13,IF($B$4="Full System Provider",DATA_RASIC!O13,IF($B$4="ESP_DOOR TRIM",DATA_RASIC!AQ13,IF($B$4="ESP_Partner_LEVEL_01",DATA_RASIC!AX13,""))))))) -> -
A21: =IF($B$4="Assembly or Component Provider",DATA_RASIC_DESC!A14,IF($B$4="Consultancy Component Provider",DATA_RASIC_DESC!A14,IF($B$4="Make to Print",DATA_RASIC_DESC!A14,IF($B$4="Engineering Service Provider",DATA_RASIC_DESC!A14,IF($B$4="Full System Provider",DATA_RASIC_DESC!A14,IF($B$4="ESP_DOOR TRIM",DATA_RASIC_DESC!D14,IF($B$4="ESP_Partner_LEVEL_01",DATA_RASIC_DESC!G14,""))))))) -> PM.12 | B21: =IF($B$4="Assembly or Component Provider",DATA_RASIC_DESC!B14,IF($B$4="Consultancy Component Provider",DATA_RASIC_DESC!B14,IF($B$4="Make to Print",DATA_RASIC_DESC!B14,IF($B$4="Engineering Service Provider",DATA_RASIC_DESC!B14,IF($B$4="Full System Provider",DATA_RASIC_DESC!B14,IF($B$4="ESP_DOOR TRIM",DATA_RASIC_DESC!E14,IF($B$4="ESP_Partner_LEVEL_01",DATA_RASIC_DESC!H14,""))))))) -> Obtain Jaguar Land Rover's approval for all changes and implement the approved changes using a robust 'manage the change' process | K21: =IF($B$4="Assembly or Component Provider",DATA_RASIC!Q14,IF($B$4="Consultancy Component Provider",DATA_RASIC!X14,IF($B$4="Make to Print",DATA_RASIC!AE14,IF($B$4="Engineering Service Provider",DATA_RASIC!C14,IF($B$4="Full System Provider",DATA_RASIC!J14,IF($B$4="ESP_DOOR TRIM",DATA_RASIC!AL14,IF($B$4="ESP_Partner_LEVEL_01",DATA_RASIC!AS14,""))))))) -> SE | L21: =IF($B$4="Assembly or Component Provider",DATA_RASIC!R14,IF($B$4="Consultancy Component Provider",DATA_RASIC!Y14,IF($B$4="Make to Print",DATA_RASIC!AF14,IF($B$4="Engineering Service Provider",DATA_RASIC!D14,IF($B$4="Full System Provider",DATA_RASIC!K14,IF($B$4="ESP_DOOR TRIM",DATA_RASIC!AM14,IF($B$4="ESP_Partner_LEVEL_01",DATA_RASIC!AT14,""))))))) -> SE | M21: =IF($B$4="Assembly or Component Provider",DATA_RASIC!S14,IF($B$4="Consultancy Component Provider",DATA_RASIC!Z14,IF($B$4="Make to Print",DATA_RASIC!AG14,IF($B$4="Engineering Service Provider",DATA_RASIC!E14,IF($B$4="Full System Provider",DATA_RASIC!L14,IF($B$4="ESP_DOOR TRIM",DATA_RASIC!AN14,IF($B$4="ESP_Partner_LEVEL_01",DATA_RASIC!AU14,""))))))) -> JLR | N21: =IF($B$4="Assembly or Component Provider",DATA_RASIC!T14,IF($B$4="Consultancy Component Provider",DATA_RASIC!AA14,IF($B$4="Make to Print",DATA_RASIC!AH14,IF($B$4="Engineering Service Provider",DATA_RASIC!F14,IF($B$4="Full System Provider",DATA_RASIC!M14,IF($B$4="ESP_DOOR TRIM",DATA_RASIC!AO14,IF($B$4="ESP_Partner_LEVEL_01",DATA_RASIC!AV14,""))))))) -> JLR | O21: =IF($B$4="Assembly or Component Provider",DATA_RASIC!U14,IF($B$4="Consultancy Component Provider",DATA_RASIC!AB14,IF($B$4="Make to Print",DATA_RASIC!AI14,IF($B$4="Engineering Service Provider",DATA_RASIC!G14,IF($B$4="Full System Provider",DATA_RASIC!N14,IF($B$4="ESP_DOOR TRIM",DATA_RASIC!AP14,IF($B$4="ESP_Partner_LEVEL_01",DATA_RASIC!AW14,""))))))) -> - | P21: =IF($B$4="Assembly or Component Provider",DATA_RASIC!V14,IF($B$4="Consultancy Component Provider",DATA_RASIC!AC14,IF($B$4="Make to Print",DATA_RASIC!AJ14,IF($B$4="Engineering Service Provider",DATA_RASIC!H14,IF($B$4="Full System Provider",DATA_RASIC!O14,IF($B$4="ESP_DOOR TRIM",DATA_RASIC!AQ14,IF($B$4="ESP_Partner_LEVEL_01",DATA_RASIC!AX14,""))))))) -> -
... A35: =IF($B$4="Assembly or Component Provider",DATA_RASIC_DESC!A28,IF($B$4="Consultancy Component Provider",DATA_RASIC_DESC!A28,IF($B$4="Make to Print",DATA_RASIC_DESC!A28,IF($B$4="Engineering Service Provider",DATA_RASIC_DESC!A28,IF($B$4="Full System Provider",DATA_RASIC_DESC!A28,IF($B$4="ESP_DOOR TRIM",DATA_RASIC_DESC!D28,IF($B$4="ESP_Partner_LEVEL_01",DATA_RASIC_DESC!G28,""))))))) -> - | B35: =IF($B$4="Assembly or Component Provider",DATA_RASIC_DESC!B28,IF($B$4="Consultancy Component Provider",DATA_RASIC_DESC!B28,IF($B$4="Make to Print",DATA_RASIC_DESC!B28,IF($B$4="Engineering Service Provider",DATA_RASIC_DESC!B28,IF($B$4="Full System Provider",DATA_RASIC_DESC!B28,IF($B$4="ESP_DOOR TRIM",DATA_RASIC_DESC!E28,IF($B$4="ESP_Partner_LEVEL_01",DATA_RASIC_DESC!H28,""))))))) -> Reserved | K35: =IF($B$4="Assembly or Component Provider",DATA_RASIC!Q28,IF($B$4="Consultancy Component Provider",DATA_RASIC!X28,IF($B$4="Make to Print",DATA_RASIC!AE28,IF($B$4="Engineering Service Provider",DATA_RASIC!C28,IF($B$4="Full System Provider",DATA_RASIC!J28,IF($B$4="ESP_DOOR TRIM",DATA_RASIC!AL28,IF($B$4="ESP_Partner_LEVEL_01",DATA_RASIC!AS28,""))))))) -> N/A | L35: =IF($B$4="Assembly or Component Provider",DATA_RASIC!R28,IF($B$4="Consultancy Component Provider",DATA_RASIC!Y28,IF($B$4="Make to Print",DATA_RASIC!AF28,IF($B$4="Engineering Service Provider",DATA_RASIC!D28,IF($B$4="Full System Provider",DATA_RASIC!K28,IF($B$4="ESP_DOOR TRIM",DATA_RASIC!AM28,IF($B$4="ESP_Partner_LEVEL_01",DATA_RASIC!AT28,""))))))) -> - | M35: =IF($B$4="Assembly or Component Provider",DATA_RASIC!S28,IF($B$4="Consultancy Component Provider",DATA_RASIC!Z28,IF($B$4="Make to Print",DATA_RASIC!AG28,IF($B$4="Engineering Service Provider",DATA_RASIC!E28,IF($B$4="Full System Provider",DATA_RASIC!L28,IF($B$4="ESP_DOOR TRIM",DATA_RASIC!AN28,IF($B$4="ESP_Partner_LEVEL_01",DATA_RASIC!AU28,""))))))) -> - | N35: =IF($B$4="Assembly or Component Provider",DATA_RASIC!T28,IF($B$4="Consultancy Component Provider",DATA_RASIC!AA28,IF($B$4="Make to Print",DATA_RASIC!AH28,IF($B$4="Engineering Service Provider",DATA_RASIC!F28,IF($B$4="Full System Provider",DATA_RASIC!M28,IF($B$4="ESP_DOOR TRIM",DATA_RASIC!AO28,IF($B$4="ESP_Partner_LEVEL_01",DATA_RASIC!AV28,""))))))) -> - | O35: =IF($B$4="Assembly or Component Provider",DATA_RASIC!U28,IF($B$4="Consultancy Component Provider",DATA_RASIC!AB28,IF($B$4="Make to Print",DATA_RASIC!AI28,IF($B$4="Engineering Service Provider",DATA_RASIC!G28,IF($B$4="Full System Provider",DATA_RASIC!N28,IF($B$4="ESP_DOOR TRIM",DATA_RASIC!AP28,IF($B$4="ESP_Partner_LEVEL_01",DATA_RASIC!AW28,""))))))) -> - | P35: =IF($B$4="Assembly or Component Provider",DATA_RASIC!V28,IF($B$4="Consultancy Component Provider",DATA_RASIC!AC28,IF($B$4="Make to Print",DATA_RASIC!AJ28,IF($B$4="Engineering Service Provider",DATA_RASIC!H28,IF($B$4="Full System Provider",DATA_RASIC!O28,IF($B$4="ESP_DOOR TRIM",DATA_RASIC!AQ28,IF($B$4="ESP_Partner_LEVEL_01",DATA_RASIC!AX28,""))))))) -> -
A36: [MB] MARKETING AND BENCHMARKING | K36: APPLICABLE TO SOURCING PROJECT: | O36: APPLICABLE
A37: ID | B37: DESCRIPTION OF TASK | K37: Lead | L37: R | M37: A | N37: S | O37: I | P37: C
A38: =IF($B$4="Assembly or Component Provider",DATA_RASIC_DESC!A31,IF($B$4="Consultancy Component Provider",DATA_RASIC_DESC!A31,IF($B$4="Make to Print",DATA_RASIC_DESC!A31,IF($B$4="Engineering Service Provider",DATA_RASIC_DESC!A31,IF($B$4="Full System Provider",DATA_RASIC_DESC!A31,IF($B$4="ESP_DOOR TRIM",DATA_RASIC_DESC!D31,IF($B$4="ESP_Partner_LEVEL_01",DATA_RASIC_DESC!G31,""))))))) -> MB.1 | B38: =IF($B$4="Assembly or Component Provider",DATA_RASIC_DESC!B31,IF($B$4="Consultancy Component Provider",DATA_RASIC_DESC!B31,IF($B$4="Make to Print",DATA_RASIC_DESC!B31,IF($B$4="Engineering Service Provider",DATA_RASIC_DESC!B31,IF($B$4="Full System Provider",DATA_RASIC_DESC!B31,IF($B$4="ESP_DOOR TRIM",DATA_RASIC_DESC!E31,IF($B$4="ESP_Partner_LEVEL_01",DATA_RASIC_DESC!H31,""))))))) -> Define market and competitive vehicles | K38: =IF($B$4="Assembly or Component Provider",DATA_RASIC!Q32,IF($B$4="Consultancy Component Provider",DATA_RASIC!X32,IF($B$4="Make to Print",DATA_RASIC!AE32,IF($B$4="Engineering Service Provider",DATA_RASIC!C32,IF($B$4="Full System Provider",DATA_RASIC!J32,IF($B$4="ESP_DOOR TRIM",DATA_RASIC!AL32,IF($B$4="ESP_Partner_LEVEL_01",DATA_RASIC!AS32,""))))))) -> JLR | L38: =IF($B$4="Assembly or Component Provider",DATA_RASIC!R32,IF($B$4="Consultancy Component Provider",DATA_RASIC!Y32,IF($B$4="Make to Print",DATA_RASIC!AF32,IF($B$4="Engineering Service Provider",DATA_RASIC!D32,IF($B$4="Full System Provider",DATA_RASIC!K32,IF($B$4="ESP_DOOR TRIM",DATA_RASIC!AM32,IF($B$4="ESP_Partner_LEVEL_01",DATA_RASIC!AT32,""))))))) -> JLR | M38: =IF($B$4="Assembly or Component Provider",DATA_RASIC!S32,IF($B$4="Consultancy Component Provider",DATA_RASIC!Z32,IF($B$4="Make to Print",DATA_RASIC!AG32,IF($B$4="Engineering Service Provider",DATA_RASIC!E32,IF($B$4="Full System Provider",DATA_RASIC!L32,IF($B$4="ESP_DOOR TRIM",DATA_RASIC!AN32,IF($B$4="ESP_Partner_LEVEL_01",DATA_RASIC!AU32,""))))))) -> JLR | N38: =IF($B$4="Assembly or Component Provider",DATA_RASIC!T32,IF($B$4="Consultancy Component Provider",DATA_RASIC!AA32,IF($B$4="Make to Print",DATA_RASIC!AH32,IF($B$4="Engineering Service Provider",DATA_RASIC!F32,IF($B$4="Full System Provider",DATA_RASIC!M32,IF($B$4="ESP_DOOR TRIM",DATA_RASIC!AO32,IF($B$4="ESP_Partner_LEVEL_01",DATA_RASIC!AV32,""))))))) -> - | O38: =IF($B$4="Assembly or Component Provider",DATA_RASIC!U32,IF($B$4="Consultancy Component Provider",DATA_RASIC!AB32,IF($B$4="Make to Print",DATA_RASIC!AI32,IF($B$4="Engineering Service Provider",DATA_RASIC!G32,IF($B$4="Full System Provider",DATA_RASIC!N32,IF($B$4="ESP_DOOR TRIM",DATA_RASIC!AP32,IF($B$4="ESP_Partner_LEVEL_01",DATA_RASIC!AW32,""))))))) -> SE | P38: =IF($B$4="Assembly or Component Provider",DATA_RASIC!V32,IF($B$4="Consultancy Component Provider",DATA_RASIC!AC32,IF($B$4="Make to Print",DATA_RASIC!AJ32,IF($B$4="Engineering Service Provider",DATA_RASIC!H32,IF($B$4="Full System Provider",DATA_RASIC!O32,IF($B$4="ESP_DOOR TRIM",DATA_RASIC!AQ32,IF($B$4="ESP_Partner_LEVEL_01",DATA_RASIC!AX32,""))))))) -> -
A39: =IF($B$4="Assembly or Component Provider",DATA_RASIC_DESC!A32,IF($B$4="Consultancy Component Provider",DATA_RASIC_DESC!A32,IF($B$4="Make to Print",DATA_RASIC_DESC!A32,IF($B$4="Engineering Service Provider",DATA_RASIC_DESC!A32,IF($B$4="Full System Provider",DATA_RASIC_DESC!A32,IF($B$4="ESP_DOOR TRIM",DATA_RASIC_DESC!D32,IF($B$4="ESP_Partner_LEVEL_01",DATA_RASIC_DESC!G32,""))))))) -> MB.2 | B39: =IF($B$4="Assembly or Component Provider",DATA_RASIC_DESC!B32,IF($B$4="Consultancy Component Provider",DATA_RASIC_DESC!B32,IF($B$4="Make to Print",DATA_RASIC_DESC!B32,IF($B$4="Engineering Service Provider",DATA_RASIC_DESC!B32,IF($B$4="Full System Provider",DATA_RASIC_DESC!B32,IF($B$4="ESP_DOOR TRIM",DATA_RASIC_DESC!E32,IF($B$4="ESP_Partner_LEVEL_01",DATA_RASIC_DESC!H32,""))))))) -> Share competitive vehicle benchmarking information | K39: =IF($B$4="Assembly or Component Provider",DATA_RASIC!Q33,IF($B$4="Consultancy Component Provider",DATA_RASIC!X33,IF($B$4="Make to Print",DATA_RASIC!AE33,IF($B$4="Engineering Service Provider",DATA_RASIC!C33,IF($B$4="Full System Provider",DATA_RASIC!J33,IF($B$4="ESP_DOOR TRIM",DATA_RASIC!AL33,IF($B$4="ESP_Partner_LEVEL_01",DATA_RASIC!AS33,""))))))) -> JLR | L39: =IF($B$4="Assembly or Component Provider",DATA_RASIC!R33,IF($B$4="Consultancy Component Provider",DATA_RASIC!Y33,IF($B$4="Make to Print",DATA_RASIC!AF33,IF($B$4="Engineering Service Provider",DATA_RASIC!D33,IF($B$4="Full System Provider",DATA_RASIC!K33,IF($B$4="ESP_DOOR TRIM",DATA_RASIC!AM33,IF($B$4="ESP_Partner_LEVEL_01",DATA_RASIC!AT33,""))))))) -> JLR | M39: =IF($B$4="Assembly or Component Provider",DATA_RASIC!S33,IF($B$4="Consultancy Component Provider",DATA_RASIC!Z33,IF($B$4="Make to Print",DATA_RASIC!AG33,IF($B$4="Engineering Service Provider",DATA_RASIC!E33,IF($B$4="Full System Provider",DATA_RASIC!L33,IF($B$4="ESP_DOOR TRIM",DATA_RASIC!AN33,IF($B$4="ESP_Partner_LEVEL_01",DATA_RASIC!AU33,""))))))) -> JLR | N39: =IF($B$4="Assembly or Component Provider",DATA_RASIC!T33,IF($B$4="Consultancy Component Provider",DATA_RASIC!AA33,IF($B$4="Make to Print",DATA_RASIC!AH33,IF($B$4="Engineering Service Provider",DATA_RASIC!F33,IF($B$4="Full System Provider",DATA_RASIC!M33,IF($B$4="ESP_DOOR TRIM",DATA_RASIC!AO33,IF($B$4="ESP_Partner_LEVEL_01",DATA_RASIC!AV33,""))))))) -> - | O39: =IF($B$4="Assembly or Component Provider",DATA_RASIC!U33,IF($B$4="Consultancy Component Provider",DATA_RASIC!AB33,IF($B$4="Make to Print",DATA_RASIC!AI33,IF($B$4="Engineering Service Provider",DATA_RASIC!G33,IF($B$4="Full System Provider",DATA_RASIC!N33,IF($B$4="ESP_DOOR TRIM",DATA_RASIC!AP33,IF($B$4="ESP_Partner_LEVEL_01",DATA_RASIC!AW33,""))))))) -> SE | P39: =IF($B$4="Assembly or Component Provider",DATA_RASIC!V33,IF($B$4="Consultancy Component Provider",DATA_RASIC!AC33,IF($B$4="Make to Print",DATA_RASIC!AJ33,IF($B$4="Engineering Service Provider",DATA_RASIC!H33,IF($B$4="Full System Provider",DATA_RASIC!O33,IF($B$4="ESP_DOOR TRIM",DATA_RASIC!AQ33,IF($B$4="ESP_Partner_LEVEL_01",DATA_RASIC!AX33,""))))))) -> -
A40: =IF($B$4="Assembly or Component Provider",DATA_RASIC_DESC!A33,IF($B$4="Consultancy Component Provider",DATA_RASIC_DESC!A33,IF($B$4="Make to Print",DATA_RASIC_DESC!A33,IF($B$4="Engineering Service Provider",DATA_RASIC_DESC!A33,IF($B$4="Full System Provider",DATA_RASIC_DESC!A33,IF($B$4="ESP_DOOR TRIM",DATA_RASIC_DESC!D33,IF($B$4="ESP_Partner_LEVEL_01",DATA_RASIC_DESC!G33,""))))))) -> MB.3 | B40: =IF($B$4="Assembly or Component Provider",DATA_RASIC_DESC!B33,IF($B$4="Consultancy Component Provider",DATA_RASIC_DESC!B33,IF($B$4="Make to Print",DATA_RASIC_DESC!B33,IF($B$4="Engineering Service Provider",DATA_RASIC_DESC!B33,IF($B$4="Full System Provider",DATA_RASIC_DESC!B33,IF($B$4="ESP_DOOR TRIM",DATA_RASIC_DESC!E33,IF($B$4="ESP_Partner_LEVEL_01",DATA_RASIC_DESC!H33,""))))))) -> Provide customer desired attributes as required ; e.g. QFD / PALS / Kano | K40: =IF($B$4="Assembly or Component Provider",DATA_RASIC!Q34,IF($B$4="Consultancy Component Provider",DATA_RASIC!X34,IF($B$4="Make to Print",DATA_RASIC!AE34,IF($B$4="Engineering Service Provider",DATA_RASIC!C34,IF($B$4="Full System Provider",DATA_RASIC!J34,IF($B$4="ESP_DOOR TRIM",DATA_RASIC!AL34,IF($B$4="ESP_Partner_LEVEL_01",DATA_RASIC!AS34,""))))))) -> JLR | L40: =IF($B$4="Assembly or Component Provider",DATA_RASIC!R34,IF($B$4="Consultancy Component Provider",DATA_RASIC!Y34,IF($B$4="Make to Print",DATA_RASIC!AF34,IF($B$4="Engineering Service Provider",DATA_RASIC!D34,IF($B$4="Full System Provider",DATA_RASIC!K34,IF($B$4="ESP_DOOR TRIM",DATA_RASIC!AM34,IF($B$4="ESP_Partner_LEVEL_01",DATA_RASIC!AT34,""))))))) -> JLR | M40: =IF($B$4="Assembly or Component Provider",DATA_RASIC!S34,IF($B$4="Consultancy Component Provider",DATA_RASIC!Z34,IF($B$4="Make to Print",DATA_RASIC!AG34,IF($B$4="Engineering Service Provider",DATA_RASIC!E34,IF($B$4="Full System Provider",DATA_RASIC!L34,IF($B$4="ESP_DOOR TRIM",DATA_RASIC!AN34,IF($B$4="ESP_Partner_LEVEL_01",DATA_RASIC!AU34,""))))))) -> JLR | N40: =IF($B$4="Assembly or Component Provider",DATA_RASIC!T34,IF($B$4="Consultancy Component Provider",DATA_RASIC!AA34,IF($B$4="Make to Print",DATA_RASIC!AH34,IF($B$4="Engineering Service Provider",DATA_RASIC!F34,IF($B$4="Full System Provider",DATA_RASIC!M34,IF($B$4="ESP_DOOR TRIM",DATA_RASIC!AO34,IF($B$4="ESP_Partner_LEVEL_01",DATA_RASIC!AV34,""))))))) -> - | O40: =IF($B$4="Assembly or Component Provider",DATA_RASIC!U34,IF($B$4="Consultancy Component Provider",DATA_RASIC!AB34,IF($B$4="Make to Print",DATA_RASIC!AI34,IF($B$4="Engineering Service Provider",DATA_RASIC!G34,IF($B$4="Full System Provider",DATA_RASIC!N34,IF($B$4="ESP_DOOR TRIM",DATA_RASIC!AP34,IF($B$4="ESP_Partner_LEVEL_01",DATA_RASIC!AW34,""))))))) -> SE | P40: =IF($B$4="Assembly or Component Provider",DATA_RASIC!V34,IF($B$4="Consultancy Component Provider",DATA_RASIC!AC34,IF($B$4="Make to Print",DATA_RASIC!AJ34,IF($B$4="Engineering Service Provider",DATA_RASIC!H34,IF($B$4="Full System Provider",DATA_RASIC!O34,IF($B$4="ESP_DOOR TRIM",DATA_RASIC!AQ34,IF($B$4="ESP_Partner_LEVEL_01",DATA_RASIC!AX34,""))))))) -> -
A41: =IF($B$4="Assembly or Component Provider",DATA_RASIC_DESC!A34,IF($B$4="Consultancy Component Provider",DATA_RASIC_DESC!A34,IF($B$4="Make to Print",DATA_RASIC_DESC!A34,IF($B$4="Engineering Service Provider",DATA_RASIC_DESC!A34,IF($B$4="Full System Provider",DATA_RASIC_DESC!A34,IF($B$4="ESP_DOOR TRIM",DATA_RASIC_DESC!D34,IF($B$4="ESP_Partner_LEVEL_01",DATA_RASIC_DESC!G34,""))))))) -> MB.4 | B41: =IF($B$4="Assembly or Component Provider",DATA_RASIC_DESC!B34,IF($B$4="Consultancy Component Provider",DATA_RASIC_DESC!B34,IF($B$4="Make to Print",DATA_RASIC_DESC!B34,IF($B$4="Engineering Service Provider",DATA_RASIC_DESC!B34,IF($B$4="Full System Provider",DATA_RASIC_DESC!B34,IF($B$4="ESP_DOOR TRIM",DATA_RASIC_DESC!E34,IF($B$4="ESP_Partner_LEVEL_01",DATA_RASIC_DESC!H34,""))))))) -> Provide commodity benchmarking information as required | K41: =IF($B$4="Assembly or Component Provider",DATA_RASIC!Q35,IF($B$4="Consultancy Component Provider",DATA_RASIC!X35,IF($B$4="Make to Print",DATA_RASIC!AE35,IF($B$4="Engineering Service Provider",DATA_RASIC!C35,IF($B$4="Full System Provider",DATA_RASIC!J35,IF($B$4="ESP_DOOR TRIM",DATA_RASIC!AL35,IF($B$4="ESP_Partner_LEVEL_01",DATA_RASIC!AS35,""))))))) -> JLR | L41: =IF($B$4="Assembly or Component Provider",DATA_RASIC!R35,IF($B$4="Consultancy Component Provider",DATA_RASIC!Y35,IF($B$4="Make to Print",DATA_RASIC!AF35,IF($B$4="Engineering Service Provider",DATA_RASIC!D35,IF($B$4="Full System Provider",DATA_RASIC!K35,IF($B$4="ESP_DOOR TRIM",DATA_RASIC!AM35,IF($B$4="ESP_Partner_LEVEL_01",DATA_RASIC!AT35,""))))))) -> JLR | M41: =IF($B$4="Assembly or Component Provider",DATA_RASIC!S35,IF($B$4="Consultancy Component Provider",DATA_RASIC!Z35,IF($B$4="Make to Print",DATA_RASIC!AG35,IF($B$4="Engineering Service Provider",DATA_RASIC!E35,IF($B$4="Full System Provider",DATA_RASIC!L35,IF($B$4="ESP_DOOR TRIM",DATA_RASIC!AN35,IF($B$4="ESP_Partner_LEVEL_01",DATA_RASIC!AU35,""))))))) -> JLR | N41: =IF($B$4="Assembly or Component Provider",DATA_RASIC!T35,IF($B$4="Consultancy Component Provider",DATA_RASIC!AA35,IF($B$4="Make to Print",DATA_RASIC!AH35,IF($B$4="Engineering Service Provider",DATA_RASIC!F35,IF($B$4="Full System Provider",DATA_RASIC!M35,IF($B$4="ESP_DOOR TRIM",DATA_RASIC!AO35,IF($B$4="ESP_Partner_LEVEL_01",DATA_RASIC!AV35,""))))))) -> - | O41: =IF($B$4="Assembly or Component Provider",DATA_RASIC!U35,IF($B$4="Consultancy Component Provider",DATA_RASIC!AB35,IF($B$4="Make to Print",DATA_RASIC!AI35,IF($B$4="Engineering Service Provider",DATA_RASIC!G35,IF($B$4="Full System Provider",DATA_RASIC!N35,IF($B$4="ESP_DOOR TRIM",DATA_RASIC!AP35,IF($B$4="ESP_Partner_LEVEL_01",DATA_RASIC!AW35,""))))))) -> SE | P41: =IF($B$4="Assembly or Component Provider",DATA_RASIC!V35,IF($B$4="Consultancy Component Provider",DATA_RASIC!AC35,IF($B$4="Make to Print",DATA_RASIC!AJ35,IF($B$4="Engineering Service Provider",DATA_RASIC!H35,IF($B$4="Full System Provider",DATA_RASIC!O35,IF($B$4="ESP_DOOR TRIM",DATA_RASIC!AQ35,IF($B$4="ESP_Partner_LEVEL_01",DATA_RASIC!AX35,""))))))) -> -
A42: =IF($B$4="Assembly or Component Provider",DATA_RASIC_DESC!A35,IF($B$4="Consultancy Component Provider",DATA_RASIC_DESC!A35,IF($B$4="Make to Print",DATA_RASIC_DESC!A35,IF($B$4="Engineering Service Provider",DATA_RASIC_DESC!A35,IF($B$4="Full System Provider",DATA_RASIC_DESC!A35,IF($B$4="ESP_DOOR TRIM",DATA_RASIC_DESC!D35,IF($B$4="ESP_Partner_LEVEL_01",DATA_RASIC_DESC!G35,""))))))) -> MB.5 | B42: =IF($B$4="Assembly or Component Provider",DATA_RASIC_DESC!B35,IF($B$4="Consultancy Component Provider",DATA_RASIC_DESC!B35,IF($B$4="Make to Print",DATA_RASIC_DESC!B35,IF($B$4="Engineering Service Provider",DATA_RASIC_DESC!B35,IF($B$4="Full System Provider",DATA_RASIC_DESC!B35,IF($B$4="ESP_DOOR TRIM",DATA_RASIC_DESC!E35,IF($B$4="ESP_Partner_LEVEL_01",DATA_RASIC_DESC!H35,""))))))) -> Provide competitive commodity teardown analysis | K42: =IF($B$4="Assembly or Component Provider",DATA_RASIC!Q36,IF($B$4="Consultancy Component Provider",DATA_RASIC!X36,IF($B$4="Make to Print",DATA_RASIC!AE36,IF($B$4="Engineering Service Provider",DATA_RASIC!C36,IF($B$4="Full System Provider",DATA_RASIC!J36,IF($B$4="ESP_DOOR TRIM",DATA_RASIC!AL36,IF($B$4="ESP_Partner_LEVEL_01",DATA_RASIC!AS36,""))))))) -> JLR | L42: =IF($B$4="Assembly or Component Provider",DATA_RASIC!R36,IF($B$4="Consultancy Component Provider",DATA_RASIC!Y36,IF($B$4="Make to Print",DATA_RASIC!AF36,IF($B$4="Engineering Service Provider",DATA_RASIC!D36,IF($B$4="Full System Provider",DATA_RASIC!K36,IF($B$4="ESP_DOOR TRIM",DATA_RASIC!AM36,IF($B$4="ESP_Partner_LEVEL_01",DATA_RASIC!AT36,""))))))) -> JLR | M42: =IF($B$4="Assembly or Component Provider",DATA_RASIC!S36,IF($B$4="Consultancy Component Provider",DATA_RASIC!Z36,IF($B$4="Make to Print",DATA_RASIC!AG36,IF($B$4="Engineering Service Provider",DATA_RASIC!E36,IF($B$4="Full System Provider",DATA_RASIC!L36,IF($B$4="ESP_DOOR TRIM",DATA_RASIC!AN36,IF($B$4="ESP_Partner_LEVEL_01",DATA_RASIC!AU36,""))))))) -> JLR | N42: =IF($B$4="Assembly or Component Provider",DATA_RASIC!T36,IF($B$4="Consultancy Component Provider",DATA_RASIC!AA36,IF($B$4="Make to Print",DATA_RASIC!AH36,IF($B$4="Engineering Service Provider",DATA_RASIC!F36,IF($B$4="Full System Provider",DATA_RASIC!M36,IF($B$4="ESP_DOOR TRIM",DATA_RASIC!AO36,IF($B$4="ESP_Partner_LEVEL_01",DATA_RASIC!AV36,""))))))) -> - | O42: =IF($B$4="Assembly or Component Provider",DATA_RASIC!U36,IF($B$4="Consultancy Component Provider",DATA_RASIC!AB36,IF($B$4="Make to Print",DATA_RASIC!AI36,IF($B$4="Engineering Service Provider",DATA_RASIC!G36,IF($B$4="Full System Provider",DATA_RASIC!N36,IF($B$4="ESP_DOOR TRIM",DATA_RASIC!AP36,IF($B$4="ESP_Partner_LEVEL_01",DATA_RASIC!AW36,""))))))) -> SE | P42: =IF($B$4="Assembly or Component Provider",DATA_RASIC!V36,IF($B$4="Consultancy Component Provider",DATA_RASIC!AC36,IF($B$4="Make to Print",DATA_RASIC!AJ36,IF($B$4="Engineering Service Provider",DATA_RASIC!H36,IF($B$4="Full System Provider",DATA_RASIC!O36,IF($B$4="ESP_DOOR TRIM",DATA_RASIC!AQ36,IF($B$4="ESP_Partner_LEVEL_01",DATA_RASIC!AX36,""))))))) -> SE
A43: =IF($B$4="Assembly or Component Provider",DATA_RASIC_DESC!A36,IF($B$4="Consultancy Component Provider",DATA_RASIC_DESC!A36,IF($B$4="Make to Print",DATA_RASIC_DESC!A36,IF($B$4="Engineering Service Provider",DATA_RASIC_DESC!A36,IF($B$4="Full System Provider",DATA_RASIC_DESC!A36,IF($B$4="ESP_DOOR TRIM",DATA_RASIC_DESC!D36,IF($B$4="ESP_Partner_LEVEL_01",DATA_RASIC_DESC!G36,""))))))) -> MB.6 | B43: =IF($B$4="Assembly or Component Provider",DATA_RASIC_DESC!B36,IF($B$4="Consultancy Component Provider",DATA_RASIC_DESC!B36,IF($B$4="Make to Print",DATA_RASIC_DESC!B36,IF($B$4="Engineering Service Provider",DATA_RASIC_DESC!B36,IF($B$4="Full System Provider",DATA_RASIC_DESC!B36,IF($B$4="ESP_DOOR TRIM",DATA_RASIC_DESC!E36,IF($B$4="ESP_Partner_LEVEL_01",DATA_RASIC_DESC!H36,""))))))) -> Develop Market Research Properties on styling as required | K43: =IF($B$4="Assembly or Component Provider",DATA_RASIC!Q37,IF($B$4="Consultancy Component Provider",DATA_RASIC!X37,IF($B$4="Make to Print",DATA_RASIC!AE37,IF($B$4="Engineering Service Provider",DATA_RASIC!C37,IF($B$4="Full System Provider",DATA_RASIC!J37,IF($B$4="ESP_DOOR TRIM",DATA_RASIC!AL37,IF($B$4="ESP_Partner_LEVEL_01",DATA_RASIC!AS37,""))))))) -> JLR | L43: =IF($B$4="Assembly or Component Provider",DATA_RASIC!R37,IF($B$4="Consultancy Component Provider",DATA_RASIC!Y37,IF($B$4="Make to Print",DATA_RASIC!AF37,IF($B$4="Engineering Service Provider",DATA_RASIC!D37,IF($B$4="Full System Provider",DATA_RASIC!K37,IF($B$4="ESP_DOOR TRIM",DATA_RASIC!AM37,IF($B$4="ESP_Partner_LEVEL_01",DATA_RASIC!AT37,""))))))) -> JLR | M43: =IF($B$4="Assembly or Component Provider",DATA_RASIC!S37,IF($B$4="Consultancy Component Provider",DATA_RASIC!Z37,IF($B$4="Make to Print",DATA_RASIC!AG37,IF($B$4="Engineering Service Provider",DATA_RASIC!E37,IF($B$4="Full System Provider",DATA_RASIC!L37,IF($B$4="ESP_DOOR TRIM",DATA_RASIC!AN37,IF($B$4="ESP_Partner_LEVEL_01",DATA_RASIC!AU37,""))))))) -> JLR | N43: =IF($B$4="Assembly or Component Provider",DATA_RASIC!T37,IF($B$4="Consultancy Component Provider",DATA_RASIC!AA37,IF($B$4="Make to Print",DATA_RASIC!AH37,IF($B$4="Engineering Service Provider",DATA_RASIC!F37,IF($B$4="Full System Provider",DATA_RASIC!M37,IF($B$4="ESP_DOOR TRIM",DATA_RASIC!AO37,IF($B$4="ESP_Partner_LEVEL_01",DATA_RASIC!AV37,""))))))) -> - | O43: =IF($B$4="Assembly or Component Provider",DATA_RASIC!U37,IF($B$4="Consultancy Component Provider",DATA_RASIC!AB37,IF($B$4="Make to Print",DATA_RASIC!AI37,IF($B$4="Engineering Service Provider",DATA_RASIC!G37,IF($B$4="Full System Provider",DATA_RASIC!N37,IF($B$4="ESP_DOOR TRIM",DATA_RASIC!AP37,IF($B$4="ESP_Partner_LEVEL_01",DATA_RASIC!AW37,""))))))) -> SE | P43: =IF($B$4="Assembly or Component Provider",DATA_RASIC!V37,IF($B$4="Consultancy Component Provider",DATA_RASIC!AC37,IF($B$4="Make to Print",DATA_RASIC!AJ37,IF($B$4="Engineering Service Provider",DATA_RASIC!H37,IF($B$4="Full System Provider",DATA_RASIC!O37,IF($B$4="ESP_DOOR TRIM",DATA_RASIC!AQ37,IF($B$4="ESP_Partner_LEVEL_01",DATA_RASIC!AX37,""))))))) -> SE
A44: =IF($B$4="Assembly or Component Provider",DATA_RASIC_DESC!A37,IF($B$4="Consultancy Component Provider",DATA_RASIC_DESC!A37,IF($B$4="Make to Print",DATA_RASIC_DESC!A37,IF($B$4="Engineering Service Provider",DATA_RASIC_DESC!A37,IF($B$4="Full System Provider",DATA_RASIC_DESC!A37,IF($B$4="ESP_DOOR TRIM",DATA_RASIC_DESC!D37,IF($B$4="ESP_Partner_LEVEL_01",DATA_RASIC_DESC!G37,""))))))) -> MB.7 | B44: =IF($B$4="Assembly or Component Provider",DATA_RASIC_DESC!B37,IF($B$4="Consultancy Component Provider",DATA_RASIC_DESC!B37,IF($B$4="Make to Print",DATA_RASIC_DESC!B37,IF($B$4="Engineering Service Provider",DATA_RASIC_DESC!B37,IF($B$4="Full System Provider",DATA_RASIC_DESC!B37,IF($B$4="ESP_DOOR TRIM",DATA_RASIC_DESC!E37,IF($B$4="ESP_Partner_LEVEL_01",DATA_RASIC_DESC!H37,""))))))) -> Undertake relevant market research, bench marking and value management to support target setting and attribute trade-off processes | K44: =IF($B$4="Assembly or Component Provider",DATA_RASIC!Q38,IF($B$4="Consultancy Component Provider",DATA_RASIC!X38,IF($B$4="Make to Print",DATA_RASIC!AE38,IF($B$4="Engineering Service Provider",DATA_RASIC!C38,IF($B$4="Full System Provider",DATA_RASIC!J38,IF($B$4="ESP_DOOR TRIM",DATA_RASIC!AL38,IF($B$4="ESP_Partner_LEVEL_01",DATA_RASIC!AS38,""))))))) -> JLR | L44: =IF($B$4="Assembly or Component Provider",DATA_RASIC!R38,IF($B$4="Consultancy Component Provider",DATA_RASIC!Y38,IF($B$4="Make to Print",DATA_RASIC!AF38,IF($B$4="Engineering Service Provider",DATA_RASIC!D38,IF($B$4="Full System Provider",DATA_RASIC!K38,IF($B$4="ESP_DOOR TRIM",DATA_RASIC!AM38,IF($B$4="ESP_Partner_LEVEL_01",DATA_RASIC!AT38,""))))))) -> JLR | M44: =IF($B$4="Assembly or Component Provider",DATA_RASIC!S38,IF($B$4="Consultancy Component Provider",DATA_RASIC!Z38,IF($B$4="Make to Print",DATA_RASIC!AG38,IF($B$4="Engineering Service Provider",DATA_RASIC!E38,IF($B$4="Full System Provider",DATA_RASIC!L38,IF($B$4="ESP_DOOR TRIM",DATA_RASIC!AN38,IF($B$4="ESP_Partner_LEVEL_01",DATA_RASIC!AU38,""))))))) -> JLR | N44: =IF($B$4="Assembly or Component Provider",DATA_RASIC!T38,IF($B$4="Consultancy Component Provider",DATA_RASIC!AA38,IF($B$4="Make to Print",DATA_RASIC!AH38,IF($B$4="Engineering Service Provider",DATA_RASIC!F38,IF($B$4="Full System Provider",DATA_RASIC!M38,IF($B$4="ESP_DOOR TRIM",DATA_RASIC!AO38,IF($B$4="ESP_Partner_LEVEL_01",DATA_RASIC!AV38,""))))))) -> - | O44: =IF($B$4="Assembly or Component Provider",DATA_RASIC!U38,IF($B$4="Consultancy Component Provider",DATA_RASIC!AB38,IF($B$4="Make to Print",DATA_RASIC!AI38,IF($B$4="Engineering Service Provider",DATA_RASIC!G38,IF($B$4="Full System Provider",DATA_RASIC!N38,IF($B$4="ESP_DOOR TRIM",DATA_RASIC!AP38,IF($B$4="ESP_Partner_LEVEL_01",DATA_RASIC!AW38,""))))))) -> JLR | P44: =IF($B$4="Assembly or Component Provider",DATA_RASIC!V38,IF($B$4="Consultancy Component Provider",DATA_RASIC!AC38,IF($B$4="Make to Print",DATA_RASIC!AJ38,IF($B$4="Engineering Service Provider",DATA_RASIC!H38,IF($B$4="Full System Provider",DATA_RASIC!O38,IF($B$4="ESP_DOOR TRIM",DATA_RASIC!AQ38,IF($B$4="ESP_Partner_LEVEL_01",DATA_RASIC!AX38,""))))))) -> JLR
A45: =IF($B$4="Assembly or Component Provider",DATA_RASIC_DESC!A38,IF($B$4="Consultancy Component Provider",DATA_RASIC_DESC!A38,IF($B$4="Make to Print",DATA_RASIC_DESC!A38,IF($B$4="Engineering Service Provider",DATA_RASIC_DESC!A38,IF($B$4="Full System Provider",DATA_RASIC_DESC!A38,IF($B$4="ESP_DOOR TRIM",DATA_RASIC_DESC!D38,IF($B$4="ESP_Partner_LEVEL_01",DATA_RASIC_DESC!G38,""))))))) -> - | B45: =IF($B$4="Assembly or Component Provider",DATA_RASIC_DESC!B38,IF($B$4="Consultancy Component Provider",DATA_RASIC_DESC!B38,IF($B$4="Make to Print",DATA_RASIC_DESC!B38,IF($B$4="Engineering Service Provider",DATA_RASIC_DESC!B38,IF($B$4="Full System Provider",DATA_RASIC_DESC!B38,IF($B$4="ESP_DOOR TRIM",DATA_RASIC_DESC!E38,IF($B$4="ESP_Partner_LEVEL_01",DATA_RASIC_DESC!H38,""))))))) -> Reserved | K45: =IF($B$4="Assembly or Component Provider",DATA_RASIC!Q39,IF($B$4="Consultancy Component Provider",DATA_RASIC!X39,IF($B$4="Make to Print",DATA_RASIC!AE39,IF($B$4="Engineering Service Provider",DATA_RASIC!C39,IF($B$4="Full System Provider",DATA_RASIC!J39,IF($B$4="ESP_DOOR TRIM",DATA_RASIC!AL39,IF($B$4="ESP_Partner_LEVEL_01",DATA_RASIC!AS39,""))))))) -> N/A | L45: =IF($B$4="Assembly or Component Provider",DATA_RASIC!R39,IF($B$4="Consultancy Component Provider",DATA_RASIC!Y39,IF($B$4="Make to Print",DATA_RASIC!AF39,IF($B$4="Engineering Service Provider",DATA_RASIC!D39,IF($B$4="Full System Provider",DATA_RASIC!K39,IF($B$4="ESP_DOOR TRIM",DATA_RASIC!AM39,IF($B$4="ESP_Partner_LEVEL_01",DATA_RASIC!AT39,""))))))) -> - | M45: =IF($B$4="Assembly or Component Provider",DATA_RASIC!S39,IF($B$4="Consultancy Component Provider",DATA_RASIC!Z39,IF($B$4="Make to Print",DATA_RASIC!AG39,IF($B$4="Engineering Service Provider",DATA_RASIC!E39,IF($B$4="Full System Provider",DATA_RASIC!L39,IF($B$4="ESP_DOOR TRIM",DATA_RASIC!AN39,IF($B$4="ESP_Partner_LEVEL_01",DATA_RASIC!AU39,""))))))) -> - | N45: =IF($B$4="Assembly or Component Provider",DATA_RASIC!T39,IF($B$4="Consultancy Component Provider",DATA_RASIC!AA39,IF($B$4="Make to Print",DATA_RASIC!AH39,IF($B$4="Engineering Service Provider",DATA_RASIC!F39,IF($B$4="Full System Provider",DATA_RASIC!M39,IF($B$4="ESP_DOOR TRIM",DATA_RASIC!AO39,IF($B$4="ESP_Partner_LEVEL_01",DATA_RASIC!AV39,""))))))) -> - | O45: =IF($B$4="Assembly or Component Provider",DATA_RASIC!U39,IF($B$4="Consultancy Component Provider",DATA_RASIC!AB39,IF($B$4="Make to Print",DATA_RASIC!AI39,IF($B$4="Engineering Service Provider",DATA_RASIC!G39,IF($B$4="Full System Provider",DATA_RASIC!N39,IF($B$4="ESP_DOOR TRIM",DATA_RASIC!AP39,IF($B$4="ESP_Partner_LEVEL_01",DATA_RASIC!AW39,""))))))) -> - | P45: =IF($B$4="Assembly or Component Provider",DATA_RASIC!V39,IF($B$4="Consultancy Component Provider",DATA_RASIC!AC39,IF($B$4="Make to Print",DATA_RASIC!AJ39,IF($B$4="Engineering Service Provider",DATA_RASIC!H39,IF($B$4="Full System Provider",DATA_RASIC!O39,IF($B$4="ESP_DOOR TRIM",DATA_RASIC!AQ39,IF($B$4="ESP_Partner_LEVEL_01",DATA_RASIC!AX39,""))))))) -> -
A46: [ES] ENGINEERING SPECIFICATION | K46: APPLICABLE TO SOURCING PROJECT: | O46: APPLICABLE
A47: ID | B47: DESCRIPTION OF TASK | K47: Lead | L47: R | M47: A | N47: S | O47: I | P47: C
A48: =IF($B$4="Assembly or Component Provider",DATA_RASIC_DESC!A41,IF($B$4="Consultancy Component Provider",DATA_RASIC_DESC!A41,IF($B$4="Make to Print",DATA_RASIC_DESC!A41,IF($B$4="Engineering Service Provider",DATA_RASIC_DESC!A41,IF($B$4="Full System Provider",DATA_RASIC_DESC!A41,IF($B$4="ESP_DOOR TRIM",DATA_RASIC_DESC!D41,IF($B$4="ESP_Partner_LEVEL_01",DATA_RASIC_DESC!G41,""))))))) -> ES.1 | B48: =IF($B$4="Assembly or Component Provider",DATA_RASIC_DESC!B41,IF($B$4="Consultancy Component Provider",DATA_RASIC_DESC!B41,IF($B$4="Make to Print",DATA_RASIC_DESC!B41,IF($B$4="Engineering Service Provider",DATA_RASIC_DESC!B41,IF($B$4="Full System Provider",DATA_RASIC_DESC!B41,IF($B$4="ESP_DOOR TRIM",DATA_RASIC_DESC!E41,IF($B$4="ESP_Partner_LEVEL_01",DATA_RASIC_DESC!H41,""))))))) -> Develop, maintain, and provide product development Standards which consist of three elements: Requirements (e.g. System Design Specifications); Design Rules (Best practice rules); and Design Verification Methods, DVM's (e.g. Key life test) | K48: =IF($B$4="Assembly or Component Provider",DATA_RASIC!Q43,IF($B$4="Consultancy Component Provider",DATA_RASIC!X43,IF($B$4="Make to Print",DATA_RASIC!AE43,IF($B$4="Engineering Service Provider",DATA_RASIC!C43,IF($B$4="Full System Provider",DATA_RASIC!J43,IF($B$4="ESP_DOOR TRIM",DATA_RASIC!AL43,IF($B$4="ESP_Partner_LEVEL_01",DATA_RASIC!AS43,""))))))) -> JLR | L48: =IF($B$4="Assembly or Component Provider",DATA_RASIC!R43,IF($B$4="Consultancy Component Provider",DATA_RASIC!Y43,IF($B$4="Make to Print",DATA_RASIC!AF43,IF($B$4="Engineering Service Provider",DATA_RASIC!D43,IF($B$4="Full System Provider",DATA_RASIC!K43,IF($B$4="ESP_DOOR TRIM",DATA_RASIC!AM43,IF($B$4="ESP_Partner_LEVEL_01",DATA_RASIC!AT43,""))))))) -> JLR | M48: =IF($B$4="Assembly or Component Provider",DATA_RASIC!S43,IF($B$4="Consultancy Component Provider",DATA_RASIC!Z43,IF($B$4="Make to Print",DATA_RASIC!AG43,IF($B$4="Engineering Service Provider",DATA_RASIC!E43,IF($B$4="Full System Provider",DATA_RASIC!L43,IF($B$4="ESP_DOOR TRIM",DATA_RASIC!AN43,IF($B$4="ESP_Partner_LEVEL_01",DATA_RASIC!AU43,""))))))) -> JLR | N48: =IF($B$4="Assembly or Component Provider",DATA_RASIC!T43,IF($B$4="Consultancy Component Provider",DATA_RASIC!AA43,IF($B$4="Make to Print",DATA_RASIC!AH43,IF($B$4="Engineering Service Provider",DATA_RASIC!F43,IF($B$4="Full System Provider",DATA_RASIC!M43,IF($B$4="ESP_DOOR TRIM",DATA_RASIC!AO43,IF($B$4="ESP_Partner_LEVEL_01",DATA_RASIC!AV43,""))))))) -> SE | O48: =IF($B$4="Assembly or Component Provider",DATA_RASIC!U43,IF($B$4="Consultancy Component Provider",DATA_RASIC!AB43,IF($B$4="Make to Print",DATA_RASIC!AI43,IF($B$4="Engineering Service Provider",DATA_RASIC!G43,IF($B$4="Full System Provider",DATA_RASIC!N43,IF($B$4="ESP_DOOR TRIM",DATA_RASIC!AP43,IF($B$4="ESP_Partner_LEVEL_01",DATA_RASIC!AW43,""))))))) -> - | P48: =IF($B$4="Assembly or Component Provider",DATA_RASIC!V43,IF($B$4="Consultancy Component Provider",DATA_RASIC!AC43,IF($B$4="Make to Print",DATA_RASIC!AJ43,IF($B$4="Engineering Service Provider",DATA_RASIC!H43,IF($B$4="Full System Provider",DATA_RASIC!O43,IF($B$4="ESP_DOOR TRIM",DATA_RASIC!AQ43,IF($B$4="ESP_Partner_LEVEL_01",DATA_RASIC!AX43,""))))))) -> -
A49: =IF($B$4="Assembly or Component Provider",DATA_RASIC_DESC!A42,IF($B$4="Consultancy Component Provider",DATA_RASIC_DESC!A42,IF($B$4="Make to Print",DATA_RASIC_DESC!A42,IF($B$4="Engineering Service Provider",DATA_RASIC_DESC!A42,IF($B$4="Full System Provider",DATA_RASIC_DESC!A42,IF($B$4="ESP_DOOR TRIM",DATA_RASIC_DESC!D42,IF($B$4="ESP_Partner_LEVEL_01",DATA_RASIC_DESC!G42,""))))))) -> ES.2 | B49: =IF($B$4="Assembly or Component Provider",DATA_RASIC_DESC!B42,IF($B$4="Consultancy Component Provider",DATA_RASIC_DESC!B42,IF($B$4="Make to Print",DATA_RASIC_DESC!B42,IF($B$4="Engineering Service Provider",DATA_RASIC_DESC!B42,IF($B$4="Full System Provider",DATA_RASIC_DESC!B42,IF($B$4="ESP_DOOR TRIM",DATA_RASIC_DESC!E42,IF($B$4="ESP_Partner_LEVEL_01",DATA_RASIC_DESC!H42,""))))))) -> Develop and maintain Programme specific (Sub) System Design Specification (SDS) for system/subsystem & all included components | K49: =IF($B$4="Assembly or Component Provider",DATA_RASIC!Q44,IF($B$4="Consultancy Component Provider",DATA_RASIC!X44,IF($B$4="Make to Print",DATA_RASIC!AE44,IF($B$4="Engineering Service Provider",DATA_RASIC!C44,IF($B$4="Full System Provider",DATA_RASIC!J44,IF($B$4="ESP_DOOR TRIM",DATA_RASIC!AL44,IF($B$4="ESP_Partner_LEVEL_01",DATA_RASIC!AS44,""))))))) -> JLR | L49: =IF($B$4="Assembly or Component Provider",DATA_RASIC!R44,IF($B$4="Consultancy Component Provider",DATA_RASIC!Y44,IF($B$4="Make to Print",DATA_RASIC!AF44,IF($B$4="Engineering Service Provider",DATA_RASIC!D44,IF($B$4="Full System Provider",DATA_RASIC!K44,IF($B$4="ESP_DOOR TRIM",DATA_RASIC!AM44,IF($B$4="ESP_Partner_LEVEL_01",DATA_RASIC!AT44,""))))))) -> JLR | M49: =IF($B$4="Assembly or Component Provider",DATA_RASIC!S44,IF($B$4="Consultancy Component Provider",DATA_RASIC!Z44,IF($B$4="Make to Print",DATA_RASIC!AG44,IF($B$4="Engineering Service Provider",DATA_RASIC!E44,IF($B$4="Full System Provider",DATA_RASIC!L44,IF($B$4="ESP_DOOR TRIM",DATA_RASIC!AN44,IF($B$4="ESP_Partner_LEVEL_01",DATA_RASIC!AU44,""))))))) -> JLR | N49: =IF($B$4="Assembly or Component Provider",DATA_RASIC!T44,IF($B$4="Consultancy Component Provider",DATA_RASIC!AA44,IF($B$4="Make to Print",DATA_RASIC!AH44,IF($B$4="Engineering Service Provider",DATA_RASIC!F44,IF($B$4="Full System Provider",DATA_RASIC!M44,IF($B$4="ESP_DOOR TRIM",DATA_RASIC!AO44,IF($B$4="ESP_Partner_LEVEL_01",DATA_RASIC!AV44,""))))))) -> SE | O49: =IF($B$4="Assembly or Component Provider",DATA_RASIC!U44,IF($B$4="Consultancy Component Provider",DATA_RASIC!AB44,IF($B$4="Make to Print",DATA_RASIC!AI44,IF($B$4="Engineering Service Provider",DATA_RASIC!G44,IF($B$4="Full System Provider",DATA_RASIC!N44,IF($B$4="ESP_DOOR TRIM",DATA_RASIC!AP44,IF($B$4="ESP_Partner_LEVEL_01",DATA_RASIC!AW44,""))))))) -> - | P49: =IF($B$4="Assembly or Component Provider",DATA_RASIC!V44,IF($B$4="Consultancy Component Provider",DATA_RASIC!AC44,IF($B$4="Make to Print",DATA_RASIC!AJ44,IF($B$4="Engineering Service Provider",DATA_RASIC!H44,IF($B$4="Full System Provider",DATA_RASIC!O44,IF($B$4="ESP_DOOR TRIM",DATA_RASIC!AQ44,IF($B$4="ESP_Partner_LEVEL_01",DATA_RASIC!AX44,""))))))) -> -
A50: =IF($B$4="Assembly or Component Provider",DATA_RASIC_DESC!A43,IF($B$4="Consultancy Component Provider",DATA_RASIC_DESC!A43,IF($B$4="Make to Print",DATA_RASIC_DESC!A43,IF($B$4="Engineering Service Provider",DATA_RASIC_DESC!A43,IF($B$4="Full System Provider",DATA_RASIC_DESC!A43,IF($B$4="ESP_DOOR TRIM",DATA_RASIC_DESC!D43,IF($B$4="ESP_Partner_LEVEL_01",DATA_RASIC_DESC!G43,""))))))) -> ES.3 | B50: =IF($B$4="Assembly or Component Provider",DATA_RASIC_DESC!B43,IF($B$4="Consultancy Component Provider",DATA_RASIC_DESC!B43,IF($B$4="Make to Print",DATA_RASIC_DESC!B43,IF($B$4="Engineering Service Provider",DATA_RASIC_DESC!B43,IF($B$4="Full System Provider",DATA_RASIC_DESC!B43,IF($B$4="ESP_DOOR TRIM",DATA_RASIC_DESC!E43,IF($B$4="ESP_Partner_LEVEL_01",DATA_RASIC_DESC!H43,""))))))) -> Develop and maintain Engineering Specifications for all component(s) per the SDS process | K50: =IF($B$4="Assembly or Component Provider",DATA_RASIC!Q45,IF($B$4="Consultancy Component Provider",DATA_RASIC!X45,IF($B$4="Make to Print",DATA_RASIC!AE45,IF($B$4="Engineering Service Provider",DATA_RASIC!C45,IF($B$4="Full System Provider",DATA_RASIC!J45,IF($B$4="ESP_DOOR TRIM",DATA_RASIC!AL45,IF($B$4="ESP_Partner_LEVEL_01",DATA_RASIC!AS45,""))))))) -> JLR | L50: =IF($B$4="Assembly or Component Provider",DATA_RASIC!R45,IF($B$4="Consultancy Component Provider",DATA_RASIC!Y45,IF($B$4="Make to Print",DATA_RASIC!AF45,IF($B$4="Engineering Service Provider",DATA_RASIC!D45,IF($B$4="Full System Provider",DATA_RASIC!K45,IF($B$4="ESP_DOOR TRIM",DATA_RASIC!AM45,IF($B$4="ESP_Partner_LEVEL_01",DATA_RASIC!AT45,""))))))) -> JLR | M50: =IF($B$4="Assembly or Component Provider",DATA_RASIC!S45,IF($B$4="Consultancy Component Provider",DATA_RASIC!Z45,IF($B$4="Make to Print",DATA_RASIC!AG45,IF($B$4="Engineering Service Provider",DATA_RASIC!E45,IF($B$4="Full System Provider",DATA_RASIC!L45,IF($B$4="ESP_DOOR TRIM",DATA_RASIC!AN45,IF($B$4="ESP_Partner_LEVEL_01",DATA_RASIC!AU45,""))))))) -> JLR | N50: =IF($B$4="Assembly or Component Provider",DATA_RASIC!T45,IF($B$4="Consultancy Component Provider",DATA_RASIC!AA45,IF($B$4="Make to Print",DATA_RASIC!AH45,IF($B$4="Engineering Service Provider",DATA_RASIC!F45,IF($B$4="Full System Provider",DATA_RASIC!M45,IF($B$4="ESP_DOOR TRIM",DATA_RASIC!AO45,IF($B$4="ESP_Partner_LEVEL_01",DATA_RASIC!AV45,""))))))) -> - | O50: =IF($B$4="Assembly or Component Provider",DATA_RASIC!U45,IF($B$4="Consultancy Component Provider",DATA_RASIC!AB45,IF($B$4="Make to Print",DATA_RASIC!AI45,IF($B$4="Engineering Service Provider",DATA_RASIC!G45,IF($B$4="Full System Provider",DATA_RASIC!N45,IF($B$4="ESP_DOOR TRIM",DATA_RASIC!AP45,IF($B$4="ESP_Partner_LEVEL_01",DATA_RASIC!AW45,""))))))) -> - | P50: =IF($B$4="Assembly or Component Provider",DATA_RASIC!V45,IF($B$4="Consultancy Component Provider",DATA_RASIC!AC45,IF($B$4="Make to Print",DATA_RASIC!AJ45,IF($B$4="Engineering Service Provider",DATA_RASIC!H45,IF($B$4="Full System Provider",DATA_RASIC!O45,IF($B$4="ESP_DOOR TRIM",DATA_RASIC!AQ45,IF($B$4="ESP_Partner_LEVEL_01",DATA_RASIC!AX45,""))))))) -> -
A51: =IF($B$4="Assembly or Component Provider",DATA_RASIC_DESC!A44,IF($B$4="Consultancy Component Provider",DATA_RASIC_DESC!A44,IF($B$4="Make to Print",DATA_RASIC_DESC!A44,IF($B$4="Engineering Service Provider",DATA_RASIC_DESC!A44,IF($B$4="Full System Provider",DATA_RASIC_DESC!A44,IF($B$4="ESP_DOOR TRIM",DATA_RASIC_DESC!D44,IF($B$4="ESP_Partner_LEVEL_01",DATA_RASIC_DESC!G44,""))))))) -> ES.4 | B51: =IF($B$4="Assembly or Component Provider",DATA_RASIC_DESC!B44,IF($B$4="Consultancy Component Provider",DATA_RASIC_DESC!B44,IF($B$4="Make to Print",DATA_RASIC_DESC!B44,IF($B$4="Engineering Service Provider",DATA_RASIC_DESC!B44,IF($B$4="Full System Provider",DATA_RASIC_DESC!B44,IF($B$4="ESP_DOOR TRIM",DATA_RASIC_DESC!E44,IF($B$4="ESP_Partner_LEVEL_01",DATA_RASIC_DESC!H44,""))))))) -> Meet all of Jaguar Land Rover's Corporate, Homologation, World Regulatory, Materials and Transportation requirements for all markets within Programme definition (e.g. FMVSS, etc.). Cost or timing affected by changes required after signing this document may be subject to re-negotiation | K51: =IF($B$4="Assembly or Component Provider",DATA_RASIC!Q46,IF($B$4="Consultancy Component Provider",DATA_RASIC!X46,IF($B$4="Make to Print",DATA_RASIC!AE46,IF($B$4="Engineering Service Provider",DATA_RASIC!C46,IF($B$4="Full System Provider",DATA_RASIC!J46,IF($B$4="ESP_DOOR TRIM",DATA_RASIC!AL46,IF($B$4="ESP_Partner_LEVEL_01",DATA_RASIC!AS46,""))))))) -> JLR | L51: =IF($B$4="Assembly or Component Provider",DATA_RASIC!R46,IF($B$4="Consultancy Component Provider",DATA_RASIC!Y46,IF($B$4="Make to Print",DATA_RASIC!AF46,IF($B$4="Engineering Service Provider",DATA_RASIC!D46,IF($B$4="Full System Provider",DATA_RASIC!K46,IF($B$4="ESP_DOOR TRIM",DATA_RASIC!AM46,IF($B$4="ESP_Partner_LEVEL_01",DATA_RASIC!AT46,""))))))) -> JLR | M51: =IF($B$4="Assembly or Component Provider",DATA_RASIC!S46,IF($B$4="Consultancy Component Provider",DATA_RASIC!Z46,IF($B$4="Make to Print",DATA_RASIC!AG46,IF($B$4="Engineering Service Provider",DATA_RASIC!E46,IF($B$4="Full System Provider",DATA_RASIC!L46,IF($B$4="ESP_DOOR TRIM",DATA_RASIC!AN46,IF($B$4="ESP_Partner_LEVEL_01",DATA_RASIC!AU46,""))))))) -> JLR | N51: =IF($B$4="Assembly or Component Provider",DATA_RASIC!T46,IF($B$4="Consultancy Component Provider",DATA_RASIC!AA46,IF($B$4="Make to Print",DATA_RASIC!AH46,IF($B$4="Engineering Service Provider",DATA_RASIC!F46,IF($B$4="Full System Provider",DATA_RASIC!M46,IF($B$4="ESP_DOOR TRIM",DATA_RASIC!AO46,IF($B$4="ESP_Partner_LEVEL_01",DATA_RASIC!AV46,""))))))) -> SE | O51: =IF($B$4="Assembly or Component Provider",DATA_RASIC!U46,IF($B$4="Consultancy Component Provider",DATA_RASIC!AB46,IF($B$4="Make to Print",DATA_RASIC!AI46,IF($B$4="Engineering Service Provider",DATA_RASIC!G46,IF($B$4="Full System Provider",DATA_RASIC!N46,IF($B$4="ESP_DOOR TRIM",DATA_RASIC!AP46,IF($B$4="ESP_Partner_LEVEL_01",DATA_RASIC!AW46,""))))))) -> - | P51: =IF($B$4="Assembly or Component Provider",DATA_RASIC!V46,IF($B$4="Consultancy Component Provider",DATA_RASIC!AC46,IF($B$4="Make to Print",DATA_RASIC!AJ46,IF($B$4="Engineering Service Provider",DATA_RASIC!H46,IF($B$4="Full System Provider",DATA_RASIC!O46,IF($B$4="ESP_DOOR TRIM",DATA_RASIC!AQ46,IF($B$4="ESP_Partner_LEVEL_01",DATA_RASIC!AX46,""))))))) -> -
A52: =IF($B$4="Assembly or Component Provider",DATA_RASIC_DESC!A45,IF($B$4="Consultancy Component Provider",DATA_RASIC_DESC!A45,IF($B$4="Make to Print",DATA_RASIC_DESC!A45,IF($B$4="Engineering Service Provider",DATA_RASIC_DESC!A45,IF($B$4="Full System Provider",DATA_RASIC_DESC!A45,IF($B$4="ESP_DOOR TRIM",DATA_RASIC_DESC!D45,IF($B$4="ESP_Partner_LEVEL_01",DATA_RASIC_DESC!G45,""))))))) -> ES.5 | B52: =IF($B$4="Assembly or Component Provider",DATA_RASIC_DESC!B45,IF($B$4="Consultancy Component Provider",DATA_RASIC_DESC!B45,IF($B$4="Make to Print",DATA_RASIC_DESC!B45,IF($B$4="Engineering Service Provider",DATA_RASIC_DESC!B45,IF($B$4="Full System Provider",DATA_RASIC_DESC!B45,IF($B$4="ESP_DOOR TRIM",DATA_RASIC_DESC!E45,IF($B$4="ESP_Partner_LEVEL_01",DATA_RASIC_DESC!H45,""))))))) -> Communicated and agree course of action in the event of discovery of technical requirements discrepancy | K52: =IF($B$4="Assembly or Component Provider",DATA_RASIC!Q47,IF($B$4="Consultancy Component Provider",DATA_RASIC!X47,IF($B$4="Make to Print",DATA_RASIC!AE47,IF($B$4="Engineering Service Provider",DATA_RASIC!C47,IF($B$4="Full System Provider",DATA_RASIC!J47,IF($B$4="ESP_DOOR TRIM",DATA_RASIC!AL47,IF($B$4="ESP_Partner_LEVEL_01",DATA_RASIC!AS47,""))))))) -> JLR | L52: =IF($B$4="Assembly or Component Provider",DATA_RASIC!R47,IF($B$4="Consultancy Component Provider",DATA_RASIC!Y47,IF($B$4="Make to Print",DATA_RASIC!AF47,IF($B$4="Engineering Service Provider",DATA_RASIC!D47,IF($B$4="Full System Provider",DATA_RASIC!K47,IF($B$4="ESP_DOOR TRIM",DATA_RASIC!AM47,IF($B$4="ESP_Partner_LEVEL_01",DATA_RASIC!AT47,""))))))) -> JLR | M52: =IF($B$4="Assembly or Component Provider",DATA_RASIC!S47,IF($B$4="Consultancy Component Provider",DATA_RASIC!Z47,IF($B$4="Make to Print",DATA_RASIC!AG47,IF($B$4="Engineering Service Provider",DATA_RASIC!E47,IF($B$4="Full System Provider",DATA_RASIC!L47,IF($B$4="ESP_DOOR TRIM",DATA_RASIC!AN47,IF($B$4="ESP_Partner_LEVEL_01",DATA_RASIC!AU47,""))))))) -> JLR | N52: =IF($B$4="Assembly or Component Provider",DATA_RASIC!T47,IF($B$4="Consultancy Component Provider",DATA_RASIC!AA47,IF($B$4="Make to Print",DATA_RASIC!AH47,IF($B$4="Engineering Service Provider",DATA_RASIC!F47,IF($B$4="Full System Provider",DATA_RASIC!M47,IF($B$4="ESP_DOOR TRIM",DATA_RASIC!AO47,IF($B$4="ESP_Partner_LEVEL_01",DATA_RASIC!AV47,""))))))) -> SE | O52: =IF($B$4="Assembly or Component Provider",DATA_RASIC!U47,IF($B$4="Consultancy Component Provider",DATA_RASIC!AB47,IF($B$4="Make to Print",DATA_RASIC!AI47,IF($B$4="Engineering Service Provider",DATA_RASIC!G47,IF($B$4="Full System Provider",DATA_RASIC!N47,IF($B$4="ESP_DOOR TRIM",DATA_RASIC!AP47,IF($B$4="ESP_Partner_LEVEL_01",DATA_RASIC!AW47,""))))))) -> - | P52: =IF($B$4="Assembly or Component Provider",DATA_RASIC!V47,IF($B$4="Consultancy Component Provider",DATA_RASIC!AC47,IF($B$4="Make to Print",DATA_RASIC!AJ47,IF($B$4="Engineering Service Provider",DATA_RASIC!H47,IF($B$4="Full System Provider",DATA_RASIC!O47,IF($B$4="ESP_DOOR TRIM",DATA_RASIC!AQ47,IF($B$4="ESP_Partner_LEVEL_01",DATA_RASIC!AX47,""))))))) -> -
A53: =IF($B$4="Assembly or Component Provider",DATA_RASIC_DESC!A46,IF($B$4="Consultancy Component Provider",DATA_RASIC_DESC!A46,IF($B$4="Make to Print",DATA_RASIC_DESC!A46,IF($B$4="Engineering Service Provider",DATA_RASIC_DESC!A46,IF($B$4="Full System Provider",DATA_RASIC_DESC!A46,IF($B$4="ESP_DOOR TRIM",DATA_RASIC_DESC!D46,IF($B$4="ESP_Partner_LEVEL_01",DATA_RASIC_DESC!G46,""))))))) -> ES.6 | B53: =IF($B$4="Assembly or Component Provider",DATA_RASIC_DESC!B46,IF($B$4="Consultancy Component Provider",DATA_RASIC_DESC!B46,IF($B$4="Make to Print",DATA_RASIC_DESC!B46,IF($B$4="Engineering Service Provider",DATA_RASIC_DESC!B46,IF($B$4="Full System Provider",DATA_RASIC_DESC!B46,IF($B$4="ESP_DOOR TRIM",DATA_RASIC_DESC!E46,IF($B$4="ESP_Partner_LEVEL_01",DATA_RASIC_DESC!H46,""))))))) -> Meet all of Jaguar Land Rover's Corporate, Homologation, World Regulatory, Materials and Transportation requirements for all markets within Programme definition as cascaded in commodity specific RMDV by JLR to SE responsible list. Cost or timing affected by changes required after signing this document may be subject to re-negotiation | K53: =IF($B$4="Assembly or Component Provider",DATA_RASIC!Q48,IF($B$4="Consultancy Component Provider",DATA_RASIC!X48,IF($B$4="Make to Print",DATA_RASIC!AE48,IF($B$4="Engineering Service Provider",DATA_RASIC!C48,IF($B$4="Full System Provider",DATA_RASIC!J48,IF($B$4="ESP_DOOR TRIM",DATA_RASIC!AL48,IF($B$4="ESP_Partner_LEVEL_01",DATA_RASIC!AS48,""))))))) -> SE | L53: =IF($B$4="Assembly or Component Provider",DATA_RASIC!R48,IF($B$4="Consultancy Component Provider",DATA_RASIC!Y48,IF($B$4="Make to Print",DATA_RASIC!AF48,IF($B$4="Engineering Service Provider",DATA_RASIC!D48,IF($B$4="Full System Provider",DATA_RASIC!K48,IF($B$4="ESP_DOOR TRIM",DATA_RASIC!AM48,IF($B$4="ESP_Partner_LEVEL_01",DATA_RASIC!AT48,""))))))) -> SE | M53: =IF($B$4="Assembly or Component Provider",DATA_RASIC!S48,IF($B$4="Consultancy Component Provider",DATA_RASIC!Z48,IF($B$4="Make to Print",DATA_RASIC!AG48,IF($B$4="Engineering Service Provider",DATA_RASIC!E48,IF($B$4="Full System Provider",DATA_RASIC!L48,IF($B$4="ESP_DOOR TRIM",DATA_RASIC!AN48,IF($B$4="ESP_Partner_LEVEL_01",DATA_RASIC!AU48,""))))))) -> JLR | N53: =IF($B$4="Assembly or Component Provider",DATA_RASIC!T48,IF($B$4="Consultancy Component Provider",DATA_RASIC!AA48,IF($B$4="Make to Print",DATA_RASIC!AH48,IF($B$4="Engineering Service Provider",DATA_RASIC!F48,IF($B$4="Full System Provider",DATA_RASIC!M48,IF($B$4="ESP_DOOR TRIM",DATA_RASIC!AO48,IF($B$4="ESP_Partner_LEVEL_01",DATA_RASIC!AV48,""))))))) -> SE | O53: =IF($B$4="Assembly or Component Provider",DATA_RASIC!U48,IF($B$4="Consultancy Component Provider",DATA_RASIC!AB48,IF($B$4="Make to Print",DATA_RASIC!AI48,IF($B$4="Engineering Service Provider",DATA_RASIC!G48,IF($B$4="Full System Provider",DATA_RASIC!N48,IF($B$4="ESP_DOOR TRIM",DATA_RASIC!AP48,IF($B$4="ESP_Partner_LEVEL_01",DATA_RASIC!AW48,""))))))) -> - | P53: =IF($B$4="Assembly or Component Provider",DATA_RASIC!V48,IF($B$4="Consultancy Component Provider",DATA_RASIC!AC48,IF($B$4="Make to Print",DATA_RASIC!AJ48,IF($B$4="Engineering Service Provider",DATA_RASIC!H48,IF($B$4="Full System Provider",DATA_RASIC!O48,IF($B$4="ESP_DOOR TRIM",DATA_RASIC!AQ48,IF($B$4="ESP_Partner_LEVEL_01",DATA_RASIC!AX48,""))))))) -> -
A54: =IF($B$4="Assembly or Component Provider",DATA_RASIC_DESC!A47,IF($B$4="Consultancy Component Provider",DATA_RASIC_DESC!A47,IF($B$4="Make to Print",DATA_RASIC_DESC!A47,IF($B$4="Engineering Service Provider",DATA_RASIC_DESC!A47,IF($B$4="Full System Provider",DATA_RASIC_DESC!A47,IF($B$4="ESP_DOOR TRIM",DATA_RASIC_DESC!D47,IF($B$4="ESP_Partner_LEVEL_01",DATA_RASIC_DESC!G47,""))))))) -> - | B54: =IF($B$4="Assembly or Component Provider",DATA_RASIC_DESC!B47,IF($B$4="Consultancy Component Provider",DATA_RASIC_DESC!B47,IF($B$4="Make to Print",DATA_RASIC_DESC!B47,IF($B$4="Engineering Service Provider",DATA_RASIC_DESC!B47,IF($B$4="Full System Provider",DATA_RASIC_DESC!B47,IF($B$4="ESP_DOOR TRIM",DATA_RASIC_DESC!E47,IF($B$4="ESP_Partner_LEVEL_01",DATA_RASIC_DESC!H47,""))))))) -> Reserved | K54: =IF($B$4="Assembly or Component Provider",DATA_RASIC!Q49,IF($B$4="Consultancy Component Provider",DATA_RASIC!X49,IF($B$4="Make to Print",DATA_RASIC!AE49,IF($B$4="Engineering Service Provider",DATA_RASIC!C49,IF($B$4="Full System Provider",DATA_RASIC!J49,IF($B$4="ESP_DOOR TRIM",DATA_RASIC!AL49,IF($B$4="ESP_Partner_LEVEL_01",DATA_RASIC!AS49,""))))))) -> N/A | L54: =IF($B$4="Assembly or Component Provider",DATA_RASIC!R49,IF($B$4="Consultancy Component Provider",DATA_RASIC!Y49,IF($B$4="Make to Print",DATA_RASIC!AF49,IF($B$4="Engineering Service Provider",DATA_RASIC!D49,IF($B$4="Full System Provider",DATA_RASIC!K49,IF($B$4="ESP_DOOR TRIM",DATA_RASIC!AM49,IF($B$4="ESP_Partner_LEVEL_01",DATA_RASIC!AT49,""))))))) -> - | M54: =IF($B$4="Assembly or Component Provider",DATA_RASIC!S49,IF($B$4="Consultancy Component Provider",DATA_RASIC!Z49,IF($B$4="Make to Print",DATA_RASIC!AG49,IF($B$4="Engineering Service Provider",DATA_RASIC!E49,IF($B$4="Full System Provider",DATA_RASIC!L49,IF($B$4="ESP_DOOR TRIM",DATA_RASIC!AN49,IF($B$4="ESP_Partner_LEVEL_01",DATA_RASIC!AU49,""))))))) -> - | N54: =IF($B$4="Assembly or Component Provider",DATA_RASIC!T49,IF($B$4="Consultancy Component Provider",DATA_RASIC!AA49,IF($B$4="Make to Print",DATA_RASIC!AH49,IF($B$4="Engineering Service Provider",DATA_RASIC!F49,IF($B$4="Full System Provider",DATA_RASIC!M49,IF($B$4="ESP_DOOR TRIM",DATA_RASIC!AO49,IF($B$4="ESP_Partner_LEVEL_01",DATA_RASIC!AV49,""))))))) -> - | O54: =IF($B$4="Assembly or Component Provider",DATA_RASIC!U49,IF($B$4="Consultancy Component Provider",DATA_RASIC!AB49,IF($B$4="Make to Print",DATA_RASIC!AI49,IF($B$4="Engineering Service Provider",DATA_RASIC!G49,IF($B$4="Full System Provider",DATA_RASIC!N49,IF($B$4="ESP_DOOR TRIM",DATA_RASIC!AP49,IF($B$4="ESP_Partner_LEVEL_01",DATA_RASIC!AW49,""))))))) -> - | P54: =IF($B$4="Assembly or Component Provider",DATA_RASIC!V49,IF($B$4="Consultancy Component Provider",DATA_RASIC!AC49,IF($B$4="Make to Print",DATA_RASIC!AJ49,IF($B$4="Engineering Service Provider",DATA_RASIC!H49,IF($B$4="Full System Provider",DATA_RASIC!O49,IF($B$4="ESP_DOOR TRIM",DATA_RASIC!AQ49,IF($B$4="ESP_Partner_LEVEL_01",DATA_RASIC!AX49,""))))))) -> -
A55: [DE] DESIGN AND ENGINEERING | K55: APPLICABLE TO SOURCING PROJECT: | O55: APPLICABLE
A56: ID | B56: DESCRIPTION OF TASK | K56: Lead | L56: R | M56: A | N56: S | O56: I | P56: C
A57: =IF($B$4="Assembly or Component Provider",DATA_RASIC_DESC!A50,IF($B$4="Consultancy Component Provider",DATA_RASIC_DESC!A50,IF($B$4="Make to Print",DATA_RASIC_DESC!A50,IF($B$4="Engineering Service Provider",DATA_RASIC_DESC!A50,IF($B$4="Full System Provider",DATA_RASIC_DESC!A50,IF($B$4="ESP_DOOR TRIM",DATA_RASIC_DESC!D50,IF($B$4="ESP_Partner_LEVEL_01",DATA_RASIC_DESC!G50,""))))))) -> DE.1 | B57: =IF($B$4="Assembly or Component Provider",DATA_RASIC_DESC!B50,IF($B$4="Consultancy Component Provider",DATA_RASIC_DESC!B50,IF($B$4="Make to Print",DATA_RASIC_DESC!B50,IF($B$4="Engineering Service Provider",DATA_RASIC_DESC!B50,IF($B$4="Full System Provider",DATA_RASIC_DESC!B50,IF($B$4="ESP_DOOR TRIM",DATA_RASIC_DESC!E50,IF($B$4="ESP_Partner_LEVEL_01",DATA_RASIC_DESC!H50,""))))))) -> Throughout the Product Development Process, Jaguar Land Rover's Engineers shall proactively assist suppliers to ensure a "Flawless Product" launch of a component, system and module (including but not limited to the following events): · Know the customer requirements (including service components) · Participate actively in supplier technical and process capability / design reviews · Conduct problem resolution and continuous improvement efforts · Lead periodic risk assessment of Jaguar Land Rover's / Supplier readiness · Communicate Programme assessment status, including the sign–off and approval of progress throughout the product development process · Review and approve all supplier deliverables · Identify, measure, monitor and control critical to quality characteristics of the product / launch · Assure that all of Jaguar Land Rover's methodologies / processes are maximised and enhanced | K57: =IF($B$4="Assembly or Component Provider",DATA_RASIC!Q53,IF($B$4="Consultancy Component Provider",DATA_RASIC!X53,IF($B$4="Make to Print",DATA_RASIC!AE53,IF($B$4="Engineering Service Provider",DATA_RASIC!C53,IF($B$4="Full System Provider",DATA_RASIC!J53,IF($B$4="ESP_DOOR TRIM",DATA_RASIC!AL53,IF($B$4="ESP_Partner_LEVEL_01",DATA_RASIC!AS53,""))))))) -> JLR | L57: =IF($B$4="Assembly or Component Provider",DATA_RASIC!R53,IF($B$4="Consultancy Component Provider",DATA_RASIC!Y53,IF($B$4="Make to Print",DATA_RASIC!AF53,IF($B$4="Engineering Service Provider",DATA_RASIC!D53,IF($B$4="Full System Provider",DATA_RASIC!K53,IF($B$4="ESP_DOOR TRIM",DATA_RASIC!AM53,IF($B$4="ESP_Partner_LEVEL_01",DATA_RASIC!AT53,""))))))) -> JLR | M57: =IF($B$4="Assembly or Component Provider",DATA_RASIC!S53,IF($B$4="Consultancy Component Provider",DATA_RASIC!Z53,IF($B$4="Make to Print",DATA_RASIC!AG53,IF($B$4="Engineering Service Provider",DATA_RASIC!E53,IF($B$4="Full System Provider",DATA_RASIC!L53,IF($B$4="ESP_DOOR TRIM",DATA_RASIC!AN53,IF($B$4="ESP_Partner_LEVEL_01",DATA_RASIC!AU53,""))))))) -> JLR | N57: =IF($B$4="Assembly or Component Provider",DATA_RASIC!T53,IF($B$4="Consultancy Component Provider",DATA_RASIC!AA53,IF($B$4="Make to Print",DATA_RASIC!AH53,IF($B$4="Engineering Service Provider",DATA_RASIC!F53,IF($B$4="Full System Provider",DATA_RASIC!M53,IF($B$4="ESP_DOOR TRIM",DATA_RASIC!AO53,IF($B$4="ESP_Partner_LEVEL_01",DATA_RASIC!AV53,""))))))) -> SE | O57: =IF($B$4="Assembly or Component Provider",DATA_RASIC!U53,IF($B$4="Consultancy Component Provider",DATA_RASIC!AB53,IF($B$4="Make to Print",DATA_RASIC!AI53,IF($B$4="Engineering Service Provider",DATA_RASIC!G53,IF($B$4="Full System Provider",DATA_RASIC!N53,IF($B$4="ESP_DOOR TRIM",DATA_RASIC!AP53,IF($B$4="ESP_Partner_LEVEL_01",DATA_RASIC!AW53,""))))))) -> - | P57: =IF($B$4="Assembly or Component Provider",DATA_RASIC!V53,IF($B$4="Consultancy Component Provider",DATA_RASIC!AC53,IF($B$4="Make to Print",DATA_RASIC!AJ53,IF($B$4="Engineering Service Provider",DATA_RASIC!H53,IF($B$4="Full System Provider",DATA_RASIC!O53,IF($B$4="ESP_DOOR TRIM",DATA_RASIC!AQ53,IF($B$4="ESP_Partner_LEVEL_01",DATA_RASIC!AX53,""))))))) -> -
A58: =IF($B$4="Assembly or Component Provider",DATA_RASIC_DESC!A51,IF($B$4="Consultancy Component Provider",DATA_RASIC_DESC!A51,IF($B$4="Make to Print",DATA_RASIC_DESC!A51,IF($B$4="Engineering Service Provider",DATA_RASIC_DESC!A51,IF($B$4="Full System Provider",DATA_RASIC_DESC!A51,IF($B$4="ESP_DOOR TRIM",DATA_RASIC_DESC!D51,IF($B$4="ESP_Partner_LEVEL_01",DATA_RASIC_DESC!G51,""))))))) -> DE.2 | B58: =IF($B$4="Assembly or Component Provider",DATA_RASIC_DESC!B51,IF($B$4="Consultancy Component Provider",DATA_RASIC_DESC!B51,IF($B$4="Make to Print",DATA_RASIC_DESC!B51,IF($B$4="Engineering Service Provider",DATA_RASIC_DESC!B51,IF($B$4="Full System Provider",DATA_RASIC_DESC!B51,IF($B$4="ESP_DOOR TRIM",DATA_RASIC_DESC!E51,IF($B$4="ESP_Partner_LEVEL_01",DATA_RASIC_DESC!H51,""))))))) -> Define system attributes & requirements of all interfacing commodities ( e.g. Headlamp-cleaning / washer bottle) | K58: =IF($B$4="Assembly or Component Provider",DATA_RASIC!Q54,IF($B$4="Consultancy Component Provider",DATA_RASIC!X54,IF($B$4="Make to Print",DATA_RASIC!AE54,IF($B$4="Engineering Service Provider",DATA_RASIC!C54,IF($B$4="Full System Provider",DATA_RASIC!J54,IF($B$4="ESP_DOOR TRIM",DATA_RASIC!AL54,IF($B$4="ESP_Partner_LEVEL_01",DATA_RASIC!AS54,""))))))) -> JLR | L58: =IF($B$4="Assembly or Component Provider",DATA_RASIC!R54,IF($B$4="Consultancy Component Provider",DATA_RASIC!Y54,IF($B$4="Make to Print",DATA_RASIC!AF54,IF($B$4="Engineering Service Provider",DATA_RASIC!D54,IF($B$4="Full System Provider",DATA_RASIC!K54,IF($B$4="ESP_DOOR TRIM",DATA_RASIC!AM54,IF($B$4="ESP_Partner_LEVEL_01",DATA_RASIC!AT54,""))))))) -> JLR | M58: =IF($B$4="Assembly or Component Provider",DATA_RASIC!S54,IF($B$4="Consultancy Component Provider",DATA_RASIC!Z54,IF($B$4="Make to Print",DATA_RASIC!AG54,IF($B$4="Engineering Service Provider",DATA_RASIC!E54,IF($B$4="Full System Provider",DATA_RASIC!L54,IF($B$4="ESP_DOOR TRIM",DATA_RASIC!AN54,IF($B$4="ESP_Partner_LEVEL_01",DATA_RASIC!AU54,""))))))) -> JLR | N58: =IF($B$4="Assembly or Component Provider",DATA_RASIC!T54,IF($B$4="Consultancy Component Provider",DATA_RASIC!AA54,IF($B$4="Make to Print",DATA_RASIC!AH54,IF($B$4="Engineering Service Provider",DATA_RASIC!F54,IF($B$4="Full System Provider",DATA_RASIC!M54,IF($B$4="ESP_DOOR TRIM",DATA_RASIC!AO54,IF($B$4="ESP_Partner_LEVEL_01",DATA_RASIC!AV54,""))))))) -> SE | O58: =IF($B$4="Assembly or Component Provider",DATA_RASIC!U54,IF($B$4="Consultancy Component Provider",DATA_RASIC!AB54,IF($B$4="Make to Print",DATA_RASIC!AI54,IF($B$4="Engineering Service Provider",DATA_RASIC!G54,IF($B$4="Full System Provider",DATA_RASIC!N54,IF($B$4="ESP_DOOR TRIM",DATA_RASIC!AP54,IF($B$4="ESP_Partner_LEVEL_01",DATA_RASIC!AW54,""))))))) -> - | P58: =IF($B$4="Assembly or Component Provider",DATA_RASIC!V54,IF($B$4="Consultancy Component Provider",DATA_RASIC!AC54,IF($B$4="Make to Print",DATA_RASIC!AJ54,IF($B$4="Engineering Service Provider",DATA_RASIC!H54,IF($B$4="Full System Provider",DATA_RASIC!O54,IF($B$4="ESP_DOOR TRIM",DATA_RASIC!AQ54,IF($B$4="ESP_Partner_LEVEL_01",DATA_RASIC!AX54,""))))))) -> -
A59: =IF($B$4="Assembly or Component Provider",DATA_RASIC_DESC!A52,IF($B$4="Consultancy Component Provider",DATA_RASIC_DESC!A52,IF($B$4="Make to Print",DATA_RASIC_DESC!A52,IF($B$4="Engineering Service Provider",DATA_RASIC_DESC!A52,IF($B$4="Full System Provider",DATA_RASIC_DESC!A52,IF($B$4="ESP_DOOR TRIM",DATA_RASIC_DESC!D52,IF($B$4="ESP_Partner_LEVEL_01",DATA_RASIC_DESC!G52,""))))))) -> DE.3 | B59: =IF($B$4="Assembly or Component Provider",DATA_RASIC_DESC!B52,IF($B$4="Consultancy Component Provider",DATA_RASIC_DESC!B52,IF($B$4="Make to Print",DATA_RASIC_DESC!B52,IF($B$4="Engineering Service Provider",DATA_RASIC_DESC!B52,IF($B$4="Full System Provider",DATA_RASIC_DESC!B52,IF($B$4="ESP_DOOR TRIM",DATA_RASIC_DESC!E52,IF($B$4="ESP_Partner_LEVEL_01",DATA_RASIC_DESC!H52,""))))))) -> Develop vehicle package for the commodity. JLR to issue list of components within package, supplier responsible for monitoring updates to parts within supplier systems. JLR to issue list of DS’s | K59: =IF($B$4="Assembly or Component Provider",DATA_RASIC!Q55,IF($B$4="Consultancy Component Provider",DATA_RASIC!X55,IF($B$4="Make to Print",DATA_RASIC!AE55,IF($B$4="Engineering Service Provider",DATA_RASIC!C55,IF($B$4="Full System Provider",DATA_RASIC!J55,IF($B$4="ESP_DOOR TRIM",DATA_RASIC!AL55,IF($B$4="ESP_Partner_LEVEL_01",DATA_RASIC!AS55,""))))))) -> JLR | L59: =IF($B$4="Assembly or Component Provider",DATA_RASIC!R55,IF($B$4="Consultancy Component Provider",DATA_RASIC!Y55,IF($B$4="Make to Print",DATA_RASIC!AF55,IF($B$4="Engineering Service Provider",DATA_RASIC!D55,IF($B$4="Full System Provider",DATA_RASIC!K55,IF($B$4="ESP_DOOR TRIM",DATA_RASIC!AM55,IF($B$4="ESP_Partner_LEVEL_01",DATA_RASIC!AT55,""))))))) -> JLR | M59: =IF($B$4="Assembly or Component Provider",DATA_RASIC!S55,IF($B$4="Consultancy Component Provider",DATA_RASIC!Z55,IF($B$4="Make to Print",DATA_RASIC!AG55,IF($B$4="Engineering Service Provider",DATA_RASIC!E55,IF($B$4="Full System Provider",DATA_RASIC!L55,IF($B$4="ESP_DOOR TRIM",DATA_RASIC!AN55,IF($B$4="ESP_Partner_LEVEL_01",DATA_RASIC!AU55,""))))))) -> JLR | N59: =IF($B$4="Assembly or Component Provider",DATA_RASIC!T55,IF($B$4="Consultancy Component Provider",DATA_RASIC!AA55,IF($B$4="Make to Print",DATA_RASIC!AH55,IF($B$4="Engineering Service Provider",DATA_RASIC!F55,IF($B$4="Full System Provider",DATA_RASIC!M55,IF($B$4="ESP_DOOR TRIM",DATA_RASIC!AO55,IF($B$4="ESP_Partner_LEVEL_01",DATA_RASIC!AV55,""))))))) -> SE | O59: =IF($B$4="Assembly or Component Provider",DATA_RASIC!U55,IF($B$4="Consultancy Component Provider",DATA_RASIC!AB55,IF($B$4="Make to Print",DATA_RASIC!AI55,IF($B$4="Engineering Service Provider",DATA_RASIC!G55,IF($B$4="Full System Provider",DATA_RASIC!N55,IF($B$4="ESP_DOOR TRIM",DATA_RASIC!AP55,IF($B$4="ESP_Partner_LEVEL_01",DATA_RASIC!AW55,""))))))) -> - | P59: =IF($B$4="Assembly or Component Provider",DATA_RASIC!V55,IF($B$4="Consultancy Component Provider",DATA_RASIC!AC55,IF($B$4="Make to Print",DATA_RASIC!AJ55,IF($B$4="Engineering Service Provider",DATA_RASIC!H55,IF($B$4="Full System Provider",DATA_RASIC!O55,IF($B$4="ESP_DOOR TRIM",DATA_RASIC!AQ55,IF($B$4="ESP_Partner_LEVEL_01",DATA_RASIC!AX55,""))))))) -> -
A60: =IF($B$4="Assembly or Component Provider",DATA_RASIC_DESC!A53,IF($B$4="Consultancy Component Provider",DATA_RASIC_DESC!A53,IF($B$4="Make to Print",DATA_RASIC_DESC!A53,IF($B$4="Engineering Service Provider",DATA_RASIC_DESC!A53,IF($B$4="Full System Provider",DATA_RASIC_DESC!A53,IF($B$4="ESP_DOOR TRIM",DATA_RASIC_DESC!D53,IF($B$4="ESP_Partner_LEVEL_01",DATA_RASIC_DESC!G53,""))))))) -> DE.4 | B60: =IF($B$4="Assembly or Component Provider",DATA_RASIC_DESC!B53,IF($B$4="Consultancy Component Provider",DATA_RASIC_DESC!B53,IF($B$4="Make to Print",DATA_RASIC_DESC!B53,IF($B$4="Engineering Service Provider",DATA_RASIC_DESC!B53,IF($B$4="Full System Provider",DATA_RASIC_DESC!B53,IF($B$4="ESP_DOOR TRIM",DATA_RASIC_DESC!E53,IF($B$4="ESP_Partner_LEVEL_01",DATA_RASIC_DESC!H53,""))))))) -> Take ownership of and maintain parts in WERS which are manufactured by Jaguar Land Rover or are “build-to-print” parts not supplier designed, prior to the use of WERS and if required | K60: =IF($B$4="Assembly or Component Provider",DATA_RASIC!Q56,IF($B$4="Consultancy Component Provider",DATA_RASIC!X56,IF($B$4="Make to Print",DATA_RASIC!AE56,IF($B$4="Engineering Service Provider",DATA_RASIC!C56,IF($B$4="Full System Provider",DATA_RASIC!J56,IF($B$4="ESP_DOOR TRIM",DATA_RASIC!AL56,IF($B$4="ESP_Partner_LEVEL_01",DATA_RASIC!AS56,""))))))) -> JLR | L60: =IF($B$4="Assembly or Component Provider",DATA_RASIC!R56,IF($B$4="Consultancy Component Provider",DATA_RASIC!Y56,IF($B$4="Make to Print",DATA_RASIC!AF56,IF($B$4="Engineering Service Provider",DATA_RASIC!D56,IF($B$4="Full System Provider",DATA_RASIC!K56,IF($B$4="ESP_DOOR TRIM",DATA_RASIC!AM56,IF($B$4="ESP_Partner_LEVEL_01",DATA_RASIC!AT56,""))))))) -> JLR | M60: =IF($B$4="Assembly or Component Provider",DATA_RASIC!S56,IF($B$4="Consultancy Component Provider",DATA_RASIC!Z56,IF($B$4="Make to Print",DATA_RASIC!AG56,IF($B$4="Engineering Service Provider",DATA_RASIC!E56,IF($B$4="Full System Provider",DATA_RASIC!L56,IF($B$4="ESP_DOOR TRIM",DATA_RASIC!AN56,IF($B$4="ESP_Partner_LEVEL_01",DATA_RASIC!AU56,""))))))) -> JLR | N60: =IF($B$4="Assembly or Component Provider",DATA_RASIC!T56,IF($B$4="Consultancy Component Provider",DATA_RASIC!AA56,IF($B$4="Make to Print",DATA_RASIC!AH56,IF($B$4="Engineering Service Provider",DATA_RASIC!F56,IF($B$4="Full System Provider",DATA_RASIC!M56,IF($B$4="ESP_DOOR TRIM",DATA_RASIC!AO56,IF($B$4="ESP_Partner_LEVEL_01",DATA_RASIC!AV56,""))))))) -> SE | O60: =IF($B$4="Assembly or Component Provider",DATA_RASIC!U56,IF($B$4="Consultancy Component Provider",DATA_RASIC!AB56,IF($B$4="Make to Print",DATA_RASIC!AI56,IF($B$4="Engineering Service Provider",DATA_RASIC!G56,IF($B$4="Full System Provider",DATA_RASIC!N56,IF($B$4="ESP_DOOR TRIM",DATA_RASIC!AP56,IF($B$4="ESP_Partner_LEVEL_01",DATA_RASIC!AW56,""))))))) -> - | P60: =IF($B$4="Assembly or Component Provider",DATA_RASIC!V56,IF($B$4="Consultancy Component Provider",DATA_RASIC!AC56,IF($B$4="Make to Print",DATA_RASIC!AJ56,IF($B$4="Engineering Service Provider",DATA_RASIC!H56,IF($B$4="Full System Provider",DATA_RASIC!O56,IF($B$4="ESP_DOOR TRIM",DATA_RASIC!AQ56,IF($B$4="ESP_Partner_LEVEL_01",DATA_RASIC!AX56,""))))))) -> -
A61: =IF($B$4="Assembly or Component Provider",DATA_RASIC_DESC!A54,IF($B$4="Consultancy Component Provider",DATA_RASIC_DESC!A54,IF($B$4="Make to Print",DATA_RASIC_DESC!A54,IF($B$4="Engineering Service Provider",DATA_RASIC_DESC!A54,IF($B$4="Full System Provider",DATA_RASIC_DESC!A54,IF($B$4="ESP_DOOR TRIM",DATA_RASIC_DESC!D54,IF($B$4="ESP_Partner_LEVEL_01",DATA_RASIC_DESC!G54,""))))))) -> DE.5 | B61: =IF($B$4="Assembly or Component Provider",DATA_RASIC_DESC!B54,IF($B$4="Consultancy Component Provider",DATA_RASIC_DESC!B54,IF($B$4="Make to Print",DATA_RASIC_DESC!B54,IF($B$4="Engineering Service Provider",DATA_RASIC_DESC!B54,IF($B$4="Full System Provider",DATA_RASIC_DESC!B54,IF($B$4="ESP_DOOR TRIM",DATA_RASIC_DESC!E54,IF($B$4="ESP_Partner_LEVEL_01",DATA_RASIC_DESC!H54,""))))))) -> Perform engineering change control process on other modules and released components affecting the supplied module that requires supplier engineering feasibility concurrence | K61: =IF($B$4="Assembly or Component Provider",DATA_RASIC!Q57,IF($B$4="Consultancy Component Provider",DATA_RASIC!X57,IF($B$4="Make to Print",DATA_RASIC!AE57,IF($B$4="Engineering Service Provider",DATA_RASIC!C57,IF($B$4="Full System Provider",DATA_RASIC!J57,IF($B$4="ESP_DOOR TRIM",DATA_RASIC!AL57,IF($B$4="ESP_Partner_LEVEL_01",DATA_RASIC!AS57,""))))))) -> JLR | L61: =IF($B$4="Assembly or Component Provider",DATA_RASIC!R57,IF($B$4="Consultancy Component Provider",DATA_RASIC!Y57,IF($B$4="Make to Print",DATA_RASIC!AF57,IF($B$4="Engineering Service Provider",DATA_RASIC!D57,IF($B$4="Full System Provider",DATA_RASIC!K57,IF($B$4="ESP_DOOR TRIM",DATA_RASIC!AM57,IF($B$4="ESP_Partner_LEVEL_01",DATA_RASIC!AT57,""))))))) -> JLR | M61: =IF($B$4="Assembly or Component Provider",DATA_RASIC!S57,IF($B$4="Consultancy Component Provider",DATA_RASIC!Z57,IF($B$4="Make to Print",DATA_RASIC!AG57,IF($B$4="Engineering Service Provider",DATA_RASIC!E57,IF($B$4="Full System Provider",DATA_RASIC!L57,IF($B$4="ESP_DOOR TRIM",DATA_RASIC!AN57,IF($B$4="ESP_Partner_LEVEL_01",DATA_RASIC!AU57,""))))))) -> JLR | N61: =IF($B$4="Assembly or Component Provider",DATA_RASIC!T57,IF($B$4="Consultancy Component Provider",DATA_RASIC!AA57,IF($B$4="Make to Print",DATA_RASIC!AH57,IF($B$4="Engineering Service Provider",DATA_RASIC!F57,IF($B$4="Full System Provider",DATA_RASIC!M57,IF($B$4="ESP_DOOR TRIM",DATA_RASIC!AO57,IF($B$4="ESP_Partner_LEVEL_01",DATA_RASIC!AV57,""))))))) -> SE | O61: =IF($B$4="Assembly or Component Provider",DATA_RASIC!U57,IF($B$4="Consultancy Component Provider",DATA_RASIC!AB57,IF($B$4="Make to Print",DATA_RASIC!AI57,IF($B$4="Engineering Service Provider",DATA_RASIC!G57,IF($B$4="Full System Provider",DATA_RASIC!N57,IF($B$4="ESP_DOOR TRIM",DATA_RASIC!AP57,IF($B$4="ESP_Partner_LEVEL_01",DATA_RASIC!AW57,""))))))) -> - | P61: =IF($B$4="Assembly or Component Provider",DATA_RASIC!V57,IF($B$4="Consultancy Component Provider",DATA_RASIC!AC57,IF($B$4="Make to Print",DATA_RASIC!AJ57,IF($B$4="Engineering Service Provider",DATA_RASIC!H57,IF($B$4="Full System Provider",DATA_RASIC!O57,IF($B$4="ESP_DOOR TRIM",DATA_RASIC!AQ57,IF($B$4="ESP_Partner_LEVEL_01",DATA_RASIC!AX57,""))))))) -> SE
A62: =IF($B$4="Assembly or Component Provider",DATA_RASIC_DESC!A55,IF($B$4="Consultancy Component Provider",DATA_RASIC_DESC!A55,IF($B$4="Make to Print",DATA_RASIC_DESC!A55,IF($B$4="Engineering Service Provider",DATA_RASIC_DESC!A55,IF($B$4="Full System Provider",DATA_RASIC_DESC!A55,IF($B$4="ESP_DOOR TRIM",DATA_RASIC_DESC!D55,IF($B$4="ESP_Partner_LEVEL_01",DATA_RASIC_DESC!G55,""))))))) -> DE.6 | B62: =IF($B$4="Assembly or Component Provider",DATA_RASIC_DESC!B55,IF($B$4="Consultancy Component Provider",DATA_RASIC_DESC!B55,IF($B$4="Make to Print",DATA_RASIC_DESC!B55,IF($B$4="Engineering Service Provider",DATA_RASIC_DESC!B55,IF($B$4="Full System Provider",DATA_RASIC_DESC!B55,IF($B$4="ESP_DOOR TRIM",DATA_RASIC_DESC!E55,IF($B$4="ESP_Partner_LEVEL_01",DATA_RASIC_DESC!H55,""))))))) -> Provide common hard points per Generic Architecture Process (GAP) to support package/architecture design | K62: =IF($B$4="Assembly or Component Provider",DATA_RASIC!Q58,IF($B$4="Consultancy Component Provider",DATA_RASIC!X58,IF($B$4="Make to Print",DATA_RASIC!AE58,IF($B$4="Engineering Service Provider",DATA_RASIC!C58,IF($B$4="Full System Provider",DATA_RASIC!J58,IF($B$4="ESP_DOOR TRIM",DATA_RASIC!AL58,IF($B$4="ESP_Partner_LEVEL_01",DATA_RASIC!AS58,""))))))) -> JLR | L62: =IF($B$4="Assembly or Component Provider",DATA_RASIC!R58,IF($B$4="Consultancy Component Provider",DATA_RASIC!Y58,IF($B$4="Make to Print",DATA_RASIC!AF58,IF($B$4="Engineering Service Provider",DATA_RASIC!D58,IF($B$4="Full System Provider",DATA_RASIC!K58,IF($B$4="ESP_DOOR TRIM",DATA_RASIC!AM58,IF($B$4="ESP_Partner_LEVEL_01",DATA_RASIC!AT58,""))))))) -> JLR | M62: =IF($B$4="Assembly or Component Provider",DATA_RASIC!S58,IF($B$4="Consultancy Component Provider",DATA_RASIC!Z58,IF($B$4="Make to Print",DATA_RASIC!AG58,IF($B$4="Engineering Service Provider",DATA_RASIC!E58,IF($B$4="Full System Provider",DATA_RASIC!L58,IF($B$4="ESP_DOOR TRIM",DATA_RASIC!AN58,IF($B$4="ESP_Partner_LEVEL_01",DATA_RASIC!AU58,""))))))) -> JLR | N62: =IF($B$4="Assembly or Component Provider",DATA_RASIC!T58,IF($B$4="Consultancy Component Provider",DATA_RASIC!AA58,IF($B$4="Make to Print",DATA_RASIC!AH58,IF($B$4="Engineering Service Provider",DATA_RASIC!F58,IF($B$4="Full System Provider",DATA_RASIC!M58,IF($B$4="ESP_DOOR TRIM",DATA_RASIC!AO58,IF($B$4="ESP_Partner_LEVEL_01",DATA_RASIC!AV58,""))))))) -> SE | O62: =IF($B$4="Assembly or Component Provider",DATA_RASIC!U58,IF($B$4="Consultancy Component Provider",DATA_RASIC!AB58,IF($B$4="Make to Print",DATA_RASIC!AI58,IF($B$4="Engineering Service Provider",DATA_RASIC!G58,IF($B$4="Full System Provider",DATA_RASIC!N58,IF($B$4="ESP_DOOR TRIM",DATA_RASIC!AP58,IF($B$4="ESP_Partner_LEVEL_01",DATA_RASIC!AW58,""))))))) -> - | P62: =IF($B$4="Assembly or Component Provider",DATA_RASIC!V58,IF($B$4="Consultancy Component Provider",DATA_RASIC!AC58,IF($B$4="Make to Print",DATA_RASIC!AJ58,IF($B$4="Engineering Service Provider",DATA_RASIC!H58,IF($B$4="Full System Provider",DATA_RASIC!O58,IF($B$4="ESP_DOOR TRIM",DATA_RASIC!AQ58,IF($B$4="ESP_Partner_LEVEL_01",DATA_RASIC!AX58,""))))))) -> SE
A63: =IF($B$4="Assembly or Component Provider",DATA_RASIC_DESC!A56,IF($B$4="Consultancy Component Provider",DATA_RASIC_DESC!A56,IF($B$4="Make to Print",DATA_RASIC_DESC!A56,IF($B$4="Engineering Service Provider",DATA_RASIC_DESC!A56,IF($B$4="Full System Provider",DATA_RASIC_DESC!A56,IF($B$4="ESP_DOOR TRIM",DATA_RASIC_DESC!D56,IF($B$4="ESP_Partner_LEVEL_01",DATA_RASIC_DESC!G56,""))))))) -> DE.7 | B63: =IF($B$4="Assembly or Component Provider",DATA_RASIC_DESC!B56,IF($B$4="Consultancy Component Provider",DATA_RASIC_DESC!B56,IF($B$4="Make to Print",DATA_RASIC_DESC!B56,IF($B$4="Engineering Service Provider",DATA_RASIC_DESC!B56,IF($B$4="Full System Provider",DATA_RASIC_DESC!B56,IF($B$4="ESP_DOOR TRIM",DATA_RASIC_DESC!E56,IF($B$4="ESP_Partner_LEVEL_01",DATA_RASIC_DESC!H56,""))))))) -> Ensure CAD-to-BOM alignment throughout Programme | K63: =IF($B$4="Assembly or Component Provider",DATA_RASIC!Q59,IF($B$4="Consultancy Component Provider",DATA_RASIC!X59,IF($B$4="Make to Print",DATA_RASIC!AE59,IF($B$4="Engineering Service Provider",DATA_RASIC!C59,IF($B$4="Full System Provider",DATA_RASIC!J59,IF($B$4="ESP_DOOR TRIM",DATA_RASIC!AL59,IF($B$4="ESP_Partner_LEVEL_01",DATA_RASIC!AS59,""))))))) -> JLR | L63: =IF($B$4="Assembly or Component Provider",DATA_RASIC!R59,IF($B$4="Consultancy Component Provider",DATA_RASIC!Y59,IF($B$4="Make to Print",DATA_RASIC!AF59,IF($B$4="Engineering Service Provider",DATA_RASIC!D59,IF($B$4="Full System Provider",DATA_RASIC!K59,IF($B$4="ESP_DOOR TRIM",DATA_RASIC!AM59,IF($B$4="ESP_Partner_LEVEL_01",DATA_RASIC!AT59,""))))))) -> JLR | M63: =IF($B$4="Assembly or Component Provider",DATA_RASIC!S59,IF($B$4="Consultancy Component Provider",DATA_RASIC!Z59,IF($B$4="Make to Print",DATA_RASIC!AG59,IF($B$4="Engineering Service Provider",DATA_RASIC!E59,IF($B$4="Full System Provider",DATA_RASIC!L59,IF($B$4="ESP_DOOR TRIM",DATA_RASIC!AN59,IF($B$4="ESP_Partner_LEVEL_01",DATA_RASIC!AU59,""))))))) -> JLR | N63: =IF($B$4="Assembly or Component Provider",DATA_RASIC!T59,IF($B$4="Consultancy Component Provider",DATA_RASIC!AA59,IF($B$4="Make to Print",DATA_RASIC!AH59,IF($B$4="Engineering Service Provider",DATA_RASIC!F59,IF($B$4="Full System Provider",DATA_RASIC!M59,IF($B$4="ESP_DOOR TRIM",DATA_RASIC!AO59,IF($B$4="ESP_Partner_LEVEL_01",DATA_RASIC!AV59,""))))))) -> SE | O63: =IF($B$4="Assembly or Component Provider",DATA_RASIC!U59,IF($B$4="Consultancy Component Provider",DATA_RASIC!AB59,IF($B$4="Make to Print",DATA_RASIC!AI59,IF($B$4="Engineering Service Provider",DATA_RASIC!G59,IF($B$4="Full System Provider",DATA_RASIC!N59,IF($B$4="ESP_DOOR TRIM",DATA_RASIC!AP59,IF($B$4="ESP_Partner_LEVEL_01",DATA_RASIC!AW59,""))))))) -> - | P63: =IF($B$4="Assembly or Component Provider",DATA_RASIC!V59,IF($B$4="Consultancy Component Provider",DATA_RASIC!AC59,IF($B$4="Make to Print",DATA_RASIC!AJ59,IF($B$4="Engineering Service Provider",DATA_RASIC!H59,IF($B$4="Full System Provider",DATA_RASIC!O59,IF($B$4="ESP_DOOR TRIM",DATA_RASIC!AQ59,IF($B$4="ESP_Partner_LEVEL_01",DATA_RASIC!AX59,""))))))) -> -
A64: =IF($B$4="Assembly or Component Provider",DATA_RASIC_DESC!A57,IF($B$4="Consultancy Component Provider",DATA_RASIC_DESC!A57,IF($B$4="Make to Print",DATA_RASIC_DESC!A57,IF($B$4="Engineering Service Provider",DATA_RASIC_DESC!A57,IF($B$4="Full System Provider",DATA_RASIC_DESC!A57,IF($B$4="ESP_DOOR TRIM",DATA_RASIC_DESC!D57,IF($B$4="ESP_Partner_LEVEL_01",DATA_RASIC_DESC!G57,""))))))) -> DE.8 | B64: =IF($B$4="Assembly or Component Provider",DATA_RASIC_DESC!B57,IF($B$4="Consultancy Component Provider",DATA_RASIC_DESC!B57,IF($B$4="Make to Print",DATA_RASIC_DESC!B57,IF($B$4="Engineering Service Provider",DATA_RASIC_DESC!B57,IF($B$4="Full System Provider",DATA_RASIC_DESC!B57,IF($B$4="ESP_DOOR TRIM",DATA_RASIC_DESC!E57,IF($B$4="ESP_Partner_LEVEL_01",DATA_RASIC_DESC!H57,""))))))) -> Support throughout Jaguar Land Rover's Product Development Process to ensure a "Flawless Product" launch (including but not limited to the following events): · Customer requirements (including service components) · Supplier technical and process capability / design reviews · Programme improvement efforts & recovery plans · Communicate all identified risks to Jaguar Land Rover · Product / Programme status reviews · Ensure all deliverables are met · All critical to quality characteristics of the product / launch · Develop product and process assurance plans that maximise the use of supplier technical resources while ensuring both product and process requirements are met | K64: =IF($B$4="Assembly or Component Provider",DATA_RASIC!Q60,IF($B$4="Consultancy Component Provider",DATA_RASIC!X60,IF($B$4="Make to Print",DATA_RASIC!AE60,IF($B$4="Engineering Service Provider",DATA_RASIC!C60,IF($B$4="Full System Provider",DATA_RASIC!J60,IF($B$4="ESP_DOOR TRIM",DATA_RASIC!AL60,IF($B$4="ESP_Partner_LEVEL_01",DATA_RASIC!AS60,""))))))) -> SE | L64: =IF($B$4="Assembly or Component Provider",DATA_RASIC!R60,IF($B$4="Consultancy Component Provider",DATA_RASIC!Y60,IF($B$4="Make to Print",DATA_RASIC!AF60,IF($B$4="Engineering Service Provider",DATA_RASIC!D60,IF($B$4="Full System Provider",DATA_RASIC!K60,IF($B$4="ESP_DOOR TRIM",DATA_RASIC!AM60,IF($B$4="ESP_Partner_LEVEL_01",DATA_RASIC!AT60,""))))))) -> SE | M64: =IF($B$4="Assembly or Component Provider",DATA_RASIC!S60,IF($B$4="Consultancy Component Provider",DATA_RASIC!Z60,IF($B$4="Make to Print",DATA_RASIC!AG60,IF($B$4="Engineering Service Provider",DATA_RASIC!E60,IF($B$4="Full System Provider",DATA_RASIC!L60,IF($B$4="ESP_DOOR TRIM",DATA_RASIC!AN60,IF($B$4="ESP_Partner_LEVEL_01",DATA_RASIC!AU60,""))))))) -> - | N64: =IF($B$4="Assembly or Component Provider",DATA_RASIC!T60,IF($B$4="Consultancy Component Provider",DATA_RASIC!AA60,IF($B$4="Make to Print",DATA_RASIC!AH60,IF($B$4="Engineering Service Provider",DATA_RASIC!F60,IF($B$4="Full System Provider",DATA_RASIC!M60,IF($B$4="ESP_DOOR TRIM",DATA_RASIC!AO60,IF($B$4="ESP_Partner_LEVEL_01",DATA_RASIC!AV60,""))))))) -> JLR | O64: =IF($B$4="Assembly or Component Provider",DATA_RASIC!U60,IF($B$4="Consultancy Component Provider",DATA_RASIC!AB60,IF($B$4="Make to Print",DATA_RASIC!AI60,IF($B$4="Engineering Service Provider",DATA_RASIC!G60,IF($B$4="Full System Provider",DATA_RASIC!N60,IF($B$4="ESP_DOOR TRIM",DATA_RASIC!AP60,IF($B$4="ESP_Partner_LEVEL_01",DATA_RASIC!AW60,""))))))) -> - | P64: =IF($B$4="Assembly or Component Provider",DATA_RASIC!V60,IF($B$4="Consultancy Component Provider",DATA_RASIC!AC60,IF($B$4="Make to Print",DATA_RASIC!AJ60,IF($B$4="Engineering Service Provider",DATA_RASIC!H60,IF($B$4="Full System Provider",DATA_RASIC!O60,IF($B$4="ESP_DOOR TRIM",DATA_RASIC!AQ60,IF($B$4="ESP_Partner_LEVEL_01",DATA_RASIC!AX60,""))))))) -> -
A65: =IF($B$4="Assembly or Component Provider",DATA_RASIC_DESC!A58,IF($B$4="Consultancy Component Provider",DATA_RASIC_DESC!A58,IF($B$4="Make to Print",DATA_RASIC_DESC!A58,IF($B$4="Engineering Service Provider",DATA_RASIC_DESC!A58,IF($B$4="Full System Provider",DATA_RASIC_DESC!A58,IF($B$4="ESP_DOOR TRIM",DATA_RASIC_DESC!D58,IF($B$4="ESP_Partner_LEVEL_01",DATA_RASIC_DESC!G58,""))))))) -> DE.9 | B65: =IF($B$4="Assembly or Component Provider",DATA_RASIC_DESC!B58,IF($B$4="Consultancy Component Provider",DATA_RASIC_DESC!B58,IF($B$4="Make to Print",DATA_RASIC_DESC!B58,IF($B$4="Engineering Service Provider",DATA_RASIC_DESC!B58,IF($B$4="Full System Provider",DATA_RASIC_DESC!B58,IF($B$4="ESP_DOOR TRIM",DATA_RASIC_DESC!E58,IF($B$4="ESP_Partner_LEVEL_01",DATA_RASIC_DESC!H58,""))))))) -> Incorporate all optimisation improvements to design | K65: =IF($B$4="Assembly or Component Provider",DATA_RASIC!Q61,IF($B$4="Consultancy Component Provider",DATA_RASIC!X61,IF($B$4="Make to Print",DATA_RASIC!AE61,IF($B$4="Engineering Service Provider",DATA_RASIC!C61,IF($B$4="Full System Provider",DATA_RASIC!J61,IF($B$4="ESP_DOOR TRIM",DATA_RASIC!AL61,IF($B$4="ESP_Partner_LEVEL_01",DATA_RASIC!AS61,""))))))) -> JLR | L65: =IF($B$4="Assembly or Component Provider",DATA_RASIC!R61,IF($B$4="Consultancy Component Provider",DATA_RASIC!Y61,IF($B$4="Make to Print",DATA_RASIC!AF61,IF($B$4="Engineering Service Provider",DATA_RASIC!D61,IF($B$4="Full System Provider",DATA_RASIC!K61,IF($B$4="ESP_DOOR TRIM",DATA_RASIC!AM61,IF($B$4="ESP_Partner_LEVEL_01",DATA_RASIC!AT61,""))))))) -> SE | M65: =IF($B$4="Assembly or Component Provider",DATA_RASIC!S61,IF($B$4="Consultancy Component Provider",DATA_RASIC!Z61,IF($B$4="Make to Print",DATA_RASIC!AG61,IF($B$4="Engineering Service Provider",DATA_RASIC!E61,IF($B$4="Full System Provider",DATA_RASIC!L61,IF($B$4="ESP_DOOR TRIM",DATA_RASIC!AN61,IF($B$4="ESP_Partner_LEVEL_01",DATA_RASIC!AU61,""))))))) -> JLR | N65: =IF($B$4="Assembly or Component Provider",DATA_RASIC!T61,IF($B$4="Consultancy Component Provider",DATA_RASIC!AA61,IF($B$4="Make to Print",DATA_RASIC!AH61,IF($B$4="Engineering Service Provider",DATA_RASIC!F61,IF($B$4="Full System Provider",DATA_RASIC!M61,IF($B$4="ESP_DOOR TRIM",DATA_RASIC!AO61,IF($B$4="ESP_Partner_LEVEL_01",DATA_RASIC!AV61,""))))))) -> - | O65: =IF($B$4="Assembly or Component Provider",DATA_RASIC!U61,IF($B$4="Consultancy Component Provider",DATA_RASIC!AB61,IF($B$4="Make to Print",DATA_RASIC!AI61,IF($B$4="Engineering Service Provider",DATA_RASIC!G61,IF($B$4="Full System Provider",DATA_RASIC!N61,IF($B$4="ESP_DOOR TRIM",DATA_RASIC!AP61,IF($B$4="ESP_Partner_LEVEL_01",DATA_RASIC!AW61,""))))))) -> - | P65: =IF($B$4="Assembly or Component Provider",DATA_RASIC!V61,IF($B$4="Consultancy Component Provider",DATA_RASIC!AC61,IF($B$4="Make to Print",DATA_RASIC!AJ61,IF($B$4="Engineering Service Provider",DATA_RASIC!H61,IF($B$4="Full System Provider",DATA_RASIC!O61,IF($B$4="ESP_DOOR TRIM",DATA_RASIC!AQ61,IF($B$4="ESP_Partner_LEVEL_01",DATA_RASIC!AX61,""))))))) -> -
A66: =IF($B$4="Assembly or Component Provider",DATA_RASIC_DESC!A59,IF($B$4="Consultancy Component Provider",DATA_RASIC_DESC!A59,IF($B$4="Make to Print",DATA_RASIC_DESC!A59,IF($B$4="Engineering Service Provider",DATA_RASIC_DESC!A59,IF($B$4="Full System Provider",DATA_RASIC_DESC!A59,IF($B$4="ESP_DOOR TRIM",DATA_RASIC_DESC!D59,IF($B$4="ESP_Partner_LEVEL_01",DATA_RASIC_DESC!G59,""))))))) -> DE.10 | B66: =IF($B$4="Assembly or Component Provider",DATA_RASIC_DESC!B59,IF($B$4="Consultancy Component Provider",DATA_RASIC_DESC!B59,IF($B$4="Make to Print",DATA_RASIC_DESC!B59,IF($B$4="Engineering Service Provider",DATA_RASIC_DESC!B59,IF($B$4="Full System Provider",DATA_RASIC_DESC!B59,IF($B$4="ESP_DOOR TRIM",DATA_RASIC_DESC!E59,IF($B$4="ESP_Partner_LEVEL_01",DATA_RASIC_DESC!H59,""))))))) -> Use hard points provided by Jaguar Land Rover for package/architecture | K66: =IF($B$4="Assembly or Component Provider",DATA_RASIC!Q62,IF($B$4="Consultancy Component Provider",DATA_RASIC!X62,IF($B$4="Make to Print",DATA_RASIC!AE62,IF($B$4="Engineering Service Provider",DATA_RASIC!C62,IF($B$4="Full System Provider",DATA_RASIC!J62,IF($B$4="ESP_DOOR TRIM",DATA_RASIC!AL62,IF($B$4="ESP_Partner_LEVEL_01",DATA_RASIC!AS62,""))))))) -> JLR | L66: =IF($B$4="Assembly or Component Provider",DATA_RASIC!R62,IF($B$4="Consultancy Component Provider",DATA_RASIC!Y62,IF($B$4="Make to Print",DATA_RASIC!AF62,IF($B$4="Engineering Service Provider",DATA_RASIC!D62,IF($B$4="Full System Provider",DATA_RASIC!K62,IF($B$4="ESP_DOOR TRIM",DATA_RASIC!AM62,IF($B$4="ESP_Partner_LEVEL_01",DATA_RASIC!AT62,""))))))) -> SE | M66: =IF($B$4="Assembly or Component Provider",DATA_RASIC!S62,IF($B$4="Consultancy Component Provider",DATA_RASIC!Z62,IF($B$4="Make to Print",DATA_RASIC!AG62,IF($B$4="Engineering Service Provider",DATA_RASIC!E62,IF($B$4="Full System Provider",DATA_RASIC!L62,IF($B$4="ESP_DOOR TRIM",DATA_RASIC!AN62,IF($B$4="ESP_Partner_LEVEL_01",DATA_RASIC!AU62,""))))))) -> JLR | N66: =IF($B$4="Assembly or Component Provider",DATA_RASIC!T62,IF($B$4="Consultancy Component Provider",DATA_RASIC!AA62,IF($B$4="Make to Print",DATA_RASIC!AH62,IF($B$4="Engineering Service Provider",DATA_RASIC!F62,IF($B$4="Full System Provider",DATA_RASIC!M62,IF($B$4="ESP_DOOR TRIM",DATA_RASIC!AO62,IF($B$4="ESP_Partner_LEVEL_01",DATA_RASIC!AV62,""))))))) -> - | O66: =IF($B$4="Assembly or Component Provider",DATA_RASIC!U62,IF($B$4="Consultancy Component Provider",DATA_RASIC!AB62,IF($B$4="Make to Print",DATA_RASIC!AI62,IF($B$4="Engineering Service Provider",DATA_RASIC!G62,IF($B$4="Full System Provider",DATA_RASIC!N62,IF($B$4="ESP_DOOR TRIM",DATA_RASIC!AP62,IF($B$4="ESP_Partner_LEVEL_01",DATA_RASIC!AW62,""))))))) -> - | P66: =IF($B$4="Assembly or Component Provider",DATA_RASIC!V62,IF($B$4="Consultancy Component Provider",DATA_RASIC!AC62,IF($B$4="Make to Print",DATA_RASIC!AJ62,IF($B$4="Engineering Service Provider",DATA_RASIC!H62,IF($B$4="Full System Provider",DATA_RASIC!O62,IF($B$4="ESP_DOOR TRIM",DATA_RASIC!AQ62,IF($B$4="ESP_Partner_LEVEL_01",DATA_RASIC!AX62,""))))))) -> -
A67: =IF($B$4="Assembly or Component Provider",DATA_RASIC_DESC!A60,IF($B$4="Consultancy Component Provider",DATA_RASIC_DESC!A60,IF($B$4="Make to Print",DATA_RASIC_DESC!A60,IF($B$4="Engineering Service Provider",DATA_RASIC_DESC!A60,IF($B$4="Full System Provider",DATA_RASIC_DESC!A60,IF($B$4="ESP_DOOR TRIM",DATA_RASIC_DESC!D60,IF($B$4="ESP_Partner_LEVEL_01",DATA_RASIC_DESC!G60,""))))))) -> DE.11 | B67: =IF($B$4="Assembly or Component Provider",DATA_RASIC_DESC!B60,IF($B$4="Consultancy Component Provider",DATA_RASIC_DESC!B60,IF($B$4="Make to Print",DATA_RASIC_DESC!B60,IF($B$4="Engineering Service Provider",DATA_RASIC_DESC!B60,IF($B$4="Full System Provider",DATA_RASIC_DESC!B60,IF($B$4="ESP_DOOR TRIM",DATA_RASIC_DESC!E60,IF($B$4="ESP_Partner_LEVEL_01",DATA_RASIC_DESC!H60,""))))))) -> Use WERS as the master Programme BOM including key attribute data for all parts, if required. | K67: =IF($B$4="Assembly or Component Provider",DATA_RASIC!Q63,IF($B$4="Consultancy Component Provider",DATA_RASIC!X63,IF($B$4="Make to Print",DATA_RASIC!AE63,IF($B$4="Engineering Service Provider",DATA_RASIC!C63,IF($B$4="Full System Provider",DATA_RASIC!J63,IF($B$4="ESP_DOOR TRIM",DATA_RASIC!AL63,IF($B$4="ESP_Partner_LEVEL_01",DATA_RASIC!AS63,""))))))) -> JLR | L67: =IF($B$4="Assembly or Component Provider",DATA_RASIC!R63,IF($B$4="Consultancy Component Provider",DATA_RASIC!Y63,IF($B$4="Make to Print",DATA_RASIC!AF63,IF($B$4="Engineering Service Provider",DATA_RASIC!D63,IF($B$4="Full System Provider",DATA_RASIC!K63,IF($B$4="ESP_DOOR TRIM",DATA_RASIC!AM63,IF($B$4="ESP_Partner_LEVEL_01",DATA_RASIC!AT63,""))))))) -> JLR | M67: =IF($B$4="Assembly or Component Provider",DATA_RASIC!S63,IF($B$4="Consultancy Component Provider",DATA_RASIC!Z63,IF($B$4="Make to Print",DATA_RASIC!AG63,IF($B$4="Engineering Service Provider",DATA_RASIC!E63,IF($B$4="Full System Provider",DATA_RASIC!L63,IF($B$4="ESP_DOOR TRIM",DATA_RASIC!AN63,IF($B$4="ESP_Partner_LEVEL_01",DATA_RASIC!AU63,""))))))) -> JLR | N67: =IF($B$4="Assembly or Component Provider",DATA_RASIC!T63,IF($B$4="Consultancy Component Provider",DATA_RASIC!AA63,IF($B$4="Make to Print",DATA_RASIC!AH63,IF($B$4="Engineering Service Provider",DATA_RASIC!F63,IF($B$4="Full System Provider",DATA_RASIC!M63,IF($B$4="ESP_DOOR TRIM",DATA_RASIC!AO63,IF($B$4="ESP_Partner_LEVEL_01",DATA_RASIC!AV63,""))))))) -> SE | O67: =IF($B$4="Assembly or Component Provider",DATA_RASIC!U63,IF($B$4="Consultancy Component Provider",DATA_RASIC!AB63,IF($B$4="Make to Print",DATA_RASIC!AI63,IF($B$4="Engineering Service Provider",DATA_RASIC!G63,IF($B$4="Full System Provider",DATA_RASIC!N63,IF($B$4="ESP_DOOR TRIM",DATA_RASIC!AP63,IF($B$4="ESP_Partner_LEVEL_01",DATA_RASIC!AW63,""))))))) -> SE | P67: =IF($B$4="Assembly or Component Provider",DATA_RASIC!V63,IF($B$4="Consultancy Component Provider",DATA_RASIC!AC63,IF($B$4="Make to Print",DATA_RASIC!AJ63,IF($B$4="Engineering Service Provider",DATA_RASIC!H63,IF($B$4="Full System Provider",DATA_RASIC!O63,IF($B$4="ESP_DOOR TRIM",DATA_RASIC!AQ63,IF($B$4="ESP_Partner_LEVEL_01",DATA_RASIC!AX63,""))))))) -> SE
A68: =IF($B$4="Assembly or Component Provider",DATA_RASIC_DESC!A61,IF($B$4="Consultancy Component Provider",DATA_RASIC_DESC!A61,IF($B$4="Make to Print",DATA_RASIC_DESC!A61,IF($B$4="Engineering Service Provider",DATA_RASIC_DESC!A61,IF($B$4="Full System Provider",DATA_RASIC_DESC!A61,IF($B$4="ESP_DOOR TRIM",DATA_RASIC_DESC!D61,IF($B$4="ESP_Partner_LEVEL_01",DATA_RASIC_DESC!G61,""))))))) -> DE.12 | B68: =IF($B$4="Assembly or Component Provider",DATA_RASIC_DESC!B61,IF($B$4="Consultancy Component Provider",DATA_RASIC_DESC!B61,IF($B$4="Make to Print",DATA_RASIC_DESC!B61,IF($B$4="Engineering Service Provider",DATA_RASIC_DESC!B61,IF($B$4="Full System Provider",DATA_RASIC_DESC!B61,IF($B$4="ESP_DOOR TRIM",DATA_RASIC_DESC!E61,IF($B$4="ESP_Partner_LEVEL_01",DATA_RASIC_DESC!H61,""))))))) -> Take ownership of parts which are loaded in WERS, create new entries as required and maintain accurate records, prior to the use of WERS and if required | K68: =IF($B$4="Assembly or Component Provider",DATA_RASIC!Q64,IF($B$4="Consultancy Component Provider",DATA_RASIC!X64,IF($B$4="Make to Print",DATA_RASIC!AE64,IF($B$4="Engineering Service Provider",DATA_RASIC!C64,IF($B$4="Full System Provider",DATA_RASIC!J64,IF($B$4="ESP_DOOR TRIM",DATA_RASIC!AL64,IF($B$4="ESP_Partner_LEVEL_01",DATA_RASIC!AS64,""))))))) -> JLR | L68: =IF($B$4="Assembly or Component Provider",DATA_RASIC!R64,IF($B$4="Consultancy Component Provider",DATA_RASIC!Y64,IF($B$4="Make to Print",DATA_RASIC!AF64,IF($B$4="Engineering Service Provider",DATA_RASIC!D64,IF($B$4="Full System Provider",DATA_RASIC!K64,IF($B$4="ESP_DOOR TRIM",DATA_RASIC!AM64,IF($B$4="ESP_Partner_LEVEL_01",DATA_RASIC!AT64,""))))))) -> JLR | M68: =IF($B$4="Assembly or Component Provider",DATA_RASIC!S64,IF($B$4="Consultancy Component Provider",DATA_RASIC!Z64,IF($B$4="Make to Print",DATA_RASIC!AG64,IF($B$4="Engineering Service Provider",DATA_RASIC!E64,IF($B$4="Full System Provider",DATA_RASIC!L64,IF($B$4="ESP_DOOR TRIM",DATA_RASIC!AN64,IF($B$4="ESP_Partner_LEVEL_01",DATA_RASIC!AU64,""))))))) -> JLR | N68: =IF($B$4="Assembly or Component Provider",DATA_RASIC!T64,IF($B$4="Consultancy Component Provider",DATA_RASIC!AA64,IF($B$4="Make to Print",DATA_RASIC!AH64,IF($B$4="Engineering Service Provider",DATA_RASIC!F64,IF($B$4="Full System Provider",DATA_RASIC!M64,IF($B$4="ESP_DOOR TRIM",DATA_RASIC!AO64,IF($B$4="ESP_Partner_LEVEL_01",DATA_RASIC!AV64,""))))))) -> - | O68: =IF($B$4="Assembly or Component Provider",DATA_RASIC!U64,IF($B$4="Consultancy Component Provider",DATA_RASIC!AB64,IF($B$4="Make to Print",DATA_RASIC!AI64,IF($B$4="Engineering Service Provider",DATA_RASIC!G64,IF($B$4="Full System Provider",DATA_RASIC!N64,IF($B$4="ESP_DOOR TRIM",DATA_RASIC!AP64,IF($B$4="ESP_Partner_LEVEL_01",DATA_RASIC!AW64,""))))))) -> - | P68: =IF($B$4="Assembly or Component Provider",DATA_RASIC!V64,IF($B$4="Consultancy Component Provider",DATA_RASIC!AC64,IF($B$4="Make to Print",DATA_RASIC!AJ64,IF($B$4="Engineering Service Provider",DATA_RASIC!H64,IF($B$4="Full System Provider",DATA_RASIC!O64,IF($B$4="ESP_DOOR TRIM",DATA_RASIC!AQ64,IF($B$4="ESP_Partner_LEVEL_01",DATA_RASIC!AX64,""))))))) -> -
